Workbook
Name add: [1]Dropdownlist!$Y$2:$Y$3
Name ag: info!$H$2:$H$6
Name age_group: [2]datavalidation!$K$2:$K$7
Name Agegp: [1]Dropdownlist!$Q$2:$Q$7
Name bawlake: Location!$I$2:$I$10
Name Beneficiary: #REF!
Name cash_org: [3]Dropdownlist!$A$12:$A$20
Name CD_orgname: #REF!
Name CD_orgname: #REF!
Name CD_orgname: #REF!
Name CD_orgname: [4]Dropdownlist!$A$10:$A$12
Name Comments: #REF!
Name communityEH: #REF!
Name communityEH: #REF!
Name communityEH: #REF!
Name communityEH: [4]Dropdownlist!$A$123:$A$128
Name constructionfacilities: #REF!
Name covid: [5]Dropdown!$D$3:$D$6
Name covid: [6]Dropdown!$D$3:$D$6
Name CSO: [7]Info!$P$2:$P$22
Name Cut_off_score: #REF!
Name del: [1]Dropdownlist!$P$2:$P$5
Name Delivery: [5]Dropdown!$T$3:$T$6
Name Delivery: [6]Dropdown!$T$3:$T$6
Name demoso: Location!$I$11:$I$36
Name dsfsafa: #REF!
Name eawfa: #REF!
Name ECC: Table4[ECC]
Name EmOC: Data_validation!$R$2:$R$93
Name ess: Location!$B$16:$B$30
Name ethnicity: [2]datavalidation!$M$2:$M$8
Name ethnicity: [6]Dropdown!$G$3:$G$9
Name ethnicity: [6]Dropdown!$G$3:$G$9
Name ethnicity: Data_validation!$I$2:$I$15
Name event1: [7]list!$H$3:$H$6
Name EXIT: #REF!
Name Exit_reason: #REF!
Name Exit_reasons: #REF!
Name facility_type: Data_validation!$G$2:$G$3
Name familytype: #REF!
Name fb: [1]Dropdownlist!$X$2:$X$5
Name Formula_start: #REF!
Name fp_method: Data_validation!$N$2:$N$10
Name health_org: Data_validation!$C$2:$C$7
Name HH_type: #REF!
Name HH_type: #REF!
Name HH_type: #REF!
Name HH_type: [4]Dropdownlist!$A$15:$A$18
Name ho_tawng_ho_tao: Location!$I$141:$I$145
Name hopong: Location!$I$365:$I$386
Name hospital_type: [2]datavalidation!$O$2:$O$4
Name how: [2]datavalidation!$AK$2:$AK$11
Name how: [6]Dropdown!$V$2:$V$9
Name hpasawng: Location!$I$37:$I$44
Name hpruso: Location!$I$45:$I$58
Name hrp: [8]info!$P$2:$P$10
Name hrp: [8]info!$P$2:$P$10
Name hrp: [8]info!$P$2:$P$10
Name hrp: Data_validation!$K$2:$K$10
Name hsihseng: Location!$I$387:$I$399

Sheet info
A1: Township | B1: Village/Camp Name | C1: Type | F1: Tsp | H1: Age Group | K1: Subcat | M1: Subcat | N1: Disease's Category | P1: HighRiskPregnancy | R1: Matrix | T1: Nutrition | V1: Type of Disability | X1: Subcat | Y1: Disease's Category | Z1: Consultation Type | AA1: Consultation Type_revised
A2: Kyauktaw | B2: COC | C2: IDP | F2: Kyauktaw | H2: <10 yrs | I2: a | K2: Abdominal pain in pregnancy | M2: Pneumonia | N2: Pneumonia | P2: Short Stature | R2: Q12023 | T2: Normal | V2: Disability of seeing | X2: Abdominal pain in pregnancy | Y2: Obstetric problem | Z2: Reproductive Health | AA2: Reproductive Health
A3: Kyauktaw | B3: Man Kyaung | C3: IDP | F3: MraukU | H3: 10 - 19 yrs | I3: b | K3: Abscess | M3: Severe pneumonia | N3: Pneumonia | P3: Extreme age | R3: Q22023 | T3: -1SD | V3: Disability of hearing | X3: Abscess | Y3: Accident/minor sugical and injuries | Z3: Communicable disease | AA3: Communicable disease
A4: Kyauktaw | B4: Thar Ta Na Bate Man | C4: IDP | F4: Myebon | H4: 20 - 24 yrs | I4: c | K4: Acute cystitis | M4: Very severe pneumonia | N4: Pneumonia | P4: Teenage pregnancy | R4: Q32023 | T4: -2SD | V4: Disability of self care | X4: Accident/minor sugical and injuries | Y4: Accident/minor sugical and injuries | Z4: Injury related | AA4: Injury related
A5: Kyauktaw | B5: Kan Sauk Monestery | C5: IDP | H5: 25 - 49 yrs | I5: d | K5: Acute diarrhoea | M5: Upper Respiratory tract infection | N5: ARI/RTI | P5: Underlying Disease | R5: Q42023 | T5: -3SD | V5: Disability of walking | X5: Acute cystitis | Y5: Genito-urinary diseases | Z5: Non-communicable disease | AA5: Other
A6: Kyauktaw | B6: Thain Pyin Kyaung | C6: IDP | H6: 50 yrs + | I6: e | K6: Acute Pharyngitis | M6: Lower Respiratory tract infection | N6: ARI/RTI | P6: Grand Multipara | V6: Disability of communication | X6: Acute diarrhoea | Y6: Diarrhoea/ GE | Z6: Communicable disease | AA6: Communicable disease
A7: Kyauktaw | B7: Shan Ywar | C7: IDP | K7: Acute prostatitis | M7: Otitis | N7: ARI/RTI | P7: Previous LSCS Scar | V7: Disability with remembering | X7: Acute Pharyngitis | Y7: ARI/RTI | Z7: Communicable disease | AA7: Communicable disease
A8: Kyauktaw | B8: Thain Kyaung | C8: IDP | K8: Acute pyelonephritis | M8: Whooping cough (pertussis) | N8: ARI/RTI | P8: Twin Pregnancy | X8: Acute prostatitis | Y8: Genito-urinary diseases | Z8: Non-communicable disease | AA8: Non-communicable disease
A9: Kyauktaw | B9: Town Hall | C9: IDP | K9: Acute Severe asthma | M9: Bronchitis | N9: ARI/RTI | P9: Antepartum Hemorrhage | X9: Acute pyelonephritis | Y9: Genito-urinary diseases | Z9: Non-communicable disease | AA9: Non-communicable disease
A10: Kyauktaw | B10: Bu Dar | C10: IDP | F10: Extremely dissatisfied | H10: Recovered | K10: Acute sinusitis | M10: Bronchiolitis | N10: ARI/RTI | P10: Pre-eclampsia | X10: Acute Severe asthma | Y10: Asthma | Z10: Non-communicable disease | AA10: Non-communicable disease
A11: Kyauktaw | B11: Shwe Kyaung | C11: IDP | F11: Dissatisfied | H11: Improved but not recovered | K11: Acute upper airway obstruction | M11: Acute sinusitis | N11: ARI/RTI | X11: Acute sinusitis | Y11: ARI/RTI | Z11: Communicable disease | AA11: Communicable disease
A12: Kyauktaw | B12: Kan Gyee Shin | C12: IDP | F12: Partially satisfied | H12: Same condition | K12: Agitation | M12: Acute Pharyngitis | N12: ARI/RTI | X12: Acute upper airway obstruction | Y12: ARI/RTI | Z12: Communicable disease | AA12: Communicable disease
A13: Kyauktaw | B13: Nay Pu Khan | C13: IDP | F13: Satisfied | H13: Worse | K13: Allergic reaction | M13: Acute upper airway obstruction | N13: ARI/RTI | X13: Agitation | Y13: Mental disorders | Z13: mental health condition | AA13: mental health condition
A14: Kyauktaw | B14: Ka Wi Yadanar | C14: IDP | F14: Extremely Satisfied | H14: Ongoing/chronic problem | K14: Amenorrhoea | M14: Bronchitis | N14: ARI/RTI | X14: Allergic reaction | Y14: Skin infection/disease | Z14: Non-communicable disease | AA14: Non-communicable disease
A15: Kyauktaw | B15: Ma Har Mu Ni | C15: IDP | H15: Unsure | K15: Anaemia | M15: Bronchiolitis | N15: ARI/RTI | X15: Amenorrhoea | Y15: Gynecological problem | Z15: Reproductive Health | AA15: Reproductive Health
A16: Kyauktaw | B16: Nyaung Chaung | C16: IDP | K16: Animal/Insect bite | M16: Chest infection | N16: ARI/RTI | X16: Anaemia | Y16: Hematological disorder | Z16: Non-communicable disease | AA16: Non-communicable disease
A17: Kyauktaw | B17: Taung Min | C17: IDP | K17: Anxiety | M17: Common cold | N17: ARI/RTI | X17: Animal/Insect bite | Y17: Accident/minor sugical and injuries | Z17: Injury related | AA17: Injury related
A18: Kyauktaw | B18: War Taung | C18: IDP | F18: Very satisfied | H18: Yes, totally | K18: Arthalgia | M18: Flu with high fever | N18: ARI/RTI | X18: Anxiety | Y18: Mental disorders | Z18: mental health condition | AA18: mental health condition
A19: Kyauktaw | B19: Taung Pauk Monestery | C19: Rakhine Village | F19: Satisfied | H19: Yes, partially | K19: Asthma | M19: Respiratory viral infection | N19: ARI/RTI | X19: ARI/RTI | Y19: ARI/RTI | Z19: Communicable disease | AA19: Communicable disease
A20: Kyauktaw | B20: Hpa Yar Paung Monestery | C20: Rakhine Village | F20: Dissatisfied | H20: Not at all | K20: Back pain in pregnancy | M20: Tonsillar abscess | N20: ARI/RTI | X20: Arthalgia | Y20: Other (non-communicable) | Z20: Non-communicable disease | AA20: Non-communicable disease
A21: MraukU | B21: Pu Zun Hpe | C21: Rakhine Village | F21: Very dissatisfied | H21: Unsure | K21: Bacteria skin infection | M21: Tuberculosis | N21: ARI/RTI | X21: Asthma | Y21: Asthma | Z21: Non-communicable disease | AA21: Non-communicable disease
A22: MraukU | B22: Pi Pin Yin | C22: Rakhine Village | H22: Don’t know | K22: Bacterial vaginosis | M22: Pulmonary TB-suspect | N22: ARI/RTI | X22: Back pain in pregnancy | Y22: Obstetric problem | Z22: Reproductive Health | AA22: Reproductive Health
A23: MraukU | B23: Tein Nyo | C23: Rakhine Village | K23: Beri Beri | M23: Asthma | N23: Asthma | X23: Bacteria disease | Y23: Bacteria disease | Z23: Communicable disease | AA23: Communicable disease
A24: MraukU | B24: Tin Htein Kan | C24: Muslim Village | K24: Bleeding during pregnancy | M24: Acute Severe asthma | N24: Asthma | X24: Bacteria skin infection | Y24: Skin infection/disease | Z24: Communicable disease | AA24: Communicable disease
A25: MraukU | B25: Ywar Thit Kay | C25: Muslim Village | K25: Bronchiolitis | M25: Chronic Asthma | N25: Asthma | X25: Bacterial vaginosis | Y25: STI | Z25: Communicable disease | AA25: Communicable disease
A26: MraukU | B26: Pya Hla | K26: Bronchiolitis | M26: Dengue haemorrhagic fever | N26: DHF | X26: Beri Beri | Y26: Beri Beri | Z26: Non-communicable disease | AA26: Non-communicable disease
A27: MraukU | B27: Na Kan | K27: Bronchitis | M27: DHF suspect | N27: DHF | X27: Bleeding during pregnancy | Y27: Obstetric problem | Z27: Reproductive Health | AA27: Reproductive Health
A28: MraukU | B28: Ku Lar Chaung | K28: Bronchitis | M28: Dengue shock | N28: DHF | X28: Bronchiolitis | Y28: ARI/RTI | Z28: Communicable disease | AA28: Communicable disease
A29: MraukU | B29: Wet Hla | K29: Burns/wounds | M29: Acute diarrhoea | N29: Diarrhoea/ GE | X29: Bronchitis | Y29: ARI/RTI | Z29: Communicable disease | AA29: Communicable disease
A30: MraukU | B30: Taung Myint | K30: Cataract | M30: Severe dehydration with diarrhoea | N30: Diarrhoea/ GE | X30: Burns/wounds | Y30: Accident/minor sugical and injuries | Z30: Injury related | AA30: Injury related
A31: Myebon | B31: Kyee Gaung Taung | K31: Cerebral soft tissue infection | M31: Dehydration with diarrhoea | N31: Diarrhoea/ GE | X31: Cataract | Y31: Eye problem/disease | Z31: Non-communicable disease | AA31: Non-communicable disease
A32: Myebon | B32: Taung Gyi Yin | K32: Cervicitis | M32: Dysentery | N32: Dysentery | X32: Cerebral soft tissue infection | Y32: Meningitis and encephalitis | Z32: Communicable disease | AA32: Communicable disease
A33: Myebon | B33: Yae Shin | K33: Chest infection | M33: Beri Beri | N33: Beri Beri | X33: Cervicitis | Y33: Gynecological problem | Z33: Reproductive Health | AA33: Reproductive Health
A34: Myebon | B34: Ah Ngu Yaw Thit | K34: Chicken Pox | M34: Malnutrition | N34: Malnutrition | X34: Chest infection | Y34: ARI/RTI | Z34: Communicable disease | AA34: Communicable disease
A35: Myebon | B35: Yet Chaung | K35: Chlamydia | M35: Severe malnutrition | N35: Malnutrition | X35: Chicken Pox | Y35: Viral diseases | Z35: Communicable disease | AA35: Communicable disease
A36: Myebon | B36: Pya Thone | K36: Chronic Asthma | M36: Protein energy malnutrition | N36: Malnutrition | X36: Chlamydia | Y36: STI | Z36: Communicable disease | AA36: Communicable disease
A37: Myebon | B37: Pin Kat Taung Maw | K37: Colitis | M37: Stomatitis | N37: Malnutrition | X37: Chronic Asthma | Y37: Asthma | Z37: Non-communicable disease | AA37: Non-communicable disease
... A42: Myebon | B42: Taung Paw Camp | K42: Congenital heart disease | M42: DM | N42: Chronic medical disease | X42: Congenital abnormalities | Y42: Congenital abnormalities | Z42: Non-communicable disease | AA42: Non-communicable disease
K43: Congenital infection | M43: Hypertension | N43: Chronic medical disease | X43: Congenital abnormalities/deformities | Y43: Neonatal problem | Z43: Non-communicable disease | AA43: Non-communicable disease
K44: Conjunctivitis | M44: Heart disease | N44: Chronic medical disease | X44: Congenital deformaties | Y44: Congenital abnormalities | Z44: Non-communicable disease | AA44: Non-communicable disease
K45: Constipation | M45: Renal disease | N45: Chronic medical disease | X45: Congenital heart disease | Y45: Congenital abnormalities | Z45: Non-communicable disease | AA45: Non-communicable disease
K46: COPD | M46: COPD | N46: Chronic medical disease | X46: Congenital infection | Y46: Neonatal problem | Z46: Communicable disease | AA46: Communicable disease
K47: Dehydration with diarrhoea | M47: HIV/AIDS | N47: Chronic medical disease | X47: Conjunctivitis | Y47: Eye problem/disease | Z47: Communicable disease | AA47: Communicable disease
K48: Delay milestones | M48: Hematological diseases | N48: Hematological disorder | X48: Constipation | Y48: GI problem | Z48: Non-communicable disease | AA48: Other
K49: Dengue | M49: Thalassemia with severe anamia | N49: Hematological disorder | X49: COPD | Y49: Chronic medical disease | Z49: Non-communicable disease | AA49: Non-communicable disease
K50: Dengue haemorrhagic fever | M50: Anaemia | N50: Hematological disorder | X50: Dehydration with diarrhoea | Y50: Diarrhoea/ GE | Z50: Communicable disease | AA50: Communicable disease
K51: Dengue shock | M51: Fungal infection | N51: Skin infection/disease | X51: Delay milestones | Y51: Congenital abnormalities | Z51: Non-communicable disease | AA51: Non-communicable disease
K52: Dental infections | M52: Other skin disorders | N52: Skin infection/disease | X52: Dengue | Y52: Viral diseases | Z52: Communicable disease | AA52: Communicable disease
K53: Depression | M53: Allergic reaction | N53: Skin infection/disease | X53: Dengue haemorrhagic fever | Y53: DHF | Z53: Communicable disease | AA53: Communicable disease
K54: DHF suspect | M54: Eczema | N54: Skin infection/disease | X54: Dengue shock | Y54: DHF | Z54: Communicable disease | AA54: Communicable disease
... K159: Very severe pneumonia | M159: Constipation | N159: GI problem | X159: Skin infection/disease | Y159: Skin infection/disease | Z159: Communicable disease | AA159: Communicable disease
K160: Viral haemorrhagic fevers | M160: Dysnonea | N160: Other | X160: Stab wound | Z160: Injury related | AA160: Injury related
K161: Viral hepatitis | M161: Hepatitis | N161: Hepatic Problem | X161: STI | Y161: STI | Z161: Communicable disease | AA161: Communicable disease
K162: Vomitting in pregnancy | M162: Arthalgia | N162: Other | X162: Stomach cramps in pregnancy | Y162: Obstetric problem | Z162: Reproductive Health | AA162: Reproductive Health
K163: Weakness | M163: Neuralgia | N163: Other | X163: Stomatitis | Y163: Malnutrition | Z163: Non-communicable disease | AA163: Non-communicable disease
K164: White discharge | M164: Headache | N164: Other | X164: Stroke | Y164: Stroke | Z164: Non-communicable disease | AA164: Non-communicable disease
K165: Whooping cough (pertussis) | M165: Fits/Epilepsy | N165: Neurological Problem | X165: Surgical Disease | Y165: Surgical Disease | Z165: Non-communicable disease | AA165: Non-communicable disease
K166: Worm infestation | M166: Pile | N166: Surgical Disease | X166: Suspected pregnancy | Y166: Obstetric problem | Z166: Reproductive Health | AA166: Reproductive Health
K167: Xerophthalmia (vitamin A deficiency) | M167: Cervicitis | N167: Gynecological problem | X167: Swelling of hands/face/feet | Y167: Obstetric problem | Z167: Reproductive Health | AA167: Reproductive Health
X168: Syphilis | Y168: STI | Z168: Communicable disease | AA168: Communicable disease
X169: Tetanus | Y169: Bacteria disease | Z169: Communicable disease | AA169: Communicable disease
X170: Thalassemia with severe anamia | Y170: Hematological disorder | Z170: Non-communicable disease | AA170: Non-communicable disease
X171: Tonsillar abscess | Y171: ARI/RTI | Z171: Communicable disease | AA171: Communicable disease
X172: Trachoma | Y172: Eye problem/disease | Z172: Communicable disease | AA172: Communicable disease
X173: Trichomoniasis | Y173: STI | Z173: Communicable disease | AA173: Communicable disease
X174: Tuberculosis | Y174: ARI/RTI | Z174: Communicable disease | AA174: Communicable disease
X175: Umbilical cord infection/sepsis | Y175: Neonatal problem | Z175: Communicable disease | AA175: Communicable disease
X176: Upper Respiratory tract infection | Y176: ARI/RTI | Z176: Communicable disease | AA176: Communicable disease
X177: Urinary incontinence | Y177: Genito-urinary diseases | Z177: Non-communicable disease | AA177: Non-communicable disease
X178: Urolithiasis | Y178: Genito-urinary diseases | Z178: Non-communicable disease | AA178: Non-communicable disease
X179: UTI | Y179: Genito-urinary diseases | Z179: Communicable disease | AA179: Communicable disease
... X192: Sexual violence related case | Y192: Sexual violence | Z192: Sexual violence | AA192: Sexual violence

Sheet Def
A1: Sr No | B1: Item Name | C1: Operation Defination
A2: 1 | B2: New consultation | C2: 1.An individual who is seen for a first time at the Mobile Clinic 2.patient not previously seen in past 30 days (starting 1 January 2017) or seen for a new condition (confirm with patient record book) 3.For chronic cases, who is seen for first time at Mobile Clinic And/or acutely new attack or condition due to chronic background stage will be new case.
A3: 2 | B3: Follow up consultation | C3: Follow up consultation means to the same patient who present/ complaint with the same symptom(s) and/or come back to the clinic to re-check disease in the willingness of the patient or MD’s follow up appointment.
A4: 3 | B4: Age | C4: Age refers to completed age of the client (Year/month/day) If the client is under 1 month please describe completed days If the client is under 1 year please describe completed month
A5: 4 | B5: ANC 1 | C5: ANC-1 means antenatal care taken by pregant woman within first 12th to 14th weeks of gestation
A6: 5 | B6: ANC 2 | C6: ANC-2 means antenatal care taken by pregant woman within 15th to 28th week of gestation
A7: 6 | B7: ANC 3 | C7: ANC-3 means antenatal care taken by pregant woman within 29th to 34th week of gestation
A8: 7 | B8: ANC 4 | C8: ANC-4 means antenatal care taken by pregant woman after 34th week of gestation
A9: 8 | B9: TT 1 | C9: TT 1 means first dose of tetanus toxoid vaccine is given to the pregnant woman
A10: 9 | B10: TT 2 | C10: TT 2 means second dose of tetanus toxoid vaccine is given to the same pregnant woman
A11: 10 | B11: PNC 1 | C11: PNC-1 (within 48 hrs)
A12: 11 | B12: PNC 2 | C12: PNC-2 (After 48 hrs after Delivery)
A13: 14 | B13: new acceptor (Family planning) | C13: 1. woman who never used any modern FP method before 2. woman who change from one method to other method which wasn't used before 3. woman used some modern FP method previously and she used the same method again after 6 months later
... A16: 17 | B16: Moderate Acute Malnutrition | C16: 11.5 to 12.5 cm(MUAC) (Yellow)
B17: *Disease category is according to MSF guideline 2018 and the list is as follow
B18: Pneumonia | C18: Pneumonia
C19: Severe pneumonia
C20: Severe pneumonia
B21: ARI/RTI | C21: Upper Respiratory tract infection
C22: Lower Respiratory tract infection
C23: Otitis
C24: Whooping cough (pertussis)
C25: Bronchitis
C26: Bronchiolitis
C27: Acute sinusitis
C28: Acute pharyngitis
C29: Acute upper airway obstruction
C30: Bronchitis
C31: Bronchiolitis
C32: Chest infection
C33: Common cold
... C38: Pulmonary TB-suspect
B39: Asthma | C39: Asthma
C40: Acute Severe asthma
C41: Chronic Asthma
B42: DHF | C42: Dengue haemorrhagic fever
C43: DHF suspect
C44: Dengue shock
B45: Diarrhoea/ GE | C45: Acute Diarrhoea
C46: Severe dehydration with diarrhoea
C47: Dehydration with diarrhoea
B48: Dysentery | C48: Dysentery
B49: Beri Beri | C49: Beri Beri
B50: Malnutrition | C50: Malnutrition
C51: Severe malnutrition
C52: Protein energy malnutrition
C53: Stomatitis
B54: Meningitis and encephalitis | C54: Meningitis
C55: Encephalitis
C56: Cerebral soft tissue infection
C57: Pneumococcal meningitis
B58: Chronic medical disease | C58: DM
C59: Hypertension
C60: Heart disease
C61: Renal disease
C62: COPD
C63: HIV/AIDS
B64: Hematological disorder | C64: Hematological diseases
C65: Thalassemia with severe anamia
C66: Anaemia
B67: Skin infection/disease | C67: Fungal infection
C68: Other skin disorders
C69: Allergic reaction
C70: Eczema
C71: Pruritis
C72: Bacteria skin infection
C73: Scabies infection
C74: Ring worm
C75: Herpes simplex and herpes zoster
B76: Eye problem/disease | C76: Conjunctivitis
C77: Cataract
C78: Glaucoma
C79: other vision problem
C80: Xerophthalmia (vitamin A deficiency)
C81: Trachoma
C82: other eye problem
B83: Genito-urinary diseases | C83: UTI
C84: Nephrotic syndrome in children
C85: Urinary incontinence
C86: Urolithiasis
C87: Acute cystitis
C88: Acute pyelonephritis
C89: Acute prostatitis
B90: Ear problem/disease | C90: Otitis media
C91: Otitis externa
C92: Otitis abscess
C93: Ear conal blockage
B94: Parasitic disease | C94: Worm infestation
C95: Malaria/ cerebral malaria
C96: Schistosomiases
C97: Filariasis
C98: other parasitic infection
B99: Accident/minor sugical and injuries | C99: Burns/wounds
C100: Injuries
C101: Fracture
C102: Abscess
C103: Scald
C104: Periorbital and orbital cellulitis
C105: Animal/Insect bite
C106: food poisoning
...

Sheet PHC
A1: PHC Database
A2: Sr.No | B2: Fund | C2: Implementing Organization Name | D2: Health Post / Clinic | E2: State | F2: Township | G2: Village Tract | H2: Place | I2: Type of place (Camp/Village/Ward) | J2: Name of Medical Person | K2: Date of Consultation (mm/dd/yy) | L2: Register No. | M2: Register.Code | N2: New/ Follow up | O2: Name of patient | P2: Age_yr | Q2: Age_mth | R2: Age_day | S2: Age_Group | T2: Sex | U2: Address (if not the same with Moblile Clinic location) | V2: Father Name | W2: Diagnosis | X2: Sub_Category | Y2: Category | Z2: Consultation Type | AA2: Treatment | AB2: eligible to receive PEP? | AC2: Receive PEP within 72 hours | AD2: Disability | AE2: Refered or Not | AF2: Referral Date | AG2: Cause of referral | AH2: Name of Referred Place | AI2: Type of Referred Facility | AJ2: Follow-up Date | AK2: Teleconsultation | AL2: Remarks | AM2: referral | AN2: PEP
A3: 1 | B3: BHA | C3: Shining Star | D3: Mobile Clinic | E3: Mandalay | F3: Amarapura | H3: Myit Too | I3: Village | K3: 46037 | L3: 1 | M3: =IF(phc_8[[#This Row],[Register No.]]="","",C3&"-"&D3&"-"&"BHA-PHC-"&phc_8[[#This Row],[Register No.]]) -> Shining Star-Mobile Clinic-BHA-PHC-1 | N3: New | O3: Daw Khin Hla | P3: 80 | S3: =IF(AND(ISBLANK(P3),ISBLANK(Q3),ISBLANK(R3))," ", IF(OR(P3<5,AND(P3=" ",Q3<>" ",R3<>" ")),"<5 yrs", IF(AND(P3>=5,P3<=14),"5 - 14 yrs", IF(AND(P3>=15,P3<=18),"15 - 18 yrs", IF(AND(P3>=19,P3<=49),"19 - 49 yrs","50 yrs +"))))) -> 50 yrs + | T3: Female | U3: Myit Too | V3: U Kyu | W3: HT | X3: Hypertension | Y3: =INDEX(info!$Y$2:$Y$192,MATCH(phc_8[[#This Row],[Sub_Category]],info!$X$2:$X$192,0)) -> Chronic medical disease | Z3: {=INDEX(info!$AA$2:$AA$192,MATCH(PHC!$X3&PHC!$Y3,info!$X$2:$X$192&info!$Y$2:$Y$192,0))} -> Non-communicable disease | AA3: Amlo5, MV, Betex | AB3: No | AC3: No | AD3: No | AE3: No | AK3: No | AM3: =IF(AF3="","","Q"&INT((MONTH(AF3)-1)/3)+1&YEAR(AF3)&#REF!&T3) | AN3: =IF(K3="","","Q"&INT((MONTH(K3)-1)/3)+1&YEAR(K3)&#REF!) -> #REF!
A4: 2 | B4: BHA | C4: Shining Star | D4: Mobile Clinic | E4: Mandalay | F4: Amarapura | H4: Myit Too | I4: Village | K4: 46037 | L4: 2 | M4: =IF(phc_8[[#This Row],[Register No.]]="","",C4&"-"&D4&"-"&"BHA-PHC-"&phc_8[[#This Row],[Register No.]]) -> Shining Star-Mobile Clinic-BHA-PHC-2 | N4: New | O4: Daw Khin Yee | P4: 89 | S4: =IF(AND(ISBLANK(P4),ISBLANK(Q4),ISBLANK(R4))," ", IF(OR(P4<5,AND(P4=" ",Q4<>" ",R4<>" ")),"<5 yrs", IF(AND(P4>=5,P4<=14),"5 - 14 yrs", IF(AND(P4>=15,P4<=18),"15 - 18 yrs", IF(AND(P4>=19,P4<=49),"19 - 49 yrs","50 yrs +"))))) -> 50 yrs + | T4: Female | U4: Myit Too | V4: U Thi Hla | W4: HT | X4: Hypertension | Y4: =INDEX(info!$Y$2:$Y$192,MATCH(phc_8[[#This Row],[Sub_Category]],info!$X$2:$X$192,0)) -> Chronic medical disease | Z4: {=INDEX(info!$AA$2:$AA$192,MATCH(PHC!$X4&PHC!$Y4,info!$X$2:$X$192&info!$Y$2:$Y$192,0))} -> Non-communicable disease | AA4: IV25%+VitC, Amlo5, Para, MV, VitC | AB4: No | AC4: No | AD4: No | AE4: No | AK4: No | AM4: =IF(AF4="","","Q"&INT((MONTH(AF4)-1)/3)+1&YEAR(AF4)&#REF!&T4) | AN4: =IF(K4="","","Q"&INT((MONTH(K4)-1)/3)+1&YEAR(K4)&#REF!) -> #REF!
A5: 3 | B5: BHA | C5: Shining Star | D5: Mobile Clinic | E5: Mandalay | F5: Amarapura | H5: Myit Too | I5: Village | K5: 46037 | L5: 3 | M5: =IF(phc_8[[#This Row],[Register No.]]="","",C5&"-"&D5&"-"&"BHA-PHC-"&phc_8[[#This Row],[Register No.]]) -> Shining Star-Mobile Clinic-BHA-PHC-3 | N5: New | O5: Daw Mya Aye | P5: 63 | S5: =IF(AND(ISBLANK(P5),ISBLANK(Q5),ISBLANK(R5))," ", IF(OR(P5<5,AND(P5=" ",Q5<>" ",R5<>" ")),"<5 yrs", IF(AND(P5>=5,P5<=14),"5 - 14 yrs", IF(AND(P5>=15,P5<=18),"15 - 18 yrs", IF(AND(P5>=19,P5<=49),"19 - 49 yrs","50 yrs +"))))) -> 50 yrs + | T5: Female | U5: Myit Too | V5: U Kho | W5: Skin Allergy | X5: Weakness | Y5: =INDEX(info!$Y$2:$Y$192,MATCH(phc_8[[#This Row],[Sub_Category]],info!$X$2:$X$192,0)) -> Other (non-communicable) | Z5: {=INDEX(info!$AA$2:$AA$192,MATCH(PHC!$X5&PHC!$Y5,info!$X$2:$X$192&info!$Y$2:$Y$192,0))} -> Other | AA5: IV B'ton, B'ton, Ranitadine, Ibu, Caladyl Lotion | AB5: No | AC5: No | AD5: No | AE5: No | AK5: No | AM5: =IF(AF5="","","Q"&INT((MONTH(AF5)-1)/3)+1&YEAR(AF5)&#REF!&T5) | AN5: =IF(K5="","","Q"&INT((MONTH(K5)-1)/3)+1&YEAR(K5)&#REF!) -> #REF!
A6: 4 | B6: BHA | C6: Shining Star | D6: Mobile Clinic | E6: Mandalay | F6: Amarapura | H6: Myit Too | I6: Village | K6: 46037 | L6: 4 | M6: =IF(phc_8[[#This Row],[Register No.]]="","",C6&"-"&D6&"-"&"BHA-PHC-"&phc_8[[#This Row],[Register No.]]) -> Shining Star-Mobile Clinic-BHA-PHC-4 | N6: New | O6: Daw Nu Nu Yee | P6: 73 | S6: =IF(AND(ISBLANK(P6),ISBLANK(Q6),ISBLANK(R6))," ", IF(OR(P6<5,AND(P6=" ",Q6<>" ",R6<>" ")),"<5 yrs", IF(AND(P6>=5,P6<=14),"5 - 14 yrs", IF(AND(P6>=15,P6<=18),"15 - 18 yrs", IF(AND(P6>=19,P6<=49),"19 - 49 yrs","50 yrs +"))))) -> 50 yrs + | T6: Female | U6: Myit Too | V6: U Kan Oo | W6: Muscle Pain | X6: Muscle Pain | Y6: =INDEX(info!$Y$2:$Y$192,MATCH(phc_8[[#This Row],[Sub_Category]],info!$X$2:$X$192,0)) -> Other (non-communicable) | Z6: {=INDEX(info!$AA$2:$AA$192,MATCH(PHC!$X6&PHC!$Y6,info!$X$2:$X$192&info!$Y$2:$Y$192,0))} -> Other | AA6: IV B12, Gabapentin, Betex, Ca+ | AB6: No | AC6: No | AD6: No | AE6: No | AK6: No | AM6: =IF(AF6="","","Q"&INT((MONTH(AF6)-1)/3)+1&YEAR(AF6)&#REF!&T6) | AN6: =IF(K6="","","Q"&INT((MONTH(K6)-1)/3)+1&YEAR(K6)&#REF!) -> #REF!
A7: 5 | B7: BHA | C7: Shining Star | D7: Mobile Clinic | E7: Mandalay | F7: Amarapura | H7: Myit Too | I7: Village | K7: 46037 | L7: 5 | M7: =IF(phc_8[[#This Row],[Register No.]]="","",C7&"-"&D7&"-"&"BHA-PHC-"&phc_8[[#This Row],[Register No.]]) -> Shining Star-Mobile Clinic-BHA-PHC-5 | N7: New | O7: Daw Kyu Kyu San | P7: 50 | S7: =IF(AND(ISBLANK(P7),ISBLANK(Q7),ISBLANK(R7))," ", IF(OR(P7<5,AND(P7=" ",Q7<>" ",R7<>" ")),"<5 yrs", IF(AND(P7>=5,P7<=14),"5 - 14 yrs", IF(AND(P7>=15,P7<=18),"15 - 18 yrs", IF(AND(P7>=19,P7<=49),"19 - 49 yrs","50 yrs +"))))) -> 50 yrs + | T7: Female | U7: Myit Too | V7: U Kyi | W7: HT | X7: Hypertension | Y7: =INDEX(info!$Y$2:$Y$192,MATCH(phc_8[[#This Row],[Sub_Category]],info!$X$2:$X$192,0)) -> Chronic medical disease | Z7: {=INDEX(info!$AA$2:$AA$192,MATCH(PHC!$X7&PHC!$Y7,info!$X$2:$X$192&info!$Y$2:$Y$192,0))} -> Non-communicable disease | AA7: IV Pantocid, Amlo5, Pantocid, Zinc, Air X | AB7: No | AC7: No | AD7: No | AE7: No | AK7: No | AM7: =IF(AF7="","","Q"&INT((MONTH(AF7)-1)/3)+1&YEAR(AF7)&#REF!&T7) | AN7: =IF(K7="","","Q"&INT((MONTH(K7)-1)/3)+1&YEAR(K7)&#REF!) -> #REF!
A8: 6 | B8: BHA | C8: Shining Star | D8: Mobile Clinic | E8: Mandalay | F8: Amarapura | H8: Myit Too | I8: Village | K8: 46037 | L8: 6 | M8: =IF(phc_8[[#This Row],[Register No.]]="","",C8&"-"&D8&"-"&"BHA-PHC-"&phc_8[[#This Row],[Register No.]]) -> Shining Star-Mobile Clinic-BHA-PHC-6 | N8: New | O8: Daw Aye Yee | P8: 78 | S8: =IF(AND(ISBLANK(P8),ISBLANK(Q8),ISBLANK(R8))," ", IF(OR(P8<5,AND(P8=" ",Q8<>" ",R8<>" ")),"<5 yrs", IF(AND(P8>=5,P8<=14),"5 - 14 yrs", IF(AND(P8>=15,P8<=18),"15 - 18 yrs", IF(AND(P8>=19,P8<=49),"19 - 49 yrs","50 yrs +"))))) -> 50 yrs + | T8: Female | U8: Myit Too | V8: U Kan Oo | W8: Muscle Pain | X8: Muscle Pain | Y8: =INDEX(info!$Y$2:$Y$192,MATCH(phc_8[[#This Row],[Sub_Category]],info!$X$2:$X$192,0)) -> Other (non-communicable) | Z8: {=INDEX(info!$AA$2:$AA$192,MATCH(PHC!$X8&PHC!$Y8,info!$X$2:$X$192&info!$Y$2:$Y$192,0))} -> Other | AA8: IV B12, Para, Ca+, MV | AB8: No | AC8: No | AD8: No | AE8: No | AK8: No | AM8: =IF(AF8="","","Q"&INT((MONTH(AF8)-1)/3)+1&YEAR(AF8)&#REF!&T8) | AN8: =IF(K8="","","Q"&INT((MONTH(K8)-1)/3)+1&YEAR(K8)&#REF!) -> #REF!
A9: 7 | B9: BHA | C9: Shining Star | D9: Mobile Clinic | E9: Mandalay | F9: Amarapura | H9: Myit Too | I9: Village | K9: 46037 | L9: 7 | M9: =IF(phc_8[[#This Row],[Register No.]]="","",C9&"-"&D9&"-"&"BHA-PHC-"&phc_8[[#This Row],[Register No.]]) -> Shining Star-Mobile Clinic-BHA-PHC-7 | N9: New | O9: Daw Moh Moh Thwin | P9: 49 | S9: =IF(AND(ISBLANK(P9),ISBLANK(Q9),ISBLANK(R9))," ", IF(OR(P9<5,AND(P9=" ",Q9<>" ",R9<>" ")),"<5 yrs", IF(AND(P9>=5,P9<=14),"5 - 14 yrs", IF(AND(P9>=15,P9<=18),"15 - 18 yrs", IF(AND(P9>=19,P9<=49),"19 - 49 yrs","50 yrs +"))))) -> 19 - 49 yrs | T9: Female | U9: Myit Too | V9: U Thaung Han | W9: Flu | X9: Flu with high fever | Y9: =INDEX(info!$Y$2:$Y$192,MATCH(phc_8[[#This Row],[Sub_Category]],info!$X$2:$X$192,0)) -> ARI/RTI | Z9: {=INDEX(info!$AA$2:$AA$192,MATCH(PHC!$X9&PHC!$Y9,info!$X$2:$X$192&info!$Y$2:$Y$192,0))} -> Communicable disease | AA9: Amlo5, Para, Cefixime, VitC, Betex | AB9: No | AC9: No | AD9: No | AE9: No | AK9: No | AM9: =IF(AF9="","","Q"&INT((MONTH(AF9)-1)/3)+1&YEAR(AF9)&#REF!&T9) | AN9: =IF(K9="","","Q"&INT((MONTH(K9)-1)/3)+1&YEAR(K9)&#REF!) -> #REF!
A10: 8 | B10: BHA | C10: Shining Star | D10: Mobile Clinic | E10: Mandalay | F10: Amarapura | H10: Myit Too | I10: Village | K10: 46037 | L10: 8 | M10: =IF(phc_8[[#This Row],[Register No.]]="","",C10&"-"&D10&"-"&"BHA-PHC-"&phc_8[[#This Row],[Register No.]]) -> Shining Star-Mobile Clinic-BHA-PHC-8 | N10: New | O10: Mg Han Min Khant | S10: =IF(AND(ISBLANK(P10),ISBLANK(Q10),ISBLANK(R10))," ", IF(OR(P10<5,AND(P10=" ",Q10<>" ",R10<>" ")),"<5 yrs", IF(AND(P10>=5,P10<=14),"5 - 14 yrs", IF(AND(P10>=15,P10<=18),"15 - 18 yrs", IF(AND(P10>=19,P10<=49),"19 - 49 yrs","50 yrs +"))))) | T10: Male | U10: Myit Too | V10: U Nay Khant | W10: CP | X10: Congenital abnormalities | Y10: =INDEX(info!$Y$2:$Y$192,MATCH(phc_8[[#This Row],[Sub_Category]],info!$X$2:$X$192,0)) -> Congenital abnormalities | Z10: {=INDEX(info!$AA$2:$AA$192,MATCH(PHC!$X10&PHC!$Y10,info!$X$2:$X$192&info!$Y$2:$Y$192,0))} -> Non-communicable disease | AA10: PB Vita | AB10: No | AC10: No | AD10: No | AE10: No | AK10: No | AM10: =IF(AF10="","","Q"&INT((MONTH(AF10)-1)/3)+1&YEAR(AF10)&#REF!&T10) | AN10: =IF(K10="","","Q"&INT((MONTH(K10)-1)/3)+1&YEAR(K10)&#REF!) -> #REF!
A11: 9 | B11: BHA | C11: Shining Star | D11: Mobile Clinic | E11: Mandalay | F11: Amarapura | H11: Myit Too | I11: Village | K11: 46037 | L11: 9 | M11: =IF(phc_8[[#This Row],[Register No.]]="","",C11&"-"&D11&"-"&"BHA-PHC-"&phc_8[[#This Row],[Register No.]]) -> Shining Star-Mobile Clinic-BHA-PHC-9 | N11: New | O11: U Nyay | P11: 51 | S11: =IF(AND(ISBLANK(P11),ISBLANK(Q11),ISBLANK(R11))," ", IF(OR(P11<5,AND(P11=" ",Q11<>" ",R11<>" ")),"<5 yrs", IF(AND(P11>=5,P11<=14),"5 - 14 yrs", IF(AND(P11>=15,P11<=18),"15 - 18 yrs", IF(AND(P11>=19,P11<=49),"19 - 49 yrs","50 yrs +"))))) -> 50 yrs + | T11: Male | U11: Myit Too | V11: U Aung Kyaw | W11: HT/DM | X11: Hypertension | Y11: =INDEX(info!$Y$2:$Y$192,MATCH(phc_8[[#This Row],[Sub_Category]],info!$X$2:$X$192,0)) -> Chronic medical disease | Z11: {=INDEX(info!$AA$2:$AA$192,MATCH(PHC!$X11&PHC!$Y11,info!$X$2:$X$192&info!$Y$2:$Y$192,0))} -> Non-communicable disease | AA11: Amlo5, MV, Cifram Eye Drop | AB11: No | AC11: No | AD11: No | AE11: No | AK11: No | AM11: =IF(AF11="","","Q"&INT((MONTH(AF11)-1)/3)+1&YEAR(AF11)&#REF!&T11) | AN11: =IF(K11="","","Q"&INT((MONTH(K11)-1)/3)+1&YEAR(K11)&#REF!) -> #REF!
A12: 10 | B12: BHA | C12: Shining Star | D12: Mobile Clinic | E12: Mandalay | F12: Amarapura | H12: Myit Too | I12: Village | K12: 46037 | L12: 10 | M12: =IF(phc_8[[#This Row],[Register No.]]="","",C12&"-"&D12&"-"&"BHA-PHC-"&phc_8[[#This Row],[Register No.]]) -> Shining Star-Mobile Clinic-BHA-PHC-10 | N12: New | O12: Daw San San Myint | P12: 65 | S12: =IF(AND(ISBLANK(P12),ISBLANK(Q12),ISBLANK(R12))," ", IF(OR(P12<5,AND(P12=" ",Q12<>" ",R12<>" ")),"<5 yrs", IF(AND(P12>=5,P12<=14),"5 - 14 yrs", IF(AND(P12>=15,P12<=18),"15 - 18 yrs", IF(AND(P12>=19,P12<=49),"19 - 49 yrs","50 yrs +"))))) -> 50 yrs + | T12: Female | U12: Myit Too | V12: U Tin Aung | W12: HT | X12: Hypertension | Y12: =INDEX(info!$Y$2:$Y$192,MATCH(phc_8[[#This Row],[Sub_Category]],info!$X$2:$X$192,0)) -> Chronic medical disease | Z12: {=INDEX(info!$AA$2:$AA$192,MATCH(PHC!$X12&PHC!$Y12,info!$X$2:$X$192&info!$Y$2:$Y$192,0))} -> Non-communicable disease | AA12: IV Hydrocortisone, Dextro, Salbutamol, Gabapentin, Nifedapine | AB12: No | AC12: No | AD12: No | AE12: No | AK12: No | AM12: =IF(AF12="","","Q"&INT((MONTH(AF12)-1)/3)+1&YEAR(AF12)&#REF!&T12) | AN12: =IF(K12="","","Q"&INT((MONTH(K12)-1)/3)+1&YEAR(K12)&#REF!) -> #REF!
A13: 11 | B13: BHA | C13: Shining Star | D13: Mobile Clinic | E13: Mandalay | F13: Amarapura | H13: Myit Too | I13: Village | K13: 46037 | L13: 11 | M13: =IF(phc_8[[#This Row],[Register No.]]="","",C13&"-"&D13&"-"&"BHA-PHC-"&phc_8[[#This Row],[Register No.]]) -> Shining Star-Mobile Clinic-BHA-PHC-11 | N13: New | O13: Daw Tin Hla | P13: 78 | S13: =IF(AND(ISBLANK(P13),ISBLANK(Q13),ISBLANK(R13))," ", IF(OR(P13<5,AND(P13=" ",Q13<>" ",R13<>" ")),"<5 yrs", IF(AND(P13>=5,P13<=14),"5 - 14 yrs", IF(AND(P13>=15,P13<=18),"15 - 18 yrs", IF(AND(P13>=19,P13<=49),"19 - 49 yrs","50 yrs +"))))) -> 50 yrs + | T13: Female | U13: Myit Too | V13: U Hla Mg | W13: HT | X13: Hypertension | Y13: =INDEX(info!$Y$2:$Y$192,MATCH(phc_8[[#This Row],[Sub_Category]],info!$X$2:$X$192,0)) -> Chronic medical disease | Z13: {=INDEX(info!$AA$2:$AA$192,MATCH(PHC!$X13&PHC!$Y13,info!$X$2:$X$192&info!$Y$2:$Y$192,0))} -> Non-communicable disease | AA13: Amlo5,Para,MV, Ca+ | AB13: No | AC13: No | AD13: No | AE13: No | AK13: No | AM13: =IF(AF13="","","Q"&INT((MONTH(AF13)-1)/3)+1&YEAR(AF13)&#REF!&T13) | AN13: =IF(K13="","","Q"&INT((MONTH(K13)-1)/3)+1&YEAR(K13)&#REF!) -> #REF!
A14: 12 | B14: BHA | C14: Shining Star | D14: Mobile Clinic | E14: Mandalay | F14: Amarapura | H14: Myit Too | I14: Village | K14: 46037 | L14: 12 | M14: =IF(phc_8[[#This Row],[Register No.]]="","",C14&"-"&D14&"-"&"BHA-PHC-"&phc_8[[#This Row],[Register No.]]) -> Shining Star-Mobile Clinic-BHA-PHC-12 | N14: New | O14: Daw Kyi Htay | P14: 73 | S14: =IF(AND(ISBLANK(P14),ISBLANK(Q14),ISBLANK(R14))," ", IF(OR(P14<5,AND(P14=" ",Q14<>" ",R14<>" ")),"<5 yrs", IF(AND(P14>=5,P14<=14),"5 - 14 yrs", IF(AND(P14>=15,P14<=18),"15 - 18 yrs", IF(AND(P14>=19,P14<=49),"19 - 49 yrs","50 yrs +"))))) -> 50 yrs + | T14: Female | U14: Myit Too | V14: U Hla Mg | W14: Asthma | X14: Asthma | Y14: =INDEX(info!$Y$2:$Y$192,MATCH(phc_8[[#This Row],[Sub_Category]],info!$X$2:$X$192,0)) -> Asthma | Z14: {=INDEX(info!$AA$2:$AA$192,MATCH(PHC!$X14&PHC!$Y14,info!$X$2:$X$192&info!$Y$2:$Y$192,0))} -> Non-communicable disease | AA14: IV Hydrocortisone, Dextro, Prednisolone, MV, Cefixime | AB14: No | AC14: No | AD14: No | AE14: No | AK14: No | AM14: =IF(AF14="","","Q"&INT((MONTH(AF14)-1)/3)+1&YEAR(AF14)&#REF!&T14) | AN14: =IF(K14="","","Q"&INT((MONTH(K14)-1)/3)+1&YEAR(K14)&#REF!) -> #REF!
A15: 13 | B15: BHA | C15: Shining Star | D15: Mobile Clinic | E15: Mandalay | F15: Amarapura | H15: Myit Too | I15: Village | K15: 46037 | L15: 13 | M15: =IF(phc_8[[#This Row],[Register No.]]="","",C15&"-"&D15&"-"&"BHA-PHC-"&phc_8[[#This Row],[Register No.]]) -> Shining Star-Mobile Clinic-BHA-PHC-13 | N15: New | O15: Daw Mya Win | P15: 68 | S15: =IF(AND(ISBLANK(P15),ISBLANK(Q15),ISBLANK(R15))," ", IF(OR(P15<5,AND(P15=" ",Q15<>" ",R15<>" ")),"<5 yrs", IF(AND(P15>=5,P15<=14),"5 - 14 yrs", IF(AND(P15>=15,P15<=18),"15 - 18 yrs", IF(AND(P15>=19,P15<=49),"19 - 49 yrs","50 yrs +"))))) -> 50 yrs + | T15: Female | U15: Myit Too | V15: U Than Kyaw | W15: DM | X15: DM | Y15: =INDEX(info!$Y$2:$Y$192,MATCH(phc_8[[#This Row],[Sub_Category]],info!$X$2:$X$192,0)) -> Chronic medical disease | Z15: {=INDEX(info!$AA$2:$AA$192,MATCH(PHC!$X15&PHC!$Y15,info!$X$2:$X$192&info!$Y$2:$Y$192,0))} -> Non-communicable disease | AA15: Metformin, Zinc, Betex | AB15: No | AC15: No | AD15: No | AE15: No | AK15: No | AM15: =IF(AF15="","","Q"&INT((MONTH(AF15)-1)/3)+1&YEAR(AF15)&#REF!&T15) | AN15: =IF(K15="","","Q"&INT((MONTH(K15)-1)/3)+1&YEAR(K15)&#REF!) -> #REF!
A16: 14 | B16: BHA | C16: Shining Star | D16: Mobile Clinic | E16: Mandalay | F16: Amarapura | H16: Myit Too | I16: Village | K16: 46037 | L16: 14 | M16: =IF(phc_8[[#This Row],[Register No.]]="","",C16&"-"&D16&"-"&"BHA-PHC-"&phc_8[[#This Row],[Register No.]]) -> Shining Star-Mobile Clinic-BHA-PHC-14 | N16: New | O16: Daw Yin Myint | P16: 80 | S16: =IF(AND(ISBLANK(P16),ISBLANK(Q16),ISBLANK(R16))," ", IF(OR(P16<5,AND(P16=" ",Q16<>" ",R16<>" ")),"<5 yrs", IF(AND(P16>=5,P16<=14),"5 - 14 yrs", IF(AND(P16>=15,P16<=18),"15 - 18 yrs", IF(AND(P16>=19,P16<=49),"19 - 49 yrs","50 yrs +"))))) -> 50 yrs + | T16: Female | U16: Myit Too | V16: U Chit | W16: HT | X16: Hypertension | Y16: =INDEX(info!$Y$2:$Y$192,MATCH(phc_8[[#This Row],[Sub_Category]],info!$X$2:$X$192,0)) -> Chronic medical disease | Z16: {=INDEX(info!$AA$2:$AA$192,MATCH(PHC!$X16&PHC!$Y16,info!$X$2:$X$192&info!$Y$2:$Y$192,0))} -> Non-communicable disease | AA16: Amlo10, Metformin, DMR30, Para, Betex | AB16: No | AC16: No | AD16: No | AE16: No | AK16: No | AM16: =IF(AF16="","","Q"&INT((MONTH(AF16)-1)/3)+1&YEAR(AF16)&#REF!&T16) | AN16: =IF(K16="","","Q"&INT((MONTH(K16)-1)/3)+1&YEAR(K16)&#REF!) -> #REF!
A17: 15 | B17: BHA | C17: Shining Star | D17: Mobile Clinic | E17: Mandalay | F17: Amarapura | H17: Myit Too | I17: Village | K17: 46037 | L17: 15 | M17: =IF(phc_8[[#This Row],[Register No.]]="","",C17&"-"&D17&"-"&"BHA-PHC-"&phc_8[[#This Row],[Register No.]]) -> Shining Star-Mobile Clinic-BHA-PHC-15 | N17: New | O17: U Kyaw Linn Soe | P17: 45 | S17: =IF(AND(ISBLANK(P17),ISBLANK(Q17),ISBLANK(R17))," ", IF(OR(P17<5,AND(P17=" ",Q17<>" ",R17<>" ")),"<5 yrs", IF(AND(P17>=5,P17<=14),"5 - 14 yrs", IF(AND(P17>=15,P17<=18),"15 - 18 yrs", IF(AND(P17>=19,P17<=49),"19 - 49 yrs","50 yrs +"))))) -> 19 - 49 yrs | T17: Male | U17: Myit Too | V17: U Nyein | W17: Injuries | X17: Injuries | Y17: =INDEX(info!$Y$2:$Y$192,MATCH(phc_8[[#This Row],[Sub_Category]],info!$X$2:$X$192,0)) -> Accident/minor sugical and injuries | Z17: {=INDEX(info!$AA$2:$AA$192,MATCH(PHC!$X17&PHC!$Y17,info!$X$2:$X$192&info!$Y$2:$Y$192,0))} -> Injury related | AA17: IM Diclo, Ibu, Omex, Ca+ | AB17: No | AC17: No | AD17: No | AE17: No | AK17: No | AM17: =IF(AF17="","","Q"&INT((MONTH(AF17)-1)/3)+1&YEAR(AF17)&#REF!&T17) | AN17: =IF(K17="","","Q"&INT((MONTH(K17)-1)/3)+1&YEAR(K17)&#REF!) -> #REF!
A18: 16 | B18: BHA | C18: Shining Star | D18: Mobile Clinic | E18: Mandalay | F18: Amarapura | H18: Myit Too | I18: Village | K18: 46037 | L18: 16 | M18: =IF(phc_8[[#This Row],[Register No.]]="","",C18&"-"&D18&"-"&"BHA-PHC-"&phc_8[[#This Row],[Register No.]]) -> Shining Star-Mobile Clinic-BHA-PHC-16 | N18: New | O18: Daw Shwe Myint | P18: 65 | S18: =IF(AND(ISBLANK(P18),ISBLANK(Q18),ISBLANK(R18))," ", IF(OR(P18<5,AND(P18=" ",Q18<>" ",R18<>" ")),"<5 yrs", IF(AND(P18>=5,P18<=14),"5 - 14 yrs", IF(AND(P18>=15,P18<=18),"15 - 18 yrs", IF(AND(P18>=19,P18<=49),"19 - 49 yrs","50 yrs +"))))) -> 50 yrs + | T18: Female | U18: Myit Too | V18: U Nyein | W18: HT | X18: Hypertension | Y18: =INDEX(info!$Y$2:$Y$192,MATCH(phc_8[[#This Row],[Sub_Category]],info!$X$2:$X$192,0)) -> Chronic medical disease | Z18: {=INDEX(info!$AA$2:$AA$192,MATCH(PHC!$X18&PHC!$Y18,info!$X$2:$X$192&info!$Y$2:$Y$192,0))} -> Non-communicable disease | AA18: Amlo5, MV, Zinc | AB18: No | AC18: No | AD18: No | AE18: No | AK18: No | AM18: =IF(AF18="","","Q"&INT((MONTH(AF18)-1)/3)+1&YEAR(AF18)&#REF!&T18) | AN18: =IF(K18="","","Q"&INT((MONTH(K18)-1)/3)+1&YEAR(K18)&#REF!) -> #REF!
A19: 17 | B19: BHA | C19: Shining Star | D19: Mobile Clinic | E19: Mandalay | F19: Amarapura | H19: Myit Too | I19: Village | K19: 46037 | L19: 17 | M19: =IF(phc_8[[#This Row],[Register No.]]="","",C19&"-"&D19&"-"&"BHA-PHC-"&phc_8[[#This Row],[Register No.]]) -> Shining Star-Mobile Clinic-BHA-PHC-17 | N19: New | O19: U Nyi | P19: 65 | S19: =IF(AND(ISBLANK(P19),ISBLANK(Q19),ISBLANK(R19))," ", IF(OR(P19<5,AND(P19=" ",Q19<>" ",R19<>" ")),"<5 yrs", IF(AND(P19>=5,P19<=14),"5 - 14 yrs", IF(AND(P19>=15,P19<=18),"15 - 18 yrs", IF(AND(P19>=19,P19<=49),"19 - 49 yrs","50 yrs +"))))) -> 50 yrs + | T19: Male | U19: Myit Too | V19: U Hla Sein | W19: Back Pain | X19: Muscle Pain | Y19: =INDEX(info!$Y$2:$Y$192,MATCH(phc_8[[#This Row],[Sub_Category]],info!$X$2:$X$192,0)) -> Other (non-communicable) | Z19: {=INDEX(info!$AA$2:$AA$192,MATCH(PHC!$X19&PHC!$Y19,info!$X$2:$X$192&info!$Y$2:$Y$192,0))} -> Other | AA19: IV B12, Ibu, Omex, Ca+, Gabapentin | AB19: No | AC19: No | AD19: No | AE19: No | AK19: No | AM19: =IF(AF19="","","Q"&INT((MONTH(AF19)-1)/3)+1&YEAR(AF19)&#REF!&T19) | AN19: =IF(K19="","","Q"&INT((MONTH(K19)-1)/3)+1&YEAR(K19)&#REF!) -> #REF!
A20: 18 | B20: BHA | C20: Shining Star | D20: Mobile Clinic | E20: Mandalay | F20: Amarapura | H20: Myit Too | I20: Village | K20: 46037 | L20: 18 | M20: =IF(phc_8[[#This Row],[Register No.]]="","",C20&"-"&D20&"-"&"BHA-PHC-"&phc_8[[#This Row],[Register No.]]) -> Shining Star-Mobile Clinic-BHA-PHC-18 | N20: New | O20: Daw Tin Tin Mu | P20: 62 | S20: =IF(AND(ISBLANK(P20),ISBLANK(Q20),ISBLANK(R20))," ", IF(OR(P20<5,AND(P20=" ",Q20<>" ",R20<>" ")),"<5 yrs", IF(AND(P20>=5,P20<=14),"5 - 14 yrs", IF(AND(P20>=15,P20<=18),"15 - 18 yrs", IF(AND(P20>=19,P20<=49),"19 - 49 yrs","50 yrs +"))))) -> 50 yrs + | T20: Female | U20: Myit Too | V20: U Bo | W20: HT/DM | X20: DM | Y20: =INDEX(info!$Y$2:$Y$192,MATCH(phc_8[[#This Row],[Sub_Category]],info!$X$2:$X$192,0)) -> Chronic medical disease | Z20: {=INDEX(info!$AA$2:$AA$192,MATCH(PHC!$X20&PHC!$Y20,info!$X$2:$X$192&info!$Y$2:$Y$192,0))} -> Non-communicable disease | AA20: Amlo5, Gliclacide, Ato10, Aspiet, Metformin, Allopurinol | AB20: No | AC20: No | AD20: No | AE20: No | AK20: No | AM20: =IF(AF20="","","Q"&INT((MONTH(AF20)-1)/3)+1&YEAR(AF20)&#REF!&T20) | AN20: =IF(K20="","","Q"&INT((MONTH(K20)-1)/3)+1&YEAR(K20)&#REF!) -> #REF!
A21: 19 | B21: BHA | C21: Shining Star | D21: Mobile Clinic | E21: Mandalay | F21: Amarapura | H21: Myit Too | I21: Village | K21: 46037 | L21: 19 | M21: =IF(phc_8[[#This Row],[Register No.]]="","",C21&"-"&D21&"-"&"BHA-PHC-"&phc_8[[#This Row],[Register No.]]) -> Shining Star-Mobile Clinic-BHA-PHC-19 | N21: New | O21: Daw Myint Moh San | P21: 51 | S21: =IF(AND(ISBLANK(P21),ISBLANK(Q21),ISBLANK(R21))," ", IF(OR(P21<5,AND(P21=" ",Q21<>" ",R21<>" ")),"<5 yrs", IF(AND(P21>=5,P21<=14),"5 - 14 yrs", IF(AND(P21>=15,P21<=18),"15 - 18 yrs", IF(AND(P21>=19,P21<=49),"19 - 49 yrs","50 yrs +"))))) -> 50 yrs + | T21: Female | U21: Myit Too | V21: U Kan | W21: Muscle Pain | X21: Muscle Pain | Y21: =INDEX(info!$Y$2:$Y$192,MATCH(phc_8[[#This Row],[Sub_Category]],info!$X$2:$X$192,0)) -> Other (non-communicable) | Z21: {=INDEX(info!$AA$2:$AA$192,MATCH(PHC!$X21&PHC!$Y21,info!$X$2:$X$192&info!$Y$2:$Y$192,0))} -> Other | AA21: Cefixime, Dextro, Vit C, Betex | AB21: No | AC21: No | AD21: No | AE21: No | AK21: No | AM21: =IF(AF21="","","Q"&INT((MONTH(AF21)-1)/3)+1&YEAR(AF21)&#REF!&T21) | AN21: =IF(K21="","","Q"&INT((MONTH(K21)-1)/3)+1&YEAR(K21)&#REF!) -> #REF!
A22: 20 | B22: BHA | C22: Shining Star | D22: Mobile Clinic | E22: Mandalay | F22: Amarapura | H22: Myit Too | I22: Village | K22: 46037 | L22: 20 | M22: =IF(phc_8[[#This Row],[Register No.]]="","",C22&"-"&D22&"-"&"BHA-PHC-"&phc_8[[#This Row],[Register No.]]) -> Shining Star-Mobile Clinic-BHA-PHC-20 | N22: New | O22: Daw Yee Myint | P22: 61 | S22: =IF(AND(ISBLANK(P22),ISBLANK(Q22),ISBLANK(R22))," ", IF(OR(P22<5,AND(P22=" ",Q22<>" ",R22<>" ")),"<5 yrs", IF(AND(P22>=5,P22<=14),"5 - 14 yrs", IF(AND(P22>=15,P22<=18),"15 - 18 yrs", IF(AND(P22>=19,P22<=49),"19 - 49 yrs","50 yrs +"))))) -> 50 yrs + | T22: Female | U22: Myit Too | V22: U Nyo | W22: DM | X22: DM | Y22: =INDEX(info!$Y$2:$Y$192,MATCH(phc_8[[#This Row],[Sub_Category]],info!$X$2:$X$192,0)) -> Chronic medical disease | Z22: {=INDEX(info!$AA$2:$AA$192,MATCH(PHC!$X22&PHC!$Y22,info!$X$2:$X$192&info!$Y$2:$Y$192,0))} -> Non-communicable disease | AA22: Amlo5, zinc, Betex | AB22: No | AC22: No | AD22: No | AE22: No | AK22: No | AM22: =IF(AF22="","","Q"&INT((MONTH(AF22)-1)/3)+1&YEAR(AF22)&#REF!&T22) | AN22: =IF(K22="","","Q"&INT((MONTH(K22)-1)/3)+1&YEAR(K22)&#REF!) -> #REF!
... A54: 52 | B54: BHA | C54: Shining Star | D54: Mobile Clinic | E54: Mandalay | F54: Amarapura | H54: Myit Too | I54: Village | K54: 46037 | L54: 52 | M54: =IF(phc_8[[#This Row],[Register No.]]="","",C54&"-"&D54&"-"&"BHA-PHC-"&phc_8[[#This Row],[Register No.]]) -> Shining Star-Mobile Clinic-BHA-PHC-52 | N54: New | O54: Daw Kay Thwel Soe | P54: 52 | S54: =IF(AND(ISBLANK(P54),ISBLANK(Q54),ISBLANK(R54))," ", IF(OR(P54<5,AND(P54=" ",Q54<>" ",R54<>" ")),"<5 yrs", IF(AND(P54>=5,P54<=14),"5 - 14 yrs", IF(AND(P54>=15,P54<=18),"15 - 18 yrs", IF(AND(P54>=19,P54<=49),"19 - 49 yrs","50 yrs +"))))) -> 50 yrs + | T54: Female | U54: Myit Too | V54: U Than Ko | W54: Back Pain | X54: Muscle Pain | Y54: =INDEX(info!$Y$2:$Y$192,MATCH(phc_8[[#This Row],[Sub_Category]],info!$X$2:$X$192,0)) -> Other (non-communicable) | Z54: {=INDEX(info!$AA$2:$AA$192,MATCH(PHC!$X54&PHC!$Y54,info!$X$2:$X$192&info!$Y$2:$Y$192,0))} -> Other | AA54: IV B12, Ca+, MV, Gabapentin | AB54: No | AC54: No | AD54: No | AE54: No | AK54: No | AM54: =IF(AF54="","","Q"&INT((MONTH(AF54)-1)/3)+1&YEAR(AF54)&#REF!&T54) | AN54: =IF(K54="","","Q"&INT((MONTH(K54)-1)/3)+1&YEAR(K54)&#REF!) -> #REF!
A55: 53 | B55: BHA | C55: Shining Star | D55: Mobile Clinic | E55: Mandalay | F55: Amarapura | H55: Myit Too | I55: Village | K55: 46037 | L55: 53 | M55: =IF(phc_8[[#This Row],[Register No.]]="","",C55&"-"&D55&"-"&"BHA-PHC-"&phc_8[[#This Row],[Register No.]]) -> Shining Star-Mobile Clinic-BHA-PHC-53 | N55: New | O55: Ma Tin Moe Aung | P55: 30 | S55: =IF(AND(ISBLANK(P55),ISBLANK(Q55),ISBLANK(R55))," ", IF(OR(P55<5,AND(P55=" ",Q55<>" ",R55<>" ")),"<5 yrs", IF(AND(P55>=5,P55<=14),"5 - 14 yrs", IF(AND(P55>=15,P55<=18),"15 - 18 yrs", IF(AND(P55>=19,P55<=49),"19 - 49 yrs","50 yrs +"))))) -> 19 - 49 yrs | T55: Female | U55: Myit Too | W55: Weakness | X55: Weakness | Y55: =INDEX(info!$Y$2:$Y$192,MATCH(phc_8[[#This Row],[Sub_Category]],info!$X$2:$X$192,0)) -> Other (non-communicable) | Z55: {=INDEX(info!$AA$2:$AA$192,MATCH(PHC!$X55&PHC!$Y55,info!$X$2:$X$192&info!$Y$2:$Y$192,0))} -> Other | AA55: MV, Zinc | AB55: No | AC55: No | AD55: No | AE55: No | AK55: No | AM55: =IF(AF55="","","Q"&INT((MONTH(AF55)-1)/3)+1&YEAR(AF55)&#REF!&T55) | AN55: =IF(K55="","","Q"&INT((MONTH(K55)-1)/3)+1&YEAR(K55)&#REF!) -> #REF!
A56: 54 | B56: BHA | C56: Shining Star | D56: Mobile Clinic | E56: Mandalay | F56: Amarapura | H56: Myit Too | I56: Village | K56: 46037 | L56: 54 | M56: =IF(phc_8[[#This Row],[Register No.]]="","",C56&"-"&D56&"-"&"BHA-PHC-"&phc_8[[#This Row],[Register No.]]) -> Shining Star-Mobile Clinic-BHA-PHC-54 | N56: New | O56: Mg Kyaw Zin Htun | Q56: 8 | S56: =IF(AND(ISBLANK(P56),ISBLANK(Q56),ISBLANK(R56))," ", IF(OR(P56<5,AND(P56=" ",Q56<>" ",R56<>" ")),"<5 yrs", IF(AND(P56>=5,P56<=14),"5 - 14 yrs", IF(AND(P56>=15,P56<=18),"15 - 18 yrs", IF(AND(P56>=19,P56<=49),"19 - 49 yrs","50 yrs +"))))) -> <5 yrs | T56: Male | U56: Myit Too | V56: U Kyaw Htoo Aung | W56: Viral | X56: Respiratory viral infection | Y56: =INDEX(info!$Y$2:$Y$192,MATCH(phc_8[[#This Row],[Sub_Category]],info!$X$2:$X$192,0)) -> ARI/RTI | Z56: {=INDEX(info!$AA$2:$AA$192,MATCH(PHC!$X56&PHC!$Y56,info!$X$2:$X$192&info!$Y$2:$Y$192,0))} -> Communicable disease | AA56: Baby Cough, B'ton | AB56: No | AC56: No | AD56: No | AE56: No | AK56: No | AM56: =IF(AF56="","","Q"&INT((MONTH(AF56)-1)/3)+1&YEAR(AF56)&#REF!&T56) | AN56: =IF(K56="","","Q"&INT((MONTH(K56)-1)/3)+1&YEAR(K56)&#REF!) -> #REF!
A57: 55 | B57: BHA | C57: Shining Star | D57: Mobile Clinic | E57: Mandalay | F57: Amarapura | H57: Myit Too | I57: Village | K57: 46037 | L57: 55 | M57: =IF(phc_8[[#This Row],[Register No.]]="","",C57&"-"&D57&"-"&"BHA-PHC-"&phc_8[[#This Row],[Register No.]]) -> Shining Star-Mobile Clinic-BHA-PHC-55 | N57: New | O57: Ma Mya Kyar Phyu | P57: 26 | S57: =IF(AND(ISBLANK(P57),ISBLANK(Q57),ISBLANK(R57))," ", IF(OR(P57<5,AND(P57=" ",Q57<>" ",R57<>" ")),"<5 yrs", IF(AND(P57>=5,P57<=14),"5 - 14 yrs", IF(AND(P57>=15,P57<=18),"15 - 18 yrs", IF(AND(P57>=19,P57<=49),"19 - 49 yrs","50 yrs +"))))) -> 19 - 49 yrs | T57: Female | U57: Myit Too | V57: U Mg Tin | W57: Weakness | X57: Weakness | Y57: =INDEX(info!$Y$2:$Y$192,MATCH(phc_8[[#This Row],[Sub_Category]],info!$X$2:$X$192,0)) -> Other (non-communicable) | Z57: {=INDEX(info!$AA$2:$AA$192,MATCH(PHC!$X57&PHC!$Y57,info!$X$2:$X$192&info!$Y$2:$Y$192,0))} -> Other | AA57: IV B12, MV, Zinc, ORS | AB57: No | AC57: No | AD57: No | AE57: No | AK57: No | AM57: =IF(AF57="","","Q"&INT((MONTH(AF57)-1)/3)+1&YEAR(AF57)&#REF!&T57) | AN57: =IF(K57="","","Q"&INT((MONTH(K57)-1)/3)+1&YEAR(K57)&#REF!) -> #REF!
A58: 56 | B58: BHA | C58: Shining Star | D58: Mobile Clinic | E58: Mandalay | F58: Amarapura | H58: Myit Too | I58: Village | K58: 46037 | L58: 56 | M58: =IF(phc_8[[#This Row],[Register No.]]="","",C58&"-"&D58&"-"&"BHA-PHC-"&phc_8[[#This Row],[Register No.]]) -> Shining Star-Mobile Clinic-BHA-PHC-56 | N58: New | O58: Mg Aung Khant Kyaw | P58: 4 | S58: =IF(AND(ISBLANK(P58),ISBLANK(Q58),ISBLANK(R58))," ", IF(OR(P58<5,AND(P58=" ",Q58<>" ",R58<>" ")),"<5 yrs", IF(AND(P58>=5,P58<=14),"5 - 14 yrs", IF(AND(P58>=15,P58<=18),"15 - 18 yrs", IF(AND(P58>=19,P58<=49),"19 - 49 yrs","50 yrs +"))))) -> <5 yrs | T58: Male | U58: Myit Too | V58: U Kyaw Linn Soe | W58: Skin Problem | X58: Other skin disorders | Y58: =INDEX(info!$Y$2:$Y$192,MATCH(phc_8[[#This Row],[Sub_Category]],info!$X$2:$X$192,0)) -> Skin infection/disease | Z58: {=INDEX(info!$AA$2:$AA$192,MATCH(PHC!$X58&PHC!$Y58,info!$X$2:$X$192&info!$Y$2:$Y$192,0))} -> Non-communicable disease | AA58: Zinc Syrup | AB58: No | AC58: No | AD58: No | AE58: No | AK58: No | AM58: =IF(AF58="","","Q"&INT((MONTH(AF58)-1)/3)+1&YEAR(AF58)&#REF!&T58) | AN58: =IF(K58="","","Q"&INT((MONTH(K58)-1)/3)+1&YEAR(K58)&#REF!) -> #REF!
A59: 57 | B59: BHA | C59: Shining Star | D59: Mobile Clinic | E59: Mandalay | F59: Amarapura | H59: Myit Too | I59: Village | K59: 46037 | L59: 57 | M59: =IF(phc_8[[#This Row],[Register No.]]="","",C59&"-"&D59&"-"&"BHA-PHC-"&phc_8[[#This Row],[Register No.]]) -> Shining Star-Mobile Clinic-BHA-PHC-57 | N59: New | O59: Ma Khin Khin Kyaw | P59: 9 | S59: =IF(AND(ISBLANK(P59),ISBLANK(Q59),ISBLANK(R59))," ", IF(OR(P59<5,AND(P59=" ",Q59<>" ",R59<>" ")),"<5 yrs", IF(AND(P59>=5,P59<=14),"5 - 14 yrs", IF(AND(P59>=15,P59<=18),"15 - 18 yrs", IF(AND(P59>=19,P59<=49),"19 - 49 yrs","50 yrs +"))))) -> 5 - 14 yrs | T59: Female | U59: Myit Too | V59: U Kyaw Linn Soe | W59: Skin Problem | X59: Other skin disorders | Y59: =INDEX(info!$Y$2:$Y$192,MATCH(phc_8[[#This Row],[Sub_Category]],info!$X$2:$X$192,0)) -> Skin infection/disease | Z59: {=INDEX(info!$AA$2:$AA$192,MATCH(PHC!$X59&PHC!$Y59,info!$X$2:$X$192&info!$Y$2:$Y$192,0))} -> Non-communicable disease | AA59: PB vita, Zinc | AB59: No | AC59: No | AD59: No | AE59: No | AK59: No | AM59: =IF(AF59="","","Q"&INT((MONTH(AF59)-1)/3)+1&YEAR(AF59)&#REF!&T59) | AN59: =IF(K59="","","Q"&INT((MONTH(K59)-1)/3)+1&YEAR(K59)&#REF!) -> #REF!
A60: 58 | B60: BHA | C60: Shining Star | D60: Mobile Clinic | E60: Mandalay | F60: Amarapura | H60: Myit Too | I60: Village | K60: 46037 | L60: 58 | M60: =IF(phc_8[[#This Row],[Register No.]]="","",C60&"-"&D60&"-"&"BHA-PHC-"&phc_8[[#This Row],[Register No.]]) -> Shining Star-Mobile Clinic-BHA-PHC-58 | N60: New | O60: Daw Khin Hla | P60: 73 | S60: =IF(AND(ISBLANK(P60),ISBLANK(Q60),ISBLANK(R60))," ", IF(OR(P60<5,AND(P60=" ",Q60<>" ",R60<>" ")),"<5 yrs", IF(AND(P60>=5,P60<=14),"5 - 14 yrs", IF(AND(P60>=15,P60<=18),"15 - 18 yrs", IF(AND(P60>=19,P60<=49),"19 - 49 yrs","50 yrs +"))))) -> 50 yrs + | T60: Female | U60: Myit Too | V60: U Chit | W60: Both Knee Pain | X60: Injuries | Y60: =INDEX(info!$Y$2:$Y$192,MATCH(phc_8[[#This Row],[Sub_Category]],info!$X$2:$X$192,0)) -> Accident/minor sugical and injuries | Z60: {=INDEX(info!$AA$2:$AA$192,MATCH(PHC!$X60&PHC!$Y60,info!$X$2:$X$192&info!$Y$2:$Y$192,0))} -> Injury related | AA60: IV B12, Ibu, Omex, Ca+, MV | AB60: No | AC60: No | AD60: No | AE60: No | AK60: No | AM60: =IF(AF60="","","Q"&INT((MONTH(AF60)-1)/3)+1&YEAR(AF60)&#REF!&T60) | AN60: =IF(K60="","","Q"&INT((MONTH(K60)-1)/3)+1&YEAR(K60)&#REF!) -> #REF!
A61: 59 | B61: BHA | C61: Shining Star | D61: Mobile Clinic | E61: Mandalay | F61: Amarapura | H61: Myit Too | I61: Village | K61: 46037 | L61: 59 | M61: =IF(phc_8[[#This Row],[Register No.]]="","",C61&"-"&D61&"-"&"BHA-PHC-"&phc_8[[#This Row],[Register No.]]) -> Shining Star-Mobile Clinic-BHA-PHC-59 | N61: New | O61: Daw Aye Thaung | P61: 83 | S61: =IF(AND(ISBLANK(P61),ISBLANK(Q61),ISBLANK(R61))," ", IF(OR(P61<5,AND(P61=" ",Q61<>" ",R61<>" ")),"<5 yrs", IF(AND(P61>=5,P61<=14),"5 - 14 yrs", IF(AND(P61>=15,P61<=18),"15 - 18 yrs", IF(AND(P61>=19,P61<=49),"19 - 49 yrs","50 yrs +"))))) -> 50 yrs + | T61: Female | U61: Myit Too | V61: U Mg Ngway | W61: Asthma | X61: Asthma | Y61: =INDEX(info!$Y$2:$Y$192,MATCH(phc_8[[#This Row],[Sub_Category]],info!$X$2:$X$192,0)) -> Asthma | Z61: {=INDEX(info!$AA$2:$AA$192,MATCH(PHC!$X61&PHC!$Y61,info!$X$2:$X$192&info!$Y$2:$Y$192,0))} -> Non-communicable disease | AA61: IV Hydrocortisone, Predinisolone, Dextro, Deriphylline, Cefixime, MV | AB61: No | AC61: No | AD61: No | AE61: No | AK61: No | AM61: =IF(AF61="","","Q"&INT((MONTH(AF61)-1)/3)+1&YEAR(AF61)&#REF!&T61) | AN61: =IF(K61="","","Q"&INT((MONTH(K61)-1)/3)+1&YEAR(K61)&#REF!) -> #REF!
A62: 60 | B62: BHA | C62: Shining Star | D62: Mobile Clinic | E62: Mandalay | F62: Amarapura | H62: Myit Too | I62: Village | K62: 46037 | L62: 60 | M62: =IF(phc_8[[#This Row],[Register No.]]="","",C62&"-"&D62&"-"&"BHA-PHC-"&phc_8[[#This Row],[Register No.]]) -> Shining Star-Mobile Clinic-BHA-PHC-60 | N62: New | O62: Daw Cherry Win | P62: 52 | S62: =IF(AND(ISBLANK(P62),ISBLANK(Q62),ISBLANK(R62))," ", IF(OR(P62<5,AND(P62=" ",Q62<>" ",R62<>" ")),"<5 yrs", IF(AND(P62>=5,P62<=14),"5 - 14 yrs", IF(AND(P62>=15,P62<=18),"15 - 18 yrs", IF(AND(P62>=19,P62<=49),"19 - 49 yrs","50 yrs +"))))) -> 50 yrs + | T62: Female | U62: Myit Too | V62: U Myint Kyi | W62: Weakness | X62: Weakness | Y62: =INDEX(info!$Y$2:$Y$192,MATCH(phc_8[[#This Row],[Sub_Category]],info!$X$2:$X$192,0)) -> Other (non-communicable) | Z62: {=INDEX(info!$AA$2:$AA$192,MATCH(PHC!$X62&PHC!$Y62,info!$X$2:$X$192&info!$Y$2:$Y$192,0))} -> Other | AA62: IV 25%+VitC+B12, MV, Para, Cinnarizine | AB62: No | AC62: No | AD62: No | AE62: No | AK62: No | AM62: =IF(AF62="","","Q"&INT((MONTH(AF62)-1)/3)+1&YEAR(AF62)&#REF!&T62) | AN62: =IF(K62="","","Q"&INT((MONTH(K62)-1)/3)+1&YEAR(K62)&#REF!) -> #REF!
A63: 61 | B63: BHA | C63: Shining Star | D63: Mobile Clinic | E63: Mandalay | F63: Amarapura | H63: Myit Too | I63: Village | K63: 46037 | L63: 61 | M63: =IF(phc_8[[#This Row],[Register No.]]="","",C63&"-"&D63&"-"&"BHA-PHC-"&phc_8[[#This Row],[Register No.]]) -> Shining Star-Mobile Clinic-BHA-PHC-61 | N63: New | O63: Ma Thu Zar Maw | P63: 44 | S63: =IF(AND(ISBLANK(P63),ISBLANK(Q63),ISBLANK(R63))," ", IF(OR(P63<5,AND(P63=" ",Q63<>" ",R63<>" ")),"<5 yrs", IF(AND(P63>=5,P63<=14),"5 - 14 yrs", IF(AND(P63>=15,P63<=18),"15 - 18 yrs", IF(AND(P63>=19,P63<=49),"19 - 49 yrs","50 yrs +"))))) -> 19 - 49 yrs | T63: Female | U63: Myit Too | V63: U Than Ko | W63: Weakness | X63: Weakness | Y63: =INDEX(info!$Y$2:$Y$192,MATCH(phc_8[[#This Row],[Sub_Category]],info!$X$2:$X$192,0)) -> Other (non-communicable) | Z63: {=INDEX(info!$AA$2:$AA$192,MATCH(PHC!$X63&PHC!$Y63,info!$X$2:$X$192&info!$Y$2:$Y$192,0))} -> Other | AA63: MV, Dextro, Cinnarizine, Cetrizine | AB63: No | AC63: No | AD63: No | AE63: No | AK63: No | AM63: =IF(AF63="","","Q"&INT((MONTH(AF63)-1)/3)+1&YEAR(AF63)&#REF!&T63) | AN63: =IF(K63="","","Q"&INT((MONTH(K63)-1)/3)+1&YEAR(K63)&#REF!) -> #REF!
A64: 62 | B64: BHA | C64: Shining Star | D64: Mobile Clinic | E64: Mandalay | F64: Amarapura | H64: Myit Too | I64: Village | K64: 46037 | L64: 62 | M64: =IF(phc_8[[#This Row],[Register No.]]="","",C64&"-"&D64&"-"&"BHA-PHC-"&phc_8[[#This Row],[Register No.]]) -> Shining Star-Mobile Clinic-BHA-PHC-62 | N64: New | O64: Daw Nway Oo | P64: 57 | S64: =IF(AND(ISBLANK(P64),ISBLANK(Q64),ISBLANK(R64))," ", IF(OR(P64<5,AND(P64=" ",Q64<>" ",R64<>" ")),"<5 yrs", IF(AND(P64>=5,P64<=14),"5 - 14 yrs", IF(AND(P64>=15,P64<=18),"15 - 18 yrs", IF(AND(P64>=19,P64<=49),"19 - 49 yrs","50 yrs +"))))) -> 50 yrs + | T64: Female | U64: Myit Too | V64: U Htway Tin | W64: Weakness | X64: Weakness | Y64: =INDEX(info!$Y$2:$Y$192,MATCH(phc_8[[#This Row],[Sub_Category]],info!$X$2:$X$192,0)) -> Other (non-communicable) | Z64: {=INDEX(info!$AA$2:$AA$192,MATCH(PHC!$X64&PHC!$Y64,info!$X$2:$X$192&info!$Y$2:$Y$192,0))} -> Other | AA64: IV B12, Cinnarizine, Betex, MV | AB64: No | AC64: No | AD64: No | AE64: No | AK64: No | AM64: =IF(AF64="","","Q"&INT((MONTH(AF64)-1)/3)+1&YEAR(AF64)&#REF!&T64) | AN64: =IF(K64="","","Q"&INT((MONTH(K64)-1)/3)+1&YEAR(K64)&#REF!) -> #REF!
A65: 63 | B65: BHA | C65: Shining Star | D65: Mobile Clinic | E65: Mandalay | F65: Amarapura | H65: Myit Too | I65: Village | K65: 46037 | L65: 63 | M65: =IF(phc_8[[#This Row],[Register No.]]="","",C65&"-"&D65&"-"&"BHA-PHC-"&phc_8[[#This Row],[Register No.]]) -> Shining Star-Mobile Clinic-BHA-PHC-63 | N65: New | O65: Ma Phue Pyae Thazin | P65: 6 | S65: =IF(AND(ISBLANK(P65),ISBLANK(Q65),ISBLANK(R65))," ", IF(OR(P65<5,AND(P65=" ",Q65<>" ",R65<>" ")),"<5 yrs", IF(AND(P65>=5,P65<=14),"5 - 14 yrs", IF(AND(P65>=15,P65<=18),"15 - 18 yrs", IF(AND(P65>=19,P65<=49),"19 - 49 yrs","50 yrs +"))))) -> 5 - 14 yrs | T65: Female | U65: Myit Too | V65: U Nay Win Htun | W65: Viral | X65: Respiratory viral infection | Y65: =INDEX(info!$Y$2:$Y$192,MATCH(phc_8[[#This Row],[Sub_Category]],info!$X$2:$X$192,0)) -> ARI/RTI | Z65: {=INDEX(info!$AA$2:$AA$192,MATCH(PHC!$X65&PHC!$Y65,info!$X$2:$X$192&info!$Y$2:$Y$192,0))} -> Communicable disease | AA65: PB Vita | AB65: No | AC65: No | AD65: No | AE65: No | AK65: No | AM65: =IF(AF65="","","Q"&INT((MONTH(AF65)-1)/3)+1&YEAR(AF65)&#REF!&T65) | AN65: =IF(K65="","","Q"&INT((MONTH(K65)-1)/3)+1&YEAR(K65)&#REF!) -> #REF!
A66: 64 | B66: BHA | C66: Shining Star | D66: Mobile Clinic | E66: Mandalay | F66: Amarapura | H66: Myit Too | I66: Village | K66: 46037 | L66: 64 | M66: =IF(phc_8[[#This Row],[Register No.]]="","",C66&"-"&D66&"-"&"BHA-PHC-"&phc_8[[#This Row],[Register No.]]) -> Shining Star-Mobile Clinic-BHA-PHC-64 | N66: New | O66: Daw Myint Myint Moe | P66: 49 | S66: =IF(AND(ISBLANK(P66),ISBLANK(Q66),ISBLANK(R66))," ", IF(OR(P66<5,AND(P66=" ",Q66<>" ",R66<>" ")),"<5 yrs", IF(AND(P66>=5,P66<=14),"5 - 14 yrs", IF(AND(P66>=15,P66<=18),"15 - 18 yrs", IF(AND(P66>=19,P66<=49),"19 - 49 yrs","50 yrs +"))))) -> 19 - 49 yrs | T66: Female | U66: Myit Too | V66: U Kyaw Swe | W66: HT/DM | X66: DM | Y66: =INDEX(info!$Y$2:$Y$192,MATCH(phc_8[[#This Row],[Sub_Category]],info!$X$2:$X$192,0)) -> Chronic medical disease | Z66: {=INDEX(info!$AA$2:$AA$192,MATCH(PHC!$X66&PHC!$Y66,info!$X$2:$X$192&info!$Y$2:$Y$192,0))} -> Non-communicable disease | AA66: Amlo5, Metformin, Betex, Ato10 | AB66: No | AC66: No | AD66: No | AE66: No | AK66: No | AM66: =IF(AF66="","","Q"&INT((MONTH(AF66)-1)/3)+1&YEAR(AF66)&#REF!&T66) | AN66: =IF(K66="","","Q"&INT((MONTH(K66)-1)/3)+1&YEAR(K66)&#REF!) -> #REF!
A67: 65 | B67: BHA | C67: Shining Star | D67: Mobile Clinic | E67: Mandalay | F67: Amarapura | H67: Myit Too | I67: Village | K67: 46037 | L67: 65 | M67: =IF(phc_8[[#This Row],[Register No.]]="","",C67&"-"&D67&"-"&"BHA-PHC-"&phc_8[[#This Row],[Register No.]]) -> Shining Star-Mobile Clinic-BHA-PHC-65 | N67: New | O67: Ma Linn Latt Nyein | P67: 28 | S67: =IF(AND(ISBLANK(P67),ISBLANK(Q67),ISBLANK(R67))," ", IF(OR(P67<5,AND(P67=" ",Q67<>" ",R67<>" ")),"<5 yrs", IF(AND(P67>=5,P67<=14),"5 - 14 yrs", IF(AND(P67>=15,P67<=18),"15 - 18 yrs", IF(AND(P67>=19,P67<=49),"19 - 49 yrs","50 yrs +"))))) -> 19 - 49 yrs | T67: Female | U67: Myit Too | V67: U Mg Tin | W67: Weakness | X67: Weakness | Y67: =INDEX(info!$Y$2:$Y$192,MATCH(phc_8[[#This Row],[Sub_Category]],info!$X$2:$X$192,0)) -> Other (non-communicable) | Z67: {=INDEX(info!$AA$2:$AA$192,MATCH(PHC!$X67&PHC!$Y67,info!$X$2:$X$192&info!$Y$2:$Y$192,0))} -> Other | AA67: MV | AB67: No | AC67: No | AD67: No | AE67: No | AK67: No | AM67: =IF(AF67="","","Q"&INT((MONTH(AF67)-1)/3)+1&YEAR(AF67)&#REF!&T67) | AN67: =IF(K67="","","Q"&INT((MONTH(K67)-1)/3)+1&YEAR(K67)&#REF!) -> #REF!
A68: 66 | B68: BHA | C68: Shining Star | D68: Mobile Clinic | E68: Mandalay | F68: Amarapura | H68: Myit Too | I68: Village | K68: 46037 | L68: 66 | M68: =IF(phc_8[[#This Row],[Register No.]]="","",C68&"-"&D68&"-"&"BHA-PHC-"&phc_8[[#This Row],[Register No.]]) -> Shining Star-Mobile Clinic-BHA-PHC-66 | N68: New | O68: Mg Htoo Wai Htun | P68: 2 | S68: =IF(AND(ISBLANK(P68),ISBLANK(Q68),ISBLANK(R68))," ", IF(OR(P68<5,AND(P68=" ",Q68<>" ",R68<>" ")),"<5 yrs", IF(AND(P68>=5,P68<=14),"5 - 14 yrs", IF(AND(P68>=15,P68<=18),"15 - 18 yrs", IF(AND(P68>=19,P68<=49),"19 - 49 yrs","50 yrs +"))))) -> <5 yrs | T68: Male | U68: Myit Too | V68: U Thae Ko | W68: Viral | X68: Respiratory viral infection | Y68: =INDEX(info!$Y$2:$Y$192,MATCH(phc_8[[#This Row],[Sub_Category]],info!$X$2:$X$192,0)) -> ARI/RTI | Z68: {=INDEX(info!$AA$2:$AA$192,MATCH(PHC!$X68&PHC!$Y68,info!$X$2:$X$192&info!$Y$2:$Y$192,0))} -> Communicable disease | AA68: Zinc Syrup | AB68: No | AC68: No | AD68: No | AE68: No | AK68: No | AM68: =IF(AF68="","","Q"&INT((MONTH(AF68)-1)/3)+1&YEAR(AF68)&#REF!&T68) | AN68: =IF(K68="","","Q"&INT((MONTH(K68)-1)/3)+1&YEAR(K68)&#REF!) -> #REF!
... A74: 72 | B74: BHA | C74: Shining Star | D74: Mobile Clinic | E74: Mandalay | F74: Amarapura | H74: Myit Too | I74: Village | K74: 46037 | L74: 72 | M74: =IF(phc_8[[#This Row],[Register No.]]="","",C74&"-"&D74&"-"&"BHA-PHC-"&phc_8[[#This Row],[Register No.]]) -> Shining Star-Mobile Clinic-BHA-PHC-72 | N74: New | O74: Daw Lwin Mar Oo | P74: 58 | S74: =IF(AND(ISBLANK(P74),ISBLANK(Q74),ISBLANK(R74))," ", IF(OR(P74<5,AND(P74=" ",Q74<>" ",R74<>" ")),"<5 yrs", IF(AND(P74>=5,P74<=14),"5 - 14 yrs", IF(AND(P74>=15,P74<=18),"15 - 18 yrs", IF(AND(P74>=19,P74<=49),"19 - 49 yrs","50 yrs +"))))) -> 50 yrs + | T74: Female | U74: Myit Too | V74: U Htay | W74: HT | X74: Hypertension | Y74: =INDEX(info!$Y$2:$Y$192,MATCH(phc_8[[#This Row],[Sub_Category]],info!$X$2:$X$192,0)) -> Chronic medical disease | Z74: {=INDEX(info!$AA$2:$AA$192,MATCH(PHC!$X74&PHC!$Y74,info!$X$2:$X$192&info!$Y$2:$Y$192,0))} -> Non-communicable disease | AA74: Losar, Aldactone, Omex, Atenolol, Siloxogene | AB74: No | AC74: No | AD74: No | AE74: No | AK74: No | AM74: =IF(AF74="","","Q"&INT((MONTH(AF74)-1)/3)+1&YEAR(AF74)&#REF!&T74) | AN74: =IF(K74="","","Q"&INT((MONTH(K74)-1)/3)+1&YEAR(K74)&#REF!) -> #REF!
A75: 73 | B75: BHA | C75: Shining Star | D75: Mobile Clinic | E75: Mandalay | F75: Amarapura | H75: Myit Too | I75: Village | K75: 46037 | L75: 73 | M75: =IF(phc_8[[#This Row],[Register No.]]="","",C75&"-"&D75&"-"&"BHA-PHC-"&phc_8[[#This Row],[Register No.]]) -> Shining Star-Mobile Clinic-BHA-PHC-73 | N75: New | O75: Daw Naing Naing Latt | P75: 41 | S75: =IF(AND(ISBLANK(P75),ISBLANK(Q75),ISBLANK(R75))," ", IF(OR(P75<5,AND(P75=" ",Q75<>" ",R75<>" ")),"<5 yrs", IF(AND(P75>=5,P75<=14),"5 - 14 yrs", IF(AND(P75>=15,P75<=18),"15 - 18 yrs", IF(AND(P75>=19,P75<=49),"19 - 49 yrs","50 yrs +"))))) -> 19 - 49 yrs | T75: Female | U75: Myit Too | V75: U Min Naing | W75: Cervical Spondylosis | Y75: =INDEX(info!$Y$2:$Y$192,MATCH(phc_8[[#This Row],[Sub_Category]],info!$X$2:$X$192,0)) -> #N/A | Z75: {=INDEX(info!$AA$2:$AA$192,MATCH(PHC!$X75&PHC!$Y75,info!$X$2:$X$192&info!$Y$2:$Y$192,0))} -> #N/A | AA75: IV B12, Para, Cinnarizine, Betex | AB75: No | AC75: No | AD75: No | AE75: No | AK75: No | AM75: =IF(AF75="","","Q"&INT((MONTH(AF75)-1)/3)+1&YEAR(AF75)&#REF!&T75) | AN75: =IF(K75="","","Q"&INT((MONTH(K75)-1)/3)+1&YEAR(K75)&#REF!) -> #REF!
A76: 74 | B76: BHA | C76: Shining Star | D76: Mobile Clinic | E76: Mandalay | F76: Amarapura | H76: Myit Too | I76: Village | K76: 46037 | L76: 74 | M76: =IF(phc_8[[#This Row],[Register No.]]="","",C76&"-"&D76&"-"&"BHA-PHC-"&phc_8[[#This Row],[Register No.]]) -> Shining Star-Mobile Clinic-BHA-PHC-74 | N76: New | O76: Daw Pyone | P76: 56 | S76: =IF(AND(ISBLANK(P76),ISBLANK(Q76),ISBLANK(R76))," ", IF(OR(P76<5,AND(P76=" ",Q76<>" ",R76<>" ")),"<5 yrs", IF(AND(P76>=5,P76<=14),"5 - 14 yrs", IF(AND(P76>=15,P76<=18),"15 - 18 yrs", IF(AND(P76>=19,P76<=49),"19 - 49 yrs","50 yrs +"))))) -> 50 yrs + | T76: Female | U76: Myit Too | V76: U Kan Thar | W76: HT | X76: Hypertension | Y76: =INDEX(info!$Y$2:$Y$192,MATCH(phc_8[[#This Row],[Sub_Category]],info!$X$2:$X$192,0)) -> Chronic medical disease | Z76: {=INDEX(info!$AA$2:$AA$192,MATCH(PHC!$X76&PHC!$Y76,info!$X$2:$X$192&info!$Y$2:$Y$192,0))} -> Non-communicable disease | AA76: IM Diclo, MV, Para, Amlo5, Zinc | AB76: No | AC76: No | AD76: No | AE76: No | AK76: No | AM76: =IF(AF76="","","Q"&INT((MONTH(AF76)-1)/3)+1&YEAR(AF76)&#REF!&T76) | AN76: =IF(K76="","","Q"&INT((MONTH(K76)-1)/3)+1&YEAR(K76)&#REF!) -> #REF!
A77: 75 | B77: BHA | C77: Shining Star | D77: Mobile Clinic | E77: Mandalay | F77: Amarapura | H77: Myit Too | I77: Village | K77: 46037 | L77: 75 | M77: =IF(phc_8[[#This Row],[Register No.]]="","",C77&"-"&D77&"-"&"BHA-PHC-"&phc_8[[#This Row],[Register No.]]) -> Shining Star-Mobile Clinic-BHA-PHC-75 | N77: New | O77: Ma Nilar Aung | P77: 30 | S77: =IF(AND(ISBLANK(P77),ISBLANK(Q77),ISBLANK(R77))," ", IF(OR(P77<5,AND(P77=" ",Q77<>" ",R77<>" ")),"<5 yrs", IF(AND(P77>=5,P77<=14),"5 - 14 yrs", IF(AND(P77>=15,P77<=18),"15 - 18 yrs", IF(AND(P77>=19,P77<=49),"19 - 49 yrs","50 yrs +"))))) -> 19 - 49 yrs | T77: Female | U77: Myit Too | V77: U Soe Win | W77: Muscle Pain | X77: Muscle Pain | Y77: =INDEX(info!$Y$2:$Y$192,MATCH(phc_8[[#This Row],[Sub_Category]],info!$X$2:$X$192,0)) -> Other (non-communicable) | Z77: {=INDEX(info!$AA$2:$AA$192,MATCH(PHC!$X77&PHC!$Y77,info!$X$2:$X$192&info!$Y$2:$Y$192,0))} -> Other | AA77: IV B12, Gabapentin, Betex | AB77: No | AC77: No | AD77: No | AE77: No | AK77: No | AM77: =IF(AF77="","","Q"&INT((MONTH(AF77)-1)/3)+1&YEAR(AF77)&#REF!&T77) | AN77: =IF(K77="","","Q"&INT((MONTH(K77)-1)/3)+1&YEAR(K77)&#REF!) -> #REF!
A78: 76 | B78: BHA | C78: Shining Star | D78: Mobile Clinic | E78: Mandalay | F78: Amarapura | H78: Myit Too | I78: Village | K78: 46037 | L78: 76 | M78: =IF(phc_8[[#This Row],[Register No.]]="","",C78&"-"&D78&"-"&"BHA-PHC-"&phc_8[[#This Row],[Register No.]]) -> Shining Star-Mobile Clinic-BHA-PHC-76 | N78: New | O78: Mg Shine Min Thant | P78: 1 | Q78: 9 | S78: =IF(AND(ISBLANK(P78),ISBLANK(Q78),ISBLANK(R78))," ", IF(OR(P78<5,AND(P78=" ",Q78<>" ",R78<>" ")),"<5 yrs", IF(AND(P78>=5,P78<=14),"5 - 14 yrs", IF(AND(P78>=15,P78<=18),"15 - 18 yrs", IF(AND(P78>=19,P78<=49),"19 - 49 yrs","50 yrs +"))))) -> <5 yrs | T78: Male | U78: Myit Too | V78: U Nay Win Htun | W78: Viral | X78: Respiratory viral infection | Y78: =INDEX(info!$Y$2:$Y$192,MATCH(phc_8[[#This Row],[Sub_Category]],info!$X$2:$X$192,0)) -> ARI/RTI | Z78: {=INDEX(info!$AA$2:$AA$192,MATCH(PHC!$X78&PHC!$Y78,info!$X$2:$X$192&info!$Y$2:$Y$192,0))} -> Communicable disease | AA78: Zinc Syrup | AB78: No | AC78: No | AD78: No | AE78: No | AK78: No | AM78: =IF(AF78="","","Q"&INT((MONTH(AF78)-1)/3)+1&YEAR(AF78)&#REF!&T78) | AN78: =IF(K78="","","Q"&INT((MONTH(K78)-1)/3)+1&YEAR(K78)&#REF!) -> #REF!
A79: 77 | B79: BHA | C79: Shining Star | D79: Mobile Clinic | E79: Mandalay | F79: Amarapura | H79: Myit Too | I79: Village | K79: 46037 | L79: 77 | M79: =IF(phc_8[[#This Row],[Register No.]]="","",C79&"-"&D79&"-"&"BHA-PHC-"&phc_8[[#This Row],[Register No.]]) -> Shining Star-Mobile Clinic-BHA-PHC-77 | N79: New | O79: Daw Moh Moh San | P79: 58 | S79: =IF(AND(ISBLANK(P79),ISBLANK(Q79),ISBLANK(R79))," ", IF(OR(P79<5,AND(P79=" ",Q79<>" ",R79<>" ")),"<5 yrs", IF(AND(P79>=5,P79<=14),"5 - 14 yrs", IF(AND(P79>=15,P79<=18),"15 - 18 yrs", IF(AND(P79>=19,P79<=49),"19 - 49 yrs","50 yrs +"))))) -> 50 yrs + | T79: Female | U79: Myit Too | V79: U Kyaw Shein | W79: Back Pain | X79: Muscle Pain | Y79: =INDEX(info!$Y$2:$Y$192,MATCH(phc_8[[#This Row],[Sub_Category]],info!$X$2:$X$192,0)) -> Other (non-communicable) | Z79: {=INDEX(info!$AA$2:$AA$192,MATCH(PHC!$X79&PHC!$Y79,info!$X$2:$X$192&info!$Y$2:$Y$192,0))} -> Other | AA79: IV B12, Gabapentin, Ibu, Omex, Betex | AB79: No | AC79: No | AD79: No | AE79: No | AK79: No | AM79: =IF(AF79="","","Q"&INT((MONTH(AF79)-1)/3)+1&YEAR(AF79)&#REF!&T79) | AN79: =IF(K79="","","Q"&INT((MONTH(K79)-1)/3)+1&YEAR(K79)&#REF!) -> #REF!
A80: 78 | B80: BHA | C80: Shining Star | D80: Mobile Clinic | E80: Mandalay | F80: Amarapura | H80: Myit Too | I80: Village | K80: 46037 | L80: 78 | M80: =IF(phc_8[[#This Row],[Register No.]]="","",C80&"-"&D80&"-"&"BHA-PHC-"&phc_8[[#This Row],[Register No.]]) -> Shining Star-Mobile Clinic-BHA-PHC-78 | N80: New | O80: Daw Phwar Yin | P80: 95 | S80: =IF(AND(ISBLANK(P80),ISBLANK(Q80),ISBLANK(R80))," ", IF(OR(P80<5,AND(P80=" ",Q80<>" ",R80<>" ")),"<5 yrs", IF(AND(P80>=5,P80<=14),"5 - 14 yrs", IF(AND(P80>=15,P80<=18),"15 - 18 yrs", IF(AND(P80>=19,P80<=49),"19 - 49 yrs","50 yrs +"))))) -> 50 yrs + | T80: Female | U80: Myit Too | V80: U Bike | W80: COPD | X80: COPD | Y80: =INDEX(info!$Y$2:$Y$192,MATCH(phc_8[[#This Row],[Sub_Category]],info!$X$2:$X$192,0)) -> Chronic medical disease | Z80: {=INDEX(info!$AA$2:$AA$192,MATCH(PHC!$X80&PHC!$Y80,info!$X$2:$X$192&info!$Y$2:$Y$192,0))} -> Non-communicable disease | AA80: Betex, Salbutamol, Amlo5, Inhaler | AB80: No | AC80: No | AD80: No | AE80: No | AK80: No | AM80: =IF(AF80="","","Q"&INT((MONTH(AF80)-1)/3)+1&YEAR(AF80)&#REF!&T80) | AN80: =IF(K80="","","Q"&INT((MONTH(K80)-1)/3)+1&YEAR(K80)&#REF!) -> #REF!
A81: 79 | B81: BHA | C81: Shining Star | D81: Mobile Clinic | E81: Mandalay | F81: Amarapura | H81: Myit Too | I81: Village | K81: 46037 | L81: 79 | M81: =IF(phc_8[[#This Row],[Register No.]]="","",C81&"-"&D81&"-"&"BHA-PHC-"&phc_8[[#This Row],[Register No.]]) -> Shining Star-Mobile Clinic-BHA-PHC-79 | N81: New | O81: U Htay Myint | P81: 66 | S81: =IF(AND(ISBLANK(P81),ISBLANK(Q81),ISBLANK(R81))," ", IF(OR(P81<5,AND(P81=" ",Q81<>" ",R81<>" ")),"<5 yrs", IF(AND(P81>=5,P81<=14),"5 - 14 yrs", IF(AND(P81>=15,P81<=18),"15 - 18 yrs", IF(AND(P81>=19,P81<=49),"19 - 49 yrs","50 yrs +"))))) -> 50 yrs + | T81: Male | U81: Myit Too | W81: Chest Infection | X81: Chest Infection | Y81: =INDEX(info!$Y$2:$Y$192,MATCH(phc_8[[#This Row],[Sub_Category]],info!$X$2:$X$192,0)) -> ARI/RTI | Z81: {=INDEX(info!$AA$2:$AA$192,MATCH(PHC!$X81&PHC!$Y81,info!$X$2:$X$192&info!$Y$2:$Y$192,0))} -> Communicable disease | AA81: Lasix, Aldactone, Aspilet | AB81: No | AC81: No | AD81: No | AE81: No | AK81: No | AM81: =IF(AF81="","","Q"&INT((MONTH(AF81)-1)/3)+1&YEAR(AF81)&#REF!&T81) | AN81: =IF(K81="","","Q"&INT((MONTH(K81)-1)/3)+1&YEAR(K81)&#REF!) -> #REF!
A82: 80 | B82: BHA | C82: Shining Star | D82: Mobile Clinic | E82: Mandalay | F82: Amarapura | H82: Myit Too | I82: Village | K82: 46037 | L82: 80 | M82: =IF(phc_8[[#This Row],[Register No.]]="","",C82&"-"&D82&"-"&"BHA-PHC-"&phc_8[[#This Row],[Register No.]]) -> Shining Star-Mobile Clinic-BHA-PHC-80 | N82: New | O82: B' Tin Zar Myo | Q82: 3 | S82: =IF(AND(ISBLANK(P82),ISBLANK(Q82),ISBLANK(R82))," ", IF(OR(P82<5,AND(P82=" ",Q82<>" ",R82<>" ")),"<5 yrs", IF(AND(P82>=5,P82<=14),"5 - 14 yrs", IF(AND(P82>=15,P82<=18),"15 - 18 yrs", IF(AND(P82>=19,P82<=49),"19 - 49 yrs","50 yrs +"))))) -> <5 yrs | T82: Female | U82: Myit Too | V82: U Ye Mg | W82: ARI | X82: Common cold | Y82: =INDEX(info!$Y$2:$Y$192,MATCH(phc_8[[#This Row],[Sub_Category]],info!$X$2:$X$192,0)) -> ARI/RTI | Z82: {=INDEX(info!$AA$2:$AA$192,MATCH(PHC!$X82&PHC!$Y82,info!$X$2:$X$192&info!$Y$2:$Y$192,0))} -> Communicable disease | AA82: Cefixime SR, Baby Cough SR, B'ton | AB82: No | AC82: No | AD82: No | AE82: No | AK82: No | AM82: =IF(AF82="","","Q"&INT((MONTH(AF82)-1)/3)+1&YEAR(AF82)&#REF!&T82) | AN82: =IF(K82="","","Q"&INT((MONTH(K82)-1)/3)+1&YEAR(K82)&#REF!) -> #REF!
A83: 81 | B83: BHA | C83: Shining Star | D83: Mobile Clinic | E83: Mandalay | F83: Kyaukse | H83: Pann Khwar | I83: Village | K83: 46038 | L83: 1 | M83: =IF(phc_8[[#This Row],[Register No.]]="","",C83&"-"&D83&"-"&"BHA-PHC-"&phc_8[[#This Row],[Register No.]]) -> Shining Star-Mobile Clinic-BHA-PHC-1 | N83: New | O83: Daw Aung Gyi | P83: 70 | S83: =IF(AND(ISBLANK(P83),ISBLANK(Q83),ISBLANK(R83))," ", IF(OR(P83<5,AND(P83=" ",Q83<>" ",R83<>" ")),"<5 yrs", IF(AND(P83>=5,P83<=14),"5 - 14 yrs", IF(AND(P83>=15,P83<=18),"15 - 18 yrs", IF(AND(P83>=19,P83<=49),"19 - 49 yrs","50 yrs +"))))) -> 50 yrs + | T83: Female | U83: Pann Khwar | V83: U Hla Maw | W83: HT | X83: Hypertension | Y83: =INDEX(info!$Y$2:$Y$192,MATCH(phc_8[[#This Row],[Sub_Category]],info!$X$2:$X$192,0)) -> Chronic medical disease | Z83: {=INDEX(info!$AA$2:$AA$192,MATCH(PHC!$X83&PHC!$Y83,info!$X$2:$X$192&info!$Y$2:$Y$192,0))} -> Non-communicable disease | AA83: Amlo5, Ibu, Omex, MV | AB83: No | AC83: No | AD83: No | AE83: No | AK83: No | AM83: =IF(AF83="","","Q"&INT((MONTH(AF83)-1)/3)+1&YEAR(AF83)&#REF!&T83) | AN83: =IF(K83="","","Q"&INT((MONTH(K83)-1)/3)+1&YEAR(K83)&#REF!) -> #REF!
A84: 82 | B84: BHA | C84: Shining Star | D84: Mobile Clinic | E84: Mandalay | F84: Kyaukse | H84: Pann Khwar | I84: Village | K84: 46038 | L84: 2 | M84: =IF(phc_8[[#This Row],[Register No.]]="","",C84&"-"&D84&"-"&"BHA-PHC-"&phc_8[[#This Row],[Register No.]]) -> Shining Star-Mobile Clinic-BHA-PHC-2 | N84: New | O84: Daw Than Tint | P84: 72 | S84: =IF(AND(ISBLANK(P84),ISBLANK(Q84),ISBLANK(R84))," ", IF(OR(P84<5,AND(P84=" ",Q84<>" ",R84<>" ")),"<5 yrs", IF(AND(P84>=5,P84<=14),"5 - 14 yrs", IF(AND(P84>=15,P84<=18),"15 - 18 yrs", IF(AND(P84>=19,P84<=49),"19 - 49 yrs","50 yrs +"))))) -> 50 yrs + | T84: Female | U84: Pann Khwar | V84: U Thaung | W84: HT | X84: Hypertension | Y84: =INDEX(info!$Y$2:$Y$192,MATCH(phc_8[[#This Row],[Sub_Category]],info!$X$2:$X$192,0)) -> Chronic medical disease | Z84: {=INDEX(info!$AA$2:$AA$192,MATCH(PHC!$X84&PHC!$Y84,info!$X$2:$X$192&info!$Y$2:$Y$192,0))} -> Non-communicable disease | AA84: Ato10, Amlo10, Betex, Zinc | AB84: No | AC84: No | AD84: No | AE84: No | AK84: No | AM84: =IF(AF84="","","Q"&INT((MONTH(AF84)-1)/3)+1&YEAR(AF84)&#REF!&T84) | AN84: =IF(K84="","","Q"&INT((MONTH(K84)-1)/3)+1&YEAR(K84)&#REF!) -> #REF!
A85: 83 | B85: BHA | C85: Shining Star | D85: Mobile Clinic | E85: Mandalay | F85: Kyaukse | H85: Pann Khwar | I85: Village | K85: 46038 | L85: 3 | M85: =IF(phc_8[[#This Row],[Register No.]]="","",C85&"-"&D85&"-"&"BHA-PHC-"&phc_8[[#This Row],[Register No.]]) -> Shining Star-Mobile Clinic-BHA-PHC-3 | N85: New | O85: Daw Htoo | P85: 70 | S85: =IF(AND(ISBLANK(P85),ISBLANK(Q85),ISBLANK(R85))," ", IF(OR(P85<5,AND(P85=" ",Q85<>" ",R85<>" ")),"<5 yrs", IF(AND(P85>=5,P85<=14),"5 - 14 yrs", IF(AND(P85>=15,P85<=18),"15 - 18 yrs", IF(AND(P85>=19,P85<=49),"19 - 49 yrs","50 yrs +"))))) -> 50 yrs + | T85: Female | U85: Pann Khwar | V85: U Shinn | W85: HT | X85: Hypertension | Y85: =INDEX(info!$Y$2:$Y$192,MATCH(phc_8[[#This Row],[Sub_Category]],info!$X$2:$X$192,0)) -> Chronic medical disease | Z85: {=INDEX(info!$AA$2:$AA$192,MATCH(PHC!$X85&PHC!$Y85,info!$X$2:$X$192&info!$Y$2:$Y$192,0))} -> Non-communicable disease | AA85: IV 25%+B12, Amlo5, Betex, Zinc | AB85: No | AC85: No | AD85: No | AE85: No | AK85: No | AM85: =IF(AF85="","","Q"&INT((MONTH(AF85)-1)/3)+1&YEAR(AF85)&#REF!&T85) | AN85: =IF(K85="","","Q"&INT((MONTH(K85)-1)/3)+1&YEAR(K85)&#REF!) -> #REF!
A86: 84 | B86: BHA | C86: Shining Star | D86: Mobile Clinic | E86: Mandalay | F86: Kyaukse | H86: Pann Khwar | I86: Village | K86: 46038 | L86: 4 | M86: =IF(phc_8[[#This Row],[Register No.]]="","",C86&"-"&D86&"-"&"BHA-PHC-"&phc_8[[#This Row],[Register No.]]) -> Shining Star-Mobile Clinic-BHA-PHC-4 | N86: New | O86: Daw WinTin | P86: 60 | S86: =IF(AND(ISBLANK(P86),ISBLANK(Q86),ISBLANK(R86))," ", IF(OR(P86<5,AND(P86=" ",Q86<>" ",R86<>" ")),"<5 yrs", IF(AND(P86>=5,P86<=14),"5 - 14 yrs", IF(AND(P86>=15,P86<=18),"15 - 18 yrs", IF(AND(P86>=19,P86<=49),"19 - 49 yrs","50 yrs +"))))) -> 50 yrs + | T86: Female | U86: Pann Khwar | V86: U Ohnn | W86: left Sciatica | X86: Injuries | Y86: =INDEX(info!$Y$2:$Y$192,MATCH(phc_8[[#This Row],[Sub_Category]],info!$X$2:$X$192,0)) -> Accident/minor sugical and injuries | Z86: {=INDEX(info!$AA$2:$AA$192,MATCH(PHC!$X86&PHC!$Y86,info!$X$2:$X$192&info!$Y$2:$Y$192,0))} -> Injury related | AA86: Aceclo, Omex, Betex, Metformin, Gliclacide, Amlo5, Ato10 | AB86: No | AC86: No | AD86: No | AE86: No | AK86: No | AM86: =IF(AF86="","","Q"&INT((MONTH(AF86)-1)/3)+1&YEAR(AF86)&#REF!&T86) | AN86: =IF(K86="","","Q"&INT((MONTH(K86)-1)/3)+1&YEAR(K86)&#REF!) -> #REF!
A87: 85 | B87: BHA | C87: Shining Star | D87: Mobile Clinic | E87: Mandalay | F87: Kyaukse | H87: Pann Khwar | I87: Village | K87: 46038 | L87: 5 | M87: =IF(phc_8[[#This Row],[Register No.]]="","",C87&"-"&D87&"-"&"BHA-PHC-"&phc_8[[#This Row],[Register No.]]) -> Shining Star-Mobile Clinic-BHA-PHC-5 | N87: New | O87: U Thaung | P87: 67 | S87: =IF(AND(ISBLANK(P87),ISBLANK(Q87),ISBLANK(R87))," ", IF(OR(P87<5,AND(P87=" ",Q87<>" ",R87<>" ")),"<5 yrs", IF(AND(P87>=5,P87<=14),"5 - 14 yrs", IF(AND(P87>=15,P87<=18),"15 - 18 yrs", IF(AND(P87>=19,P87<=49),"19 - 49 yrs","50 yrs +"))))) -> 50 yrs + | T87: Male | U87: Pann Khwar | V87: U Ba Han | W87: COPD | X87: COPD | Y87: =INDEX(info!$Y$2:$Y$192,MATCH(phc_8[[#This Row],[Sub_Category]],info!$X$2:$X$192,0)) -> Chronic medical disease | Z87: {=INDEX(info!$AA$2:$AA$192,MATCH(PHC!$X87&PHC!$Y87,info!$X$2:$X$192&info!$Y$2:$Y$192,0))} -> Non-communicable disease | AA87: Deriphylline, Detusin, Para, MV, Ato10 | AB87: No | AC87: No | AD87: No | AE87: No | AK87: No | AM87: =IF(AF87="","","Q"&INT((MONTH(AF87)-1)/3)+1&YEAR(AF87)&#REF!&T87) | AN87: =IF(K87="","","Q"&INT((MONTH(K87)-1)/3)+1&YEAR(K87)&#REF!) -> #REF!
A88: 86 | B88: BHA | C88: Shining Star | D88: Mobile Clinic | E88: Mandalay | F88: Kyaukse | H88: Pann Khwar | I88: Village | K88: 46038 | L88: 6 | M88: =IF(phc_8[[#This Row],[Register No.]]="","",C88&"-"&D88&"-"&"BHA-PHC-"&phc_8[[#This Row],[Register No.]]) -> Shining Star-Mobile Clinic-BHA-PHC-6 | N88: New | O88: Daw Ohne Myaing | P88: 87 | S88: =IF(AND(ISBLANK(P88),ISBLANK(Q88),ISBLANK(R88))," ", IF(OR(P88<5,AND(P88=" ",Q88<>" ",R88<>" ")),"<5 yrs", IF(AND(P88>=5,P88<=14),"5 - 14 yrs", IF(AND(P88>=15,P88<=18),"15 - 18 yrs", IF(AND(P88>=19,P88<=49),"19 - 49 yrs","50 yrs +"))))) -> 50 yrs + | T88: Female | U88: Pann Khwar | V88: U Thar Kywel | W88: Abscess | X88: Abscess | Y88: =INDEX(info!$Y$2:$Y$192,MATCH(phc_8[[#This Row],[Sub_Category]],info!$X$2:$X$192,0)) -> Accident/minor sugical and injuries | Z88: {=INDEX(info!$AA$2:$AA$192,MATCH(PHC!$X88&PHC!$Y88,info!$X$2:$X$192&info!$Y$2:$Y$192,0))} -> Communicable disease | AA88: Dressing, Ampiclox, Para, VitC, Ca+ | AB88: No | AC88: No | AD88: No | AE88: No | AK88: No | AM88: =IF(AF88="","","Q"&INT((MONTH(AF88)-1)/3)+1&YEAR(AF88)&#REF!&T88) | AN88: =IF(K88="","","Q"&INT((MONTH(K88)-1)/3)+1&YEAR(K88)&#REF!) -> #REF!
A89: 87 | B89: BHA | C89: Shining Star | D89: Mobile Clinic | E89: Mandalay | F89: Kyaukse | H89: Pann Khwar | I89: Village | K89: 46038 | L89: 7 | M89: =IF(phc_8[[#This Row],[Register No.]]="","",C89&"-"&D89&"-"&"BHA-PHC-"&phc_8[[#This Row],[Register No.]]) -> Shining Star-Mobile Clinic-BHA-PHC-7 | N89: New | O89: Daw Than Aye | P89: 59 | S89: =IF(AND(ISBLANK(P89),ISBLANK(Q89),ISBLANK(R89))," ", IF(OR(P89<5,AND(P89=" ",Q89<>" ",R89<>" ")),"<5 yrs", IF(AND(P89>=5,P89<=14),"5 - 14 yrs", IF(AND(P89>=15,P89<=18),"15 - 18 yrs", IF(AND(P89>=19,P89<=49),"19 - 49 yrs","50 yrs +"))))) -> 50 yrs + | T89: Female | U89: Pann Khwar | V89: U Tin Oo | W89: Heart Disease | X89: Heart Disease | Y89: =INDEX(info!$Y$2:$Y$192,MATCH(phc_8[[#This Row],[Sub_Category]],info!$X$2:$X$192,0)) -> Chronic medical disease | Z89: {=INDEX(info!$AA$2:$AA$192,MATCH(PHC!$X89&PHC!$Y89,info!$X$2:$X$192&info!$Y$2:$Y$192,0))} -> Non-communicable disease | AA89: Aspilet, Losar, Ato 10, Cardivas | AB89: No | AC89: No | AD89: No | AE89: No | AK89: No | AM89: =IF(AF89="","","Q"&INT((MONTH(AF89)-1)/3)+1&YEAR(AF89)&#REF!&T89) | AN89: =IF(K89="","","Q"&INT((MONTH(K89)-1)/3)+1&YEAR(K89)&#REF!) -> #REF!
A90: 88 | B90: BHA | C90: Shining Star | D90: Mobile Clinic | E90: Mandalay | F90: Kyaukse | H90: Pann Khwar | I90: Village | K90: 46038 | L90: 8 | M90: =IF(phc_8[[#This Row],[Register No.]]="","",C90&"-"&D90&"-"&"BHA-PHC-"&phc_8[[#This Row],[Register No.]]) -> Shining Star-Mobile Clinic-BHA-PHC-8 | N90: New | O90: Daw Hla Kyin | P90: 73 | S90: =IF(AND(ISBLANK(P90),ISBLANK(Q90),ISBLANK(R90))," ", IF(OR(P90<5,AND(P90=" ",Q90<>" ",R90<>" ")),"<5 yrs", IF(AND(P90>=5,P90<=14),"5 - 14 yrs", IF(AND(P90>=15,P90<=18),"15 - 18 yrs", IF(AND(P90>=19,P90<=49),"19 - 49 yrs","50 yrs +"))))) -> 50 yrs + | T90: Female | U90: Pann Khwar | V90: U Thura | W90: Muscle Pain | X90: Muscle Pain | Y90: =INDEX(info!$Y$2:$Y$192,MATCH(phc_8[[#This Row],[Sub_Category]],info!$X$2:$X$192,0)) -> Other (non-communicable) | Z90: {=INDEX(info!$AA$2:$AA$192,MATCH(PHC!$X90&PHC!$Y90,info!$X$2:$X$192&info!$Y$2:$Y$192,0))} -> Other | AA90: IV B12, Para, Cinnarizine, MV | AB90: No | AC90: No | AD90: No | AE90: No | AK90: No | AM90: =IF(AF90="","","Q"&INT((MONTH(AF90)-1)/3)+1&YEAR(AF90)&#REF!&T90) | AN90: =IF(K90="","","Q"&INT((MONTH(K90)-1)/3)+1&YEAR(K90)&#REF!) -> #REF!
A91: 89 | B91: BHA | C91: Shining Star | D91: Mobile Clinic | E91: Mandalay | F91: Kyaukse | H91: Pann Khwar | I91: Village | K91: 46038 | L91: 9 | M91: =IF(phc_8[[#This Row],[Register No.]]="","",C91&"-"&D91&"-"&"BHA-PHC-"&phc_8[[#This Row],[Register No.]]) -> Shining Star-Mobile Clinic-BHA-PHC-9 | N91: New | O91: U Yay Baw | P91: 63 | S91: =IF(AND(ISBLANK(P91),ISBLANK(Q91),ISBLANK(R91))," ", IF(OR(P91<5,AND(P91=" ",Q91<>" ",R91<>" ")),"<5 yrs", IF(AND(P91>=5,P91<=14),"5 - 14 yrs", IF(AND(P91>=15,P91<=18),"15 - 18 yrs", IF(AND(P91>=19,P91<=49),"19 - 49 yrs","50 yrs +"))))) -> 50 yrs + | T91: Male | U91: Pann Khwar | V91: U Myint | W91: Hypertension with storke | X91: Stroke | Y91: =INDEX(info!$Y$2:$Y$192,MATCH(phc_8[[#This Row],[Sub_Category]],info!$X$2:$X$192,0)) -> Stroke | Z91: {=INDEX(info!$AA$2:$AA$192,MATCH(PHC!$X91&PHC!$Y91,info!$X$2:$X$192&info!$Y$2:$Y$192,0))} -> Non-communicable disease | AA91: Amlo10, Ato 10, MV | AB91: No | AC91: No | AD91: No | AE91: No | AK91: No | AM91: =IF(AF91="","","Q"&INT((MONTH(AF91)-1)/3)+1&YEAR(AF91)&#REF!&T91) | AN91: =IF(K91="","","Q"&INT((MONTH(K91)-1)/3)+1&YEAR(K91)&#REF!) -> #REF!
A92: 90 | B92: BHA | C92: Shining Star | D92: Mobile Clinic | E92: Mandalay | F92: Kyaukse | H92: Pann Khwar | I92: Village | K92: 46038 | L92: 10 | M92: =IF(phc_8[[#This Row],[Register No.]]="","",C92&"-"&D92&"-"&"BHA-PHC-"&phc_8[[#This Row],[Register No.]]) -> Shining Star-Mobile Clinic-BHA-PHC-10 | N92: New | O92: U Tay Zani Ya | P92: 56 | S92: =IF(AND(ISBLANK(P92),ISBLANK(Q92),ISBLANK(R92))," ", IF(OR(P92<5,AND(P92=" ",Q92<>" ",R92<>" ")),"<5 yrs", IF(AND(P92>=5,P92<=14),"5 - 14 yrs", IF(AND(P92>=15,P92<=18),"15 - 18 yrs", IF(AND(P92>=19,P92<=49),"19 - 49 yrs","50 yrs +"))))) -> 50 yrs + | T92: Male | U92: Pann Khwar | V92: U Bo Ni | W92: Flu with high fever | X92: Flu with high fever | Y92: =INDEX(info!$Y$2:$Y$192,MATCH(phc_8[[#This Row],[Sub_Category]],info!$X$2:$X$192,0)) -> ARI/RTI | Z92: {=INDEX(info!$AA$2:$AA$192,MATCH(PHC!$X92&PHC!$Y92,info!$X$2:$X$192&info!$Y$2:$Y$192,0))} -> Communicable disease | AA92: IM Diclo, Para, Cetrizine, Presco, VitC, Azithro | AB92: No | AC92: No | AD92: No | AE92: No | AK92: No | AM92: =IF(AF92="","","Q"&INT((MONTH(AF92)-1)/3)+1&YEAR(AF92)&#REF!&T92) | AN92: =IF(K92="","","Q"&INT((MONTH(K92)-1)/3)+1&YEAR(K92)&#REF!) -> #REF!
A93: 91 | B93: BHA | C93: Shining Star | D93: Mobile Clinic | E93: Mandalay | F93: Kyaukse | H93: Pann Khwar | I93: Village | K93: 46038 | L93: 11 | M93: =IF(phc_8[[#This Row],[Register No.]]="","",C93&"-"&D93&"-"&"BHA-PHC-"&phc_8[[#This Row],[Register No.]]) -> Shining Star-Mobile Clinic-BHA-PHC-11 | N93: New | O93: Ma Mee Mee | P93: 31 | S93: =IF(AND(ISBLANK(P93),ISBLANK(Q93),ISBLANK(R93))," ", IF(OR(P93<5,AND(P93=" ",Q93<>" ",R93<>" ")),"<5 yrs", IF(AND(P93>=5,P93<=14),"5 - 14 yrs", IF(AND(P93>=15,P93<=18),"15 - 18 yrs", IF(AND(P93>=19,P93<=49),"19 - 49 yrs","50 yrs +"))))) -> 19 - 49 yrs | T93: Female | U93: Pann Khwar | V93: U Mg Thant | W93: Ortits | X93: Otitis media | Y93: =INDEX(info!$Y$2:$Y$192,MATCH(phc_8[[#This Row],[Sub_Category]],info!$X$2:$X$192,0)) -> Ear problem/disease | Z93: {=INDEX(info!$AA$2:$AA$192,MATCH(PHC!$X93&PHC!$Y93,info!$X$2:$X$192&info!$Y$2:$Y$192,0))} -> Communicable disease | AA93: IM Diclo, Ibu, Betex, Cifram, Gentamycin ear drop | AB93: No | AC93: No | AD93: No | AE93: No | AK93: No | AM93: =IF(AF93="","","Q"&INT((MONTH(AF93)-1)/3)+1&YEAR(AF93)&#REF!&T93) | AN93: =IF(K93="","","Q"&INT((MONTH(K93)-1)/3)+1&YEAR(K93)&#REF!) -> #REF!
A94: 92 | B94: BHA | C94: Shining Star | D94: Mobile Clinic | E94: Mandalay | F94: Kyaukse | H94: Pann Khwar | I94: Village | K94: 46038 | L94: 12 | M94: =IF(phc_8[[#This Row],[Register No.]]="","",C94&"-"&D94&"-"&"BHA-PHC-"&phc_8[[#This Row],[Register No.]]) -> Shining Star-Mobile Clinic-BHA-PHC-12 | N94: New | O94: Shin Thaw Ma Nanda | P94: 17 | S94: =IF(AND(ISBLANK(P94),ISBLANK(Q94),ISBLANK(R94))," ", IF(OR(P94<5,AND(P94=" ",Q94<>" ",R94<>" ")),"<5 yrs", IF(AND(P94>=5,P94<=14),"5 - 14 yrs", IF(AND(P94>=15,P94<=18),"15 - 18 yrs", IF(AND(P94>=19,P94<=49),"19 - 49 yrs","50 yrs +"))))) -> 15 - 18 yrs | T94: Male | U94: Pann Khwar | V94: U Cho | W94: Gastritis | X94: Gastritis | Y94: =INDEX(info!$Y$2:$Y$192,MATCH(phc_8[[#This Row],[Sub_Category]],info!$X$2:$X$192,0)) -> GI problem | Z94: {=INDEX(info!$AA$2:$AA$192,MATCH(PHC!$X94&PHC!$Y94,info!$X$2:$X$192&info!$Y$2:$Y$192,0))} -> Non-communicable disease | AA94: IV Pantocid, ORS, Pantocid, Zinc, Air X | AB94: No | AC94: No | AD94: No | AE94: No | AK94: No | AM94: =IF(AF94="","","Q"&INT((MONTH(AF94)-1)/3)+1&YEAR(AF94)&#REF!&T94) | AN94: =IF(K94="","","Q"&INT((MONTH(K94)-1)/3)+1&YEAR(K94)&#REF!) -> #REF!
... A104: 102 | B104: BHA | C104: Shining Star | D104: Mobile Clinic | E104: Mandalay | F104: Kyaukse | H104: Pann Khwar | I104: Village | K104: 46038 | L104: 22 | M104: =IF(phc_8[[#This Row],[Register No.]]="","",C104&"-"&D104&"-"&"BHA-PHC-"&phc_8[[#This Row],[Register No.]]) -> Shining Star-Mobile Clinic-BHA-PHC-22 | N104: New | O104: Daw Gyan Bone | P104: 90 | S104: =IF(AND(ISBLANK(P104),ISBLANK(Q104),ISBLANK(R104))," ", IF(OR(P104<5,AND(P104=" ",Q104<>" ",R104<>" ")),"<5 yrs", IF(AND(P104>=5,P104<=14),"5 - 14 yrs", IF(AND(P104>=15,P104<=18),"15 - 18 yrs", IF(AND(P104>=19,P104<=49),"19 - 49 yrs","50 yrs +"))))) -> 50 yrs + | T104: Female | U104: Pann Khwar | V104: U Bo Gyi | W104: Chest Infection | X104: Chest Infection | Y104: =INDEX(info!$Y$2:$Y$192,MATCH(phc_8[[#This Row],[Sub_Category]],info!$X$2:$X$192,0)) -> ARI/RTI | Z104: {=INDEX(info!$AA$2:$AA$192,MATCH(PHC!$X104&PHC!$Y104,info!$X$2:$X$192&info!$Y$2:$Y$192,0))} -> Communicable disease | AA104: Azithro, Bronhexine, Cevit, Amlo5 | AB104: No | AC104: No | AD104: No | AE104: No | AK104: No | AM104: =IF(AF104="","","Q"&INT((MONTH(AF104)-1)/3)+1&YEAR(AF104)&#REF!&T104) | AN104: =IF(K104="","","Q"&INT((MONTH(K104)-1)/3)+1&YEAR(K104)&#REF!) -> #REF!
A105: 103 | B105: BHA | C105: Shining Star | D105: Mobile Clinic | E105: Mandalay | F105: Kyaukse | H105: Pann Khwar | I105: Village | K105: 46038 | L105: 23 | M105: =IF(phc_8[[#This Row],[Register No.]]="","",C105&"-"&D105&"-"&"BHA-PHC-"&phc_8[[#This Row],[Register No.]]) -> Shining Star-Mobile Clinic-BHA-PHC-23 | N105: New | O105: U Phoe Wine | P105: 70 | S105: =IF(AND(ISBLANK(P105),ISBLANK(Q105),ISBLANK(R105))," ", IF(OR(P105<5,AND(P105=" ",Q105<>" ",R105<>" ")),"<5 yrs", IF(AND(P105>=5,P105<=14),"5 - 14 yrs", IF(AND(P105>=15,P105<=18),"15 - 18 yrs", IF(AND(P105>=19,P105<=49),"19 - 49 yrs","50 yrs +"))))) -> 50 yrs + | T105: Male | U105: Pann Khwar | V105: U Kyi | W105: Gout | Y105: =INDEX(info!$Y$2:$Y$192,MATCH(phc_8[[#This Row],[Sub_Category]],info!$X$2:$X$192,0)) -> #N/A | Z105: {=INDEX(info!$AA$2:$AA$192,MATCH(PHC!$X105&PHC!$Y105,info!$X$2:$X$192&info!$Y$2:$Y$192,0))} -> #N/A | AA105: Allopurinol, Aceclo, Omex, Amlo5, Betex | AB105: No | AC105: No | AD105: No | AE105: No | AK105: No | AM105: =IF(AF105="","","Q"&INT((MONTH(AF105)-1)/3)+1&YEAR(AF105)&#REF!&T105) | AN105: =IF(K105="","","Q"&INT((MONTH(K105)-1)/3)+1&YEAR(K105)&#REF!) -> #REF!
A106: 104 | B106: BHA | C106: Shining Star | D106: Mobile Clinic | E106: Mandalay | F106: Kyaukse | H106: Pann Khwar | I106: Village | K106: 46038 | L106: 24 | M106: =IF(phc_8[[#This Row],[Register No.]]="","",C106&"-"&D106&"-"&"BHA-PHC-"&phc_8[[#This Row],[Register No.]]) -> Shining Star-Mobile Clinic-BHA-PHC-24 | N106: New | O106: Daw Han Shinn | P106: 70 | S106: =IF(AND(ISBLANK(P106),ISBLANK(Q106),ISBLANK(R106))," ", IF(OR(P106<5,AND(P106=" ",Q106<>" ",R106<>" ")),"<5 yrs", IF(AND(P106>=5,P106<=14),"5 - 14 yrs", IF(AND(P106>=15,P106<=18),"15 - 18 yrs", IF(AND(P106>=19,P106<=49),"19 - 49 yrs","50 yrs +"))))) -> 50 yrs + | T106: Female | U106: Pann Khwar | V106: U Htun Hla | W106: Chest Infection | X106: Chest Infection | Y106: =INDEX(info!$Y$2:$Y$192,MATCH(phc_8[[#This Row],[Sub_Category]],info!$X$2:$X$192,0)) -> ARI/RTI | Z106: {=INDEX(info!$AA$2:$AA$192,MATCH(PHC!$X106&PHC!$Y106,info!$X$2:$X$192&info!$Y$2:$Y$192,0))} -> Communicable disease | AA106: Cetrizine, bronhexine, Amlo10 | AB106: No | AC106: No | AD106: No | AE106: No | AK106: No | AM106: =IF(AF106="","","Q"&INT((MONTH(AF106)-1)/3)+1&YEAR(AF106)&#REF!&T106) | AN106: =IF(K106="","","Q"&INT((MONTH(K106)-1)/3)+1&YEAR(K106)&#REF!) -> #REF!
A107: 105 | B107: BHA | C107: Shining Star | D107: Mobile Clinic | E107: Mandalay | F107: Kyaukse | H107: Pann Khwar | I107: Village | K107: 46038 | L107: 25 | M107: =IF(phc_8[[#This Row],[Register No.]]="","",C107&"-"&D107&"-"&"BHA-PHC-"&phc_8[[#This Row],[Register No.]]) -> Shining Star-Mobile Clinic-BHA-PHC-25 | N107: New | O107: Daw Thaung Shwe | P107: 88 | S107: =IF(AND(ISBLANK(P107),ISBLANK(Q107),ISBLANK(R107))," ", IF(OR(P107<5,AND(P107=" ",Q107<>" ",R107<>" ")),"<5 yrs", IF(AND(P107>=5,P107<=14),"5 - 14 yrs", IF(AND(P107>=15,P107<=18),"15 - 18 yrs", IF(AND(P107>=19,P107<=49),"19 - 49 yrs","50 yrs +"))))) -> 50 yrs + | T107: Female | U107: Pann Khwar | V107: U Hla Din | W107: HT | X107: Hypertension | Y107: =INDEX(info!$Y$2:$Y$192,MATCH(phc_8[[#This Row],[Sub_Category]],info!$X$2:$X$192,0)) -> Chronic medical disease | Z107: {=INDEX(info!$AA$2:$AA$192,MATCH(PHC!$X107&PHC!$Y107,info!$X$2:$X$192&info!$Y$2:$Y$192,0))} -> Non-communicable disease | AA107: Amlo5, MV, Ibu, Omex | AB107: No | AC107: No | AD107: No | AE107: No | AK107: No | AM107: =IF(AF107="","","Q"&INT((MONTH(AF107)-1)/3)+1&YEAR(AF107)&#REF!&T107) | AN107: =IF(K107="","","Q"&INT((MONTH(K107)-1)/3)+1&YEAR(K107)&#REF!) -> #REF!
A108: 106 | B108: BHA | C108: Shining Star | D108: Mobile Clinic | E108: Mandalay | F108: Kyaukse | H108: Pann Khwar | I108: Village | K108: 46038 | L108: 26 | M108: =IF(phc_8[[#This Row],[Register No.]]="","",C108&"-"&D108&"-"&"BHA-PHC-"&phc_8[[#This Row],[Register No.]]) -> Shining Star-Mobile Clinic-BHA-PHC-26 | N108: New | O108: U Nyar Na Wara | P108: 43 | S108: =IF(AND(ISBLANK(P108),ISBLANK(Q108),ISBLANK(R108))," ", IF(OR(P108<5,AND(P108=" ",Q108<>" ",R108<>" ")),"<5 yrs", IF(AND(P108>=5,P108<=14),"5 - 14 yrs", IF(AND(P108>=15,P108<=18),"15 - 18 yrs", IF(AND(P108>=19,P108<=49),"19 - 49 yrs","50 yrs +"))))) -> 19 - 49 yrs | T108: Male | U108: Pann Khwar | V108: U Saw Lwin | W108: Acute GE | X108: Acute diarrhoea | Y108: =INDEX(info!$Y$2:$Y$192,MATCH(phc_8[[#This Row],[Sub_Category]],info!$X$2:$X$192,0)) -> Diarrhoea/ GE | Z108: {=INDEX(info!$AA$2:$AA$192,MATCH(PHC!$X108&PHC!$Y108,info!$X$2:$X$192&info!$Y$2:$Y$192,0))} -> Communicable disease | AA108: Metformin, Metro, Cifram, FA, ORS | AB108: No | AC108: No | AD108: No | AE108: No | AK108: No | AM108: =IF(AF108="","","Q"&INT((MONTH(AF108)-1)/3)+1&YEAR(AF108)&#REF!&T108) | AN108: =IF(K108="","","Q"&INT((MONTH(K108)-1)/3)+1&YEAR(K108)&#REF!) -> #REF!
A109: 107 | B109: BHA | C109: Shining Star | D109: Mobile Clinic | E109: Mandalay | F109: Kyaukse | H109: Pann Khwar | I109: Village | K109: 46038 | L109: 27 | M109: =IF(phc_8[[#This Row],[Register No.]]="","",C109&"-"&D109&"-"&"BHA-PHC-"&phc_8[[#This Row],[Register No.]]) -> Shining Star-Mobile Clinic-BHA-PHC-27 | N109: New | O109: Daw Aye San | P109: 75 | S109: =IF(AND(ISBLANK(P109),ISBLANK(Q109),ISBLANK(R109))," ", IF(OR(P109<5,AND(P109=" ",Q109<>" ",R109<>" ")),"<5 yrs", IF(AND(P109>=5,P109<=14),"5 - 14 yrs", IF(AND(P109>=15,P109<=18),"15 - 18 yrs", IF(AND(P109>=19,P109<=49),"19 - 49 yrs","50 yrs +"))))) -> 50 yrs + | T109: Female | U109: Pann Khwar | V109: U Tote Phyo | W109: Rt shoulder pain | X109: Injuries | Y109: =INDEX(info!$Y$2:$Y$192,MATCH(phc_8[[#This Row],[Sub_Category]],info!$X$2:$X$192,0)) -> Accident/minor sugical and injuries | Z109: {=INDEX(info!$AA$2:$AA$192,MATCH(PHC!$X109&PHC!$Y109,info!$X$2:$X$192&info!$Y$2:$Y$192,0))} -> Injury related | AA109: Amlo5, Ibu, Omex, MV | AB109: No | AC109: No | AD109: No | AE109: No | AK109: No | AM109: =IF(AF109="","","Q"&INT((MONTH(AF109)-1)/3)+1&YEAR(AF109)&#REF!&T109) | AN109: =IF(K109="","","Q"&INT((MONTH(K109)-1)/3)+1&YEAR(K109)&#REF!) -> #REF!
A110: 108 | B110: BHA | C110: Shining Star | D110: Mobile Clinic | E110: Mandalay | F110: Kyaukse | H110: Pann Khwar | I110: Village | K110: 46038 | L110: 28 | M110: =IF(phc_8[[#This Row],[Register No.]]="","",C110&"-"&D110&"-"&"BHA-PHC-"&phc_8[[#This Row],[Register No.]]) -> Shining Star-Mobile Clinic-BHA-PHC-28 | N110: New | O110: U Zaw Ti Ka | P110: 53 | S110: =IF(AND(ISBLANK(P110),ISBLANK(Q110),ISBLANK(R110))," ", IF(OR(P110<5,AND(P110=" ",Q110<>" ",R110<>" ")),"<5 yrs", IF(AND(P110>=5,P110<=14),"5 - 14 yrs", IF(AND(P110>=15,P110<=18),"15 - 18 yrs", IF(AND(P110>=19,P110<=49),"19 - 49 yrs","50 yrs +"))))) -> 50 yrs + | T110: Male | U110: Pann Khwar | V110: U TinHla | W110: HT/DM | X110: Hypertension | Y110: =INDEX(info!$Y$2:$Y$192,MATCH(phc_8[[#This Row],[Sub_Category]],info!$X$2:$X$192,0)) -> Chronic medical disease | Z110: {=INDEX(info!$AA$2:$AA$192,MATCH(PHC!$X110&PHC!$Y110,info!$X$2:$X$192&info!$Y$2:$Y$192,0))} -> Non-communicable disease | AA110: Ato10, Amlo5, Allopurinol, Deriphylline, Aspilet | AB110: No | AC110: No | AD110: No | AE110: No | AK110: No | AM110: =IF(AF110="","","Q"&INT((MONTH(AF110)-1)/3)+1&YEAR(AF110)&#REF!&T110) | AN110: =IF(K110="","","Q"&INT((MONTH(K110)-1)/3)+1&YEAR(K110)&#REF!) -> #REF!
A111: 109 | B111: BHA | C111: Shining Star | D111: Mobile Clinic | E111: Mandalay | F111: Kyaukse | H111: Pann Khwar | I111: Village | K111: 46038 | L111: 29 | M111: =IF(phc_8[[#This Row],[Register No.]]="","",C111&"-"&D111&"-"&"BHA-PHC-"&phc_8[[#This Row],[Register No.]]) -> Shining Star-Mobile Clinic-BHA-PHC-29 | N111: New | O111: Daw Tin Kyi | P111: 70 | S111: =IF(AND(ISBLANK(P111),ISBLANK(Q111),ISBLANK(R111))," ", IF(OR(P111<5,AND(P111=" ",Q111<>" ",R111<>" ")),"<5 yrs", IF(AND(P111>=5,P111<=14),"5 - 14 yrs", IF(AND(P111>=15,P111<=18),"15 - 18 yrs", IF(AND(P111>=19,P111<=49),"19 - 49 yrs","50 yrs +"))))) -> 50 yrs + | T111: Female | U111: Pann Khwar | V111: U Hla Sein | W111: HT | X111: Hypertension | Y111: =INDEX(info!$Y$2:$Y$192,MATCH(phc_8[[#This Row],[Sub_Category]],info!$X$2:$X$192,0)) -> Chronic medical disease | Z111: {=INDEX(info!$AA$2:$AA$192,MATCH(PHC!$X111&PHC!$Y111,info!$X$2:$X$192&info!$Y$2:$Y$192,0))} -> Non-communicable disease | AA111: Amlo5, Para. Ca+, Betex, AirX | AB111: No | AC111: No | AD111: No | AE111: No | AK111: No | AM111: =IF(AF111="","","Q"&INT((MONTH(AF111)-1)/3)+1&YEAR(AF111)&#REF!&T111) | AN111: =IF(K111="","","Q"&INT((MONTH(K111)-1)/3)+1&YEAR(K111)&#REF!) -> #REF!
A112: 110 | B112: BHA | C112: Shining Star | D112: Mobile Clinic | E112: Mandalay | F112: Kyaukse | H112: Pann Khwar | I112: Village | K112: 46038 | L112: 30 | M112: =IF(phc_8[[#This Row],[Register No.]]="","",C112&"-"&D112&"-"&"BHA-PHC-"&phc_8[[#This Row],[Register No.]]) -> Shining Star-Mobile Clinic-BHA-PHC-30 | N112: New | O112: Daw Aye | P112: 79 | S112: =IF(AND(ISBLANK(P112),ISBLANK(Q112),ISBLANK(R112))," ", IF(OR(P112<5,AND(P112=" ",Q112<>" ",R112<>" ")),"<5 yrs", IF(AND(P112>=5,P112<=14),"5 - 14 yrs", IF(AND(P112>=15,P112<=18),"15 - 18 yrs", IF(AND(P112>=19,P112<=49),"19 - 49 yrs","50 yrs +"))))) -> 50 yrs + | T112: Female | U112: Pann Khwar | V112: U Hla Mg | W112: HT | X112: Hypertension | Y112: =INDEX(info!$Y$2:$Y$192,MATCH(phc_8[[#This Row],[Sub_Category]],info!$X$2:$X$192,0)) -> Chronic medical disease | Z112: {=INDEX(info!$AA$2:$AA$192,MATCH(PHC!$X112&PHC!$Y112,info!$X$2:$X$192&info!$Y$2:$Y$192,0))} -> Non-communicable disease | AA112: IV B12, Amlo5, Detusin, Betex | AB112: No | AC112: No | AD112: No | AE112: No | AK112: No | AM112: =IF(AF112="","","Q"&INT((MONTH(AF112)-1)/3)+1&YEAR(AF112)&#REF!&T112) | AN112: =IF(K112="","","Q"&INT((MONTH(K112)-1)/3)+1&YEAR(K112)&#REF!) -> #REF!
A113: 111 | B113: BHA | C113: Shining Star | D113: Mobile Clinic | E113: Mandalay | F113: Kyaukse | H113: Pann Khwar | I113: Village | K113: 46038 | L113: 31 | M113: =IF(phc_8[[#This Row],[Register No.]]="","",C113&"-"&D113&"-"&"BHA-PHC-"&phc_8[[#This Row],[Register No.]]) -> Shining Star-Mobile Clinic-BHA-PHC-31 | N113: New | O113: U Thaung Sein | P113: 78 | S113: =IF(AND(ISBLANK(P113),ISBLANK(Q113),ISBLANK(R113))," ", IF(OR(P113<5,AND(P113=" ",Q113<>" ",R113<>" ")),"<5 yrs", IF(AND(P113>=5,P113<=14),"5 - 14 yrs", IF(AND(P113>=15,P113<=18),"15 - 18 yrs", IF(AND(P113>=19,P113<=49),"19 - 49 yrs","50 yrs +"))))) -> 50 yrs + | T113: Male | U113: Pann Khwar | V113: U Than Myint | W113: Knee Jt Pain | X113: Injuries | Y113: =INDEX(info!$Y$2:$Y$192,MATCH(phc_8[[#This Row],[Sub_Category]],info!$X$2:$X$192,0)) -> Accident/minor sugical and injuries | Z113: {=INDEX(info!$AA$2:$AA$192,MATCH(PHC!$X113&PHC!$Y113,info!$X$2:$X$192&info!$Y$2:$Y$192,0))} -> Injury related | AA113: IM Diclo, Ibu, Para, Omex, MV | AB113: No | AC113: No | AD113: No | AE113: No | AK113: No | AM113: =IF(AF113="","","Q"&INT((MONTH(AF113)-1)/3)+1&YEAR(AF113)&#REF!&T113) | AN113: =IF(K113="","","Q"&INT((MONTH(K113)-1)/3)+1&YEAR(K113)&#REF!) -> #REF!
A114: 112 | B114: BHA | C114: Shining Star | D114: Mobile Clinic | E114: Mandalay | F114: Kyaukse | H114: Pann Khwar | I114: Village | K114: 46038 | L114: 32 | M114: =IF(phc_8[[#This Row],[Register No.]]="","",C114&"-"&D114&"-"&"BHA-PHC-"&phc_8[[#This Row],[Register No.]]) -> Shining Star-Mobile Clinic-BHA-PHC-32 | N114: New | O114: Daw Tin Ohne | P114: 64 | S114: =IF(AND(ISBLANK(P114),ISBLANK(Q114),ISBLANK(R114))," ", IF(OR(P114<5,AND(P114=" ",Q114<>" ",R114<>" ")),"<5 yrs", IF(AND(P114>=5,P114<=14),"5 - 14 yrs", IF(AND(P114>=15,P114<=18),"15 - 18 yrs", IF(AND(P114>=19,P114<=49),"19 - 49 yrs","50 yrs +"))))) -> 50 yrs + | T114: Female | U114: Pann Khwar | V114: U Chit Tin | W114: HT | X114: Hypertension | Y114: =INDEX(info!$Y$2:$Y$192,MATCH(phc_8[[#This Row],[Sub_Category]],info!$X$2:$X$192,0)) -> Chronic medical disease | Z114: {=INDEX(info!$AA$2:$AA$192,MATCH(PHC!$X114&PHC!$Y114,info!$X$2:$X$192&info!$Y$2:$Y$192,0))} -> Non-communicable disease | AA114: Amlo5, Myomas, Betex | AB114: No | AC114: No | AD114: No | AE114: No | AK114: No | AM114: =IF(AF114="","","Q"&INT((MONTH(AF114)-1)/3)+1&YEAR(AF114)&#REF!&T114) | AN114: =IF(K114="","","Q"&INT((MONTH(K114)-1)/3)+1&YEAR(K114)&#REF!) -> #REF!
A115: 113 | B115: BHA | C115: Shining Star | D115: Mobile Clinic | E115: Mandalay | F115: Kyaukse | H115: Pann Khwar | I115: Village | K115: 46038 | L115: 33 | M115: =IF(phc_8[[#This Row],[Register No.]]="","",C115&"-"&D115&"-"&"BHA-PHC-"&phc_8[[#This Row],[Register No.]]) -> Shining Star-Mobile Clinic-BHA-PHC-33 | N115: New | O115: Daw Nyo | P115: 67 | S115: =IF(AND(ISBLANK(P115),ISBLANK(Q115),ISBLANK(R115))," ", IF(OR(P115<5,AND(P115=" ",Q115<>" ",R115<>" ")),"<5 yrs", IF(AND(P115>=5,P115<=14),"5 - 14 yrs", IF(AND(P115>=15,P115<=18),"15 - 18 yrs", IF(AND(P115>=19,P115<=49),"19 - 49 yrs","50 yrs +"))))) -> 50 yrs + | T115: Female | U115: Pann Khwar | V115: U Ohne Khin | W115: HT | X115: Hypertension | Y115: =INDEX(info!$Y$2:$Y$192,MATCH(phc_8[[#This Row],[Sub_Category]],info!$X$2:$X$192,0)) -> Chronic medical disease | Z115: {=INDEX(info!$AA$2:$AA$192,MATCH(PHC!$X115&PHC!$Y115,info!$X$2:$X$192&info!$Y$2:$Y$192,0))} -> Non-communicable disease | AA115: Amlo5, Metformin, zinc | AB115: No | AC115: No | AD115: No | AE115: No | AK115: No | AM115: =IF(AF115="","","Q"&INT((MONTH(AF115)-1)/3)+1&YEAR(AF115)&#REF!&T115) | AN115: =IF(K115="","","Q"&INT((MONTH(K115)-1)/3)+1&YEAR(K115)&#REF!) -> #REF!
A116: 114 | B116: BHA | C116: Shining Star | D116: Mobile Clinic | E116: Mandalay | F116: Kyaukse | H116: Pann Khwar | I116: Village | K116: 46038 | L116: 34 | M116: =IF(phc_8[[#This Row],[Register No.]]="","",C116&"-"&D116&"-"&"BHA-PHC-"&phc_8[[#This Row],[Register No.]]) -> Shining Star-Mobile Clinic-BHA-PHC-34 | N116: New | O116: Daw Tin Thant | P116: 60 | S116: =IF(AND(ISBLANK(P116),ISBLANK(Q116),ISBLANK(R116))," ", IF(OR(P116<5,AND(P116=" ",Q116<>" ",R116<>" ")),"<5 yrs", IF(AND(P116>=5,P116<=14),"5 - 14 yrs", IF(AND(P116>=15,P116<=18),"15 - 18 yrs", IF(AND(P116>=19,P116<=49),"19 - 49 yrs","50 yrs +"))))) -> 50 yrs + | T116: Female | U116: Pann Khwar | V116: U Ohne Khin | W116: Muscle Pain | X116: Muscle Pain | Y116: =INDEX(info!$Y$2:$Y$192,MATCH(phc_8[[#This Row],[Sub_Category]],info!$X$2:$X$192,0)) -> Other (non-communicable) | Z116: {=INDEX(info!$AA$2:$AA$192,MATCH(PHC!$X116&PHC!$Y116,info!$X$2:$X$192&info!$Y$2:$Y$192,0))} -> Other | AA116: IM Diclo, Amlo5, Aceclo, Omex, Betex | AB116: No | AC116: No | AD116: No | AE116: No | AK116: No | AM116: =IF(AF116="","","Q"&INT((MONTH(AF116)-1)/3)+1&YEAR(AF116)&#REF!&T116) | AN116: =IF(K116="","","Q"&INT((MONTH(K116)-1)/3)+1&YEAR(K116)&#REF!) -> #REF!
A117: 115 | B117: BHA | C117: Shining Star | D117: Mobile Clinic | E117: Mandalay | F117: Kyaukse | H117: Pann Khwar | I117: Village | K117: 46038 | L117: 35 | M117: =IF(phc_8[[#This Row],[Register No.]]="","",C117&"-"&D117&"-"&"BHA-PHC-"&phc_8[[#This Row],[Register No.]]) -> Shining Star-Mobile Clinic-BHA-PHC-35 | N117: New | O117: Ma Ohne | P117: 53 | S117: =IF(AND(ISBLANK(P117),ISBLANK(Q117),ISBLANK(R117))," ", IF(OR(P117<5,AND(P117=" ",Q117<>" ",R117<>" ")),"<5 yrs", IF(AND(P117>=5,P117<=14),"5 - 14 yrs", IF(AND(P117>=15,P117<=18),"15 - 18 yrs", IF(AND(P117>=19,P117<=49),"19 - 49 yrs","50 yrs +"))))) -> 50 yrs + | T117: Female | U117: Pann Khwar | V117: U Kyi San | W117: HT | X117: Hypertension | Y117: =INDEX(info!$Y$2:$Y$192,MATCH(phc_8[[#This Row],[Sub_Category]],info!$X$2:$X$192,0)) -> Chronic medical disease | Z117: {=INDEX(info!$AA$2:$AA$192,MATCH(PHC!$X117&PHC!$Y117,info!$X$2:$X$192&info!$Y$2:$Y$192,0))} -> Non-communicable disease | AA117: Amlo5, MV | AB117: No | AC117: No | AD117: No | AE117: No | AK117: No | AM117: =IF(AF117="","","Q"&INT((MONTH(AF117)-1)/3)+1&YEAR(AF117)&#REF!&T117) | AN117: =IF(K117="","","Q"&INT((MONTH(K117)-1)/3)+1&YEAR(K117)&#REF!) -> #REF!
A118: 116 | B118: BHA | C118: Shining Star | D118: Mobile Clinic | E118: Mandalay | F118: Kyaukse | H118: Pann Khwar | I118: Village | K118: 46038 | L118: 36 | M118: =IF(phc_8[[#This Row],[Register No.]]="","",C118&"-"&D118&"-"&"BHA-PHC-"&phc_8[[#This Row],[Register No.]]) -> Shining Star-Mobile Clinic-BHA-PHC-36 | N118: New | O118: Daw Chaw | P118: 57 | S118: =IF(AND(ISBLANK(P118),ISBLANK(Q118),ISBLANK(R118))," ", IF(OR(P118<5,AND(P118=" ",Q118<>" ",R118<>" ")),"<5 yrs", IF(AND(P118>=5,P118<=14),"5 - 14 yrs", IF(AND(P118>=15,P118<=18),"15 - 18 yrs", IF(AND(P118>=19,P118<=49),"19 - 49 yrs","50 yrs +"))))) -> 50 yrs + | T118: Female | U118: Pann Khwar | V118: U Ohne | W118: HT | X118: Hypertension | Y118: =INDEX(info!$Y$2:$Y$192,MATCH(phc_8[[#This Row],[Sub_Category]],info!$X$2:$X$192,0)) -> Chronic medical disease | Z118: {=INDEX(info!$AA$2:$AA$192,MATCH(PHC!$X118&PHC!$Y118,info!$X$2:$X$192&info!$Y$2:$Y$192,0))} -> Non-communicable disease | AA118: IV B12, Amlo5, Para, Betex, Zinc | AB118: No | AC118: No | AD118: No | AE118: No | AK118: No | AM118: =IF(AF118="","","Q"&INT((MONTH(AF118)-1)/3)+1&YEAR(AF118)&#REF!&T118) | AN118: =IF(K118="","","Q"&INT((MONTH(K118)-1)/3)+1&YEAR(K118)&#REF!) -> #REF!
A119: 117 | B119: BHA | C119: Shining Star | D119: Mobile Clinic | E119: Mandalay | F119: Kyaukse | H119: Pann Khwar | I119: Village | K119: 46038 | L119: 37 | M119: =IF(phc_8[[#This Row],[Register No.]]="","",C119&"-"&D119&"-"&"BHA-PHC-"&phc_8[[#This Row],[Register No.]]) -> Shining Star-Mobile Clinic-BHA-PHC-37 | N119: New | O119: Daw Tin Hla | P119: 37 | S119: =IF(AND(ISBLANK(P119),ISBLANK(Q119),ISBLANK(R119))," ", IF(OR(P119<5,AND(P119=" ",Q119<>" ",R119<>" ")),"<5 yrs", IF(AND(P119>=5,P119<=14),"5 - 14 yrs", IF(AND(P119>=15,P119<=18),"15 - 18 yrs", IF(AND(P119>=19,P119<=49),"19 - 49 yrs","50 yrs +"))))) -> 19 - 49 yrs | T119: Female | U119: Pann Khwar | W119: Family Planning | Y119: =INDEX(info!$Y$2:$Y$192,MATCH(phc_8[[#This Row],[Sub_Category]],info!$X$2:$X$192,0)) -> #N/A | Z119: {=INDEX(info!$AA$2:$AA$192,MATCH(PHC!$X119&PHC!$Y119,info!$X$2:$X$192&info!$Y$2:$Y$192,0))} -> #N/A | AA119: Implant, Para, VitC | AB119: No | AC119: No | AD119: No | AE119: No | AK119: No | AM119: =IF(AF119="","","Q"&INT((MONTH(AF119)-1)/3)+1&YEAR(AF119)&#REF!&T119) | AN119: =IF(K119="","","Q"&INT((MONTH(K119)-1)/3)+1&YEAR(K119)&#REF!) -> #REF!
A120: 118 | B120: BHA | C120: Shining Star | D120: Mobile Clinic | E120: Mandalay | F120: Kyaukse | H120: Pann Khwar | I120: Village | K120: 46038 | L120: 38 | M120: =IF(phc_8[[#This Row],[Register No.]]="","",C120&"-"&D120&"-"&"BHA-PHC-"&phc_8[[#This Row],[Register No.]]) -> Shining Star-Mobile Clinic-BHA-PHC-38 | N120: New | O120: U Zaw Myint | P120: 66 | S120: =IF(AND(ISBLANK(P120),ISBLANK(Q120),ISBLANK(R120))," ", IF(OR(P120<5,AND(P120=" ",Q120<>" ",R120<>" ")),"<5 yrs", IF(AND(P120>=5,P120<=14),"5 - 14 yrs", IF(AND(P120>=15,P120<=18),"15 - 18 yrs", IF(AND(P120>=19,P120<=49),"19 - 49 yrs","50 yrs +"))))) -> 50 yrs + | T120: Male | U120: Pann Khwar | V120: U Pann | W120: HT | X120: Hypertension | Y120: =INDEX(info!$Y$2:$Y$192,MATCH(phc_8[[#This Row],[Sub_Category]],info!$X$2:$X$192,0)) -> Chronic medical disease | Z120: {=INDEX(info!$AA$2:$AA$192,MATCH(PHC!$X120&PHC!$Y120,info!$X$2:$X$192&info!$Y$2:$Y$192,0))} -> Non-communicable disease | AA120: Amlo10, Losar25, Betex, Ato10 | AB120: No | AC120: No | AD120: No | AE120: No | AK120: No | AM120: =IF(AF120="","","Q"&INT((MONTH(AF120)-1)/3)+1&YEAR(AF120)&#REF!&T120) | AN120: =IF(K120="","","Q"&INT((MONTH(K120)-1)/3)+1&YEAR(K120)&#REF!) -> #REF!
A121: 119 | B121: BHA | C121: Shining Star | D121: Mobile Clinic | E121: Mandalay | F121: Kyaukse | H121: Pann Khwar | I121: Village | K121: 46038 | L121: 39 | M121: =IF(phc_8[[#This Row],[Register No.]]="","",C121&"-"&D121&"-"&"BHA-PHC-"&phc_8[[#This Row],[Register No.]]) -> Shining Star-Mobile Clinic-BHA-PHC-39 | N121: New | O121: Ma Po Po Hlaing | P121: 21 | S121: =IF(AND(ISBLANK(P121),ISBLANK(Q121),ISBLANK(#REF!))," ", IF(OR(P121<5,AND(P121=" ",Q121<>" ",#REF!<>" ")),"<5 yrs", IF(AND(P121>=5,P121<=14),"5 - 14 yrs", IF(AND(P121>=15,P121<=18),"15 - 18 yrs", IF(AND(P121>=19,P121<=49),"19 - 49 yrs","50 yrs +"))))) -> #REF! | T121: Female | U121: Pann Khwar | V121: U Myint Hlaing | W121: AN Care | Y121: =INDEX(info!$Y$2:$Y$192,MATCH(phc_8[[#This Row],[Sub_Category]],info!$X$2:$X$192,0)) -> #N/A | Z121: {=INDEX(info!$AA$2:$AA$192,MATCH(PHC!$X121&PHC!$Y121,info!$X$2:$X$192&info!$Y$2:$Y$192,0))} -> #N/A | AA121: Folic acid, B1, MMN | AB121: No | AC121: No | AD121: No | AE121: No | AK121: No | AM121: =IF(AF121="","","Q"&INT((MONTH(AF121)-1)/3)+1&YEAR(AF121)&#REF!&T121) | AN121: =IF(K121="","","Q"&INT((MONTH(K121)-1)/3)+1&YEAR(K121)&#REF!) -> #REF!
A122: 120 | B122: BHA | C122: Shining Star | D122: Mobile Clinic | E122: Mandalay | F122: Kyaukse | H122: Pann Khwar | I122: Village | K122: 46038 | L122: 40 | M122: =IF(phc_8[[#This Row],[Register No.]]="","",C122&"-"&D122&"-"&"BHA-PHC-"&phc_8[[#This Row],[Register No.]]) -> Shining Star-Mobile Clinic-BHA-PHC-40 | N122: New | O122: Ma May Phue Wathan | R122: 17 | S122: =IF(AND(ISBLANK(P122),ISBLANK(Q122),ISBLANK(R122))," ", IF(OR(P122<5,AND(P122=" ",Q122<>" ",R122<>" ")),"<5 yrs", IF(AND(P122>=5,P122<=14),"5 - 14 yrs", IF(AND(P122>=15,P122<=18),"15 - 18 yrs", IF(AND(P122>=19,P122<=49),"19 - 49 yrs","50 yrs +"))))) -> <5 yrs | T122: Female | U122: Pann Khwar | V122: U Zin Yaw Oo | W122: Neonatal Care | Y122: =INDEX(info!$Y$2:$Y$192,MATCH(phc_8[[#This Row],[Sub_Category]],info!$X$2:$X$192,0)) -> #N/A | Z122: {=INDEX(info!$AA$2:$AA$192,MATCH(PHC!$X122&PHC!$Y122,info!$X$2:$X$192&info!$Y$2:$Y$192,0))} -> #N/A | AA122: Neonatal care | AB122: No | AC122: No | AD122: No | AE122: No | AK122: No | AM122: =IF(AF122="","","Q"&INT((MONTH(AF122)-1)/3)+1&YEAR(AF122)&#REF!&T122) | AN122: =IF(K122="","","Q"&INT((MONTH(K122)-1)/3)+1&YEAR(K122)&#REF!) -> #REF!
A123: 121 | B123: BHA | C123: Shining Star | D123: Mobile Clinic | E123: Mandalay | F123: Kyaukse | H123: Pann Khwar | I123: Village | K123: 46038 | L123: 41 | M123: =IF(phc_8[[#This Row],[Register No.]]="","",C123&"-"&D123&"-"&"BHA-PHC-"&phc_8[[#This Row],[Register No.]]) -> Shining Star-Mobile Clinic-BHA-PHC-41 | N123: New | O123: Daw Mya Mya | P123: 67 | S123: =IF(AND(ISBLANK(P123),ISBLANK(Q123),ISBLANK(R123))," ", IF(OR(P123<5,AND(P123=" ",Q123<>" ",R123<>" ")),"<5 yrs", IF(AND(P123>=5,P123<=14),"5 - 14 yrs", IF(AND(P123>=15,P123<=18),"15 - 18 yrs", IF(AND(P123>=19,P123<=49),"19 - 49 yrs","50 yrs +"))))) -> 50 yrs + | T123: Female | U123: Pann Khwar | V123: U Thaung Tin | W123: Eye Problem | X123: other eye problem | Y123: =INDEX(info!$Y$2:$Y$192,MATCH(phc_8[[#This Row],[Sub_Category]],info!$X$2:$X$192,0)) -> Eye problem/disease | Z123: {=INDEX(info!$AA$2:$AA$192,MATCH(PHC!$X123&PHC!$Y123,info!$X$2:$X$192&info!$Y$2:$Y$192,0))} -> Non-communicable disease | AA123: Betex, Zinc | AB123: No | AC123: No | AD123: No | AE123: No | AK123: No | AM123: =IF(AF123="","","Q"&INT((MONTH(AF123)-1)/3)+1&YEAR(AF123)&#REF!&T123) | AN123: =IF(K123="","","Q"&INT((MONTH(K123)-1)/3)+1&YEAR(K123)&#REF!) -> #REF!
A124: 122 | B124: BHA | C124: Shining Star | D124: Mobile Clinic | E124: Mandalay | F124: Kyaukse | H124: Pann Khwar | I124: Village | K124: 46038 | L124: 42 | M124: =IF(phc_8[[#This Row],[Register No.]]="","",C124&"-"&D124&"-"&"BHA-PHC-"&phc_8[[#This Row],[Register No.]]) -> Shining Star-Mobile Clinic-BHA-PHC-42 | N124: New | O124: Aye Mar Khaing | P124: 33 | S124: =IF(AND(ISBLANK(P124),ISBLANK(Q124),ISBLANK(R124))," ", IF(OR(P124<5,AND(P124=" ",Q124<>" ",R124<>" ")),"<5 yrs", IF(AND(P124>=5,P124<=14),"5 - 14 yrs", IF(AND(P124>=15,P124<=18),"15 - 18 yrs", IF(AND(P124>=19,P124<=49),"19 - 49 yrs","50 yrs +"))))) -> 19 - 49 yrs | T124: Female | U124: Pann Khwar | W124: Family Planning | Y124: =INDEX(info!$Y$2:$Y$192,MATCH(phc_8[[#This Row],[Sub_Category]],info!$X$2:$X$192,0)) -> #N/A | Z124: {=INDEX(info!$AA$2:$AA$192,MATCH(PHC!$X124&PHC!$Y124,info!$X$2:$X$192&info!$Y$2:$Y$192,0))} -> #N/A | AA124: Implant, Para, VitC | AB124: No | AC124: No | AD124: No | AE124: No | AK124: No | AM124: =IF(AF124="","","Q"&INT((MONTH(AF124)-1)/3)+1&YEAR(AF124)&#REF!&T124) | AN124: =IF(K124="","","Q"&INT((MONTH(K124)-1)/3)+1&YEAR(K124)&#REF!) -> #REF!
A125: 123 | B125: BHA | C125: Shining Star | D125: Mobile Clinic | E125: Mandalay | F125: Kyaukse | H125: Pann Khwar | I125: Village | K125: 46038 | L125: 43 | M125: =IF(phc_8[[#This Row],[Register No.]]="","",C125&"-"&D125&"-"&"BHA-PHC-"&phc_8[[#This Row],[Register No.]]) -> Shining Star-Mobile Clinic-BHA-PHC-43 | N125: New | O125: Daw Yin Ngway | P125: 67 | S125: =IF(AND(ISBLANK(P125),ISBLANK(Q125),ISBLANK(R125))," ", IF(OR(P125<5,AND(P125=" ",Q125<>" ",R125<>" ")),"<5 yrs", IF(AND(P125>=5,P125<=14),"5 - 14 yrs", IF(AND(P125>=15,P125<=18),"15 - 18 yrs", IF(AND(P125>=19,P125<=49),"19 - 49 yrs","50 yrs +"))))) -> 50 yrs + | T125: Female | U125: Pann Khwar | V125: U Htun Shein | W125: Weakness | X125: Weakness | Y125: =INDEX(info!$Y$2:$Y$192,MATCH(phc_8[[#This Row],[Sub_Category]],info!$X$2:$X$192,0)) -> Other (non-communicable) | Z125: {=INDEX(info!$AA$2:$AA$192,MATCH(PHC!$X125&PHC!$Y125,info!$X$2:$X$192&info!$Y$2:$Y$192,0))} -> Other | AA125: IV B12, Betex, Zinc | AB125: No | AC125: No | AD125: No | AE125: No | AK125: No | AM125: =IF(AF125="","","Q"&INT((MONTH(AF125)-1)/3)+1&YEAR(AF125)&#REF!&T125) | AN125: =IF(K125="","","Q"&INT((MONTH(K125)-1)/3)+1&YEAR(K125)&#REF!) -> #REF!
A126: 124 | B126: BHA | C126: Shining Star | D126: Mobile Clinic | E126: Mandalay | F126: Kyaukse | H126: Pann Khwar | I126: Village | K126: 46038 | L126: 44 | M126: =IF(phc_8[[#This Row],[Register No.]]="","",C126&"-"&D126&"-"&"BHA-PHC-"&phc_8[[#This Row],[Register No.]]) -> Shining Star-Mobile Clinic-BHA-PHC-44 | N126: New | O126: Daw Aye | P126: 47 | S126: =IF(AND(ISBLANK(P126),ISBLANK(Q126),ISBLANK(R126))," ", IF(OR(P126<5,AND(P126=" ",Q126<>" ",R126<>" ")),"<5 yrs", IF(AND(P126>=5,P126<=14),"5 - 14 yrs", IF(AND(P126>=15,P126<=18),"15 - 18 yrs", IF(AND(P126>=19,P126<=49),"19 - 49 yrs","50 yrs +"))))) -> 19 - 49 yrs | T126: Female | U126: Pann Khwar | V126: U Nyo Mg | W126: Weakness | X126: Weakness | Y126: =INDEX(info!$Y$2:$Y$192,MATCH(phc_8[[#This Row],[Sub_Category]],info!$X$2:$X$192,0)) -> Other (non-communicable) | Z126: {=INDEX(info!$AA$2:$AA$192,MATCH(PHC!$X126&PHC!$Y126,info!$X$2:$X$192&info!$Y$2:$Y$192,0))} -> Other | AA126: MV, Zinc | AB126: No | AC126: No | AD126: No | AE126: No | AK126: No | AM126: =IF(AF126="","","Q"&INT((MONTH(AF126)-1)/3)+1&YEAR(AF126)&#REF!&T126) | AN126: =IF(K126="","","Q"&INT((MONTH(K126)-1)/3)+1&YEAR(K126)&#REF!) -> #REF!
A127: 125 | B127: BHA | C127: Shining Star | D127: Mobile Clinic | E127: Mandalay | F127: Kyaukse | H127: Pann Khwar | I127: Village | K127: 46038 | L127: 45 | M127: =IF(phc_8[[#This Row],[Register No.]]="","",C127&"-"&D127&"-"&"BHA-PHC-"&phc_8[[#This Row],[Register No.]]) -> Shining Star-Mobile Clinic-BHA-PHC-45 | N127: New | O127: Daw Aye Thant | P127: 42 | S127: =IF(AND(ISBLANK(P127),ISBLANK(Q127),ISBLANK(R127))," ", IF(OR(P127<5,AND(P127=" ",Q127<>" ",R127<>" ")),"<5 yrs", IF(AND(P127>=5,P127<=14),"5 - 14 yrs", IF(AND(P127>=15,P127<=18),"15 - 18 yrs", IF(AND(P127>=19,P127<=49),"19 - 49 yrs","50 yrs +"))))) -> 19 - 49 yrs | T127: Female | U127: Pann Khwar | V127: U Chit Tote | W127: Back Pain | X127: Muscle Pain | Y127: =INDEX(info!$Y$2:$Y$192,MATCH(phc_8[[#This Row],[Sub_Category]],info!$X$2:$X$192,0)) -> Other (non-communicable) | Z127: {=INDEX(info!$AA$2:$AA$192,MATCH(PHC!$X127&PHC!$Y127,info!$X$2:$X$192&info!$Y$2:$Y$192,0))} -> Other | AA127: Zinc, MOM, Betex | AB127: No | AC127: No | AD127: No | AE127: No | AK127: No | AM127: =IF(AF127="","","Q"&INT((MONTH(AF127)-1)/3)+1&YEAR(AF127)&#REF!&T127) | AN127: =IF(K127="","","Q"&INT((MONTH(K127)-1)/3)+1&YEAR(K127)&#REF!) -> #REF!
A128: 126 | B128: BHA | C128: Shining Star | D128: Mobile Clinic | E128: Mandalay | F128: Kyaukse | H128: Pann Khwar | I128: Village | K128: 46038 | L128: 46 | M128: =IF(phc_8[[#This Row],[Register No.]]="","",C128&"-"&D128&"-"&"BHA-PHC-"&phc_8[[#This Row],[Register No.]]) -> Shining Star-Mobile Clinic-BHA-PHC-46 | N128: New | O128: Ma Hnin Nu Wai | P128: 8 | S128: =IF(AND(ISBLANK(P128),ISBLANK(Q128),ISBLANK(R128))," ", IF(OR(P128<5,AND(P128=" ",Q128<>" ",R128<>" ")),"<5 yrs", IF(AND(P128>=5,P128<=14),"5 - 14 yrs", IF(AND(P128>=15,P128<=18),"15 - 18 yrs", IF(AND(P128>=19,P128<=49),"19 - 49 yrs","50 yrs +"))))) -> 5 - 14 yrs | T128: Female | U128: Pann Khwar | V128: U Zaw Win Aung | W128: Flu | X128: Flu with high fever | Y128: =INDEX(info!$Y$2:$Y$192,MATCH(phc_8[[#This Row],[Sub_Category]],info!$X$2:$X$192,0)) -> ARI/RTI | Z128: {=INDEX(info!$AA$2:$AA$192,MATCH(PHC!$X128&PHC!$Y128,info!$X$2:$X$192&info!$Y$2:$Y$192,0))} -> Communicable disease | AA128: Para, PB Vita, Zinc, ORS | AB128: No | AC128: No | AD128: No | AE128: No | AK128: No | AM128: =IF(AF128="","","Q"&INT((MONTH(AF128)-1)/3)+1&YEAR(AF128)&#REF!&T128) | AN128: =IF(K128="","","Q"&INT((MONTH(K128)-1)/3)+1&YEAR(K128)&#REF!) -> #REF!
A129: 127 | B129: BHA | C129: Shining Star | D129: Mobile Clinic | E129: Mandalay | F129: Kyaukse | H129: Pann Khwar | I129: Village | K129: 46038 | L129: 47 | M129: =IF(phc_8[[#This Row],[Register No.]]="","",C129&"-"&D129&"-"&"BHA-PHC-"&phc_8[[#This Row],[Register No.]]) -> Shining Star-Mobile Clinic-BHA-PHC-47 | N129: New | O129: Daw Mya Shein | P129: 65 | S129: =IF(AND(ISBLANK(P129),ISBLANK(Q129),ISBLANK(R129))," ", IF(OR(P129<5,AND(P129=" ",Q129<>" ",R129<>" ")),"<5 yrs", IF(AND(P129>=5,P129<=14),"5 - 14 yrs", IF(AND(P129>=15,P129<=18),"15 - 18 yrs", IF(AND(P129>=19,P129<=49),"19 - 49 yrs","50 yrs +"))))) -> 50 yrs + | T129: Female | U129: Pann Khwar | V129: U Sein Win | W129: RT Parotid region pain | X129: Dental infections | Y129: =INDEX(info!$Y$2:$Y$192,MATCH(phc_8[[#This Row],[Sub_Category]],info!$X$2:$X$192,0)) -> Bacteria disease | Z129: {=INDEX(info!$AA$2:$AA$192,MATCH(PHC!$X129&PHC!$Y129,info!$X$2:$X$192&info!$Y$2:$Y$192,0))} -> Communicable disease | AA129: Amlo5, Para, Danzen, Cevit, Ampiclox | AB129: No | AC129: No | AD129: No | AE129: No | AK129: No | AM129: =IF(AF129="","","Q"&INT((MONTH(AF129)-1)/3)+1&YEAR(AF129)&#REF!&T129) | AN129: =IF(K129="","","Q"&INT((MONTH(K129)-1)/3)+1&YEAR(K129)&#REF!) -> #REF!
A130: 128 | B130: BHA | C130: Shining Star | D130: Mobile Clinic | E130: Mandalay | F130: Kyaukse | H130: Pann Khwar | I130: Village | K130: 46038 | L130: 48 | M130: =IF(phc_8[[#This Row],[Register No.]]="","",C130&"-"&D130&"-"&"BHA-PHC-"&phc_8[[#This Row],[Register No.]]) -> Shining Star-Mobile Clinic-BHA-PHC-48 | N130: New | O130: Daw Swe | P130: 48 | S130: =IF(AND(ISBLANK(P130),ISBLANK(Q130),ISBLANK(R130))," ", IF(OR(P130<5,AND(P130=" ",Q130<>" ",R130<>" ")),"<5 yrs", IF(AND(P130>=5,P130<=14),"5 - 14 yrs", IF(AND(P130>=15,P130<=18),"15 - 18 yrs", IF(AND(P130>=19,P130<=49),"19 - 49 yrs","50 yrs +"))))) -> 19 - 49 yrs | T130: Female | U130: Pann Khwar | V130: U Chit Naing | W130: Weakness | X130: Weakness | Y130: =INDEX(info!$Y$2:$Y$192,MATCH(phc_8[[#This Row],[Sub_Category]],info!$X$2:$X$192,0)) -> Other (non-communicable) | Z130: {=INDEX(info!$AA$2:$AA$192,MATCH(PHC!$X130&PHC!$Y130,info!$X$2:$X$192&info!$Y$2:$Y$192,0))} -> Other | AA130: Zinc,Para, MV | AB130: No | AC130: No | AD130: No | AE130: No | AK130: No | AM130: =IF(AF130="","","Q"&INT((MONTH(AF130)-1)/3)+1&YEAR(AF130)&#REF!&T130) | AN130: =IF(K130="","","Q"&INT((MONTH(K130)-1)/3)+1&YEAR(K130)&#REF!) -> #REF!
A131: 129 | B131: BHA | C131: Shining Star | D131: Mobile Clinic | E131: Mandalay | F131: Kyaukse | H131: Pann Khwar | I131: Village | K131: 46038 | L131: 49 | M131: =IF(phc_8[[#This Row],[Register No.]]="","",C131&"-"&D131&"-"&"BHA-PHC-"&phc_8[[#This Row],[Register No.]]) -> Shining Star-Mobile Clinic-BHA-PHC-49 | N131: New | O131: Daw Kyi Win | P131: 45 | S131: =IF(AND(ISBLANK(P131),ISBLANK(Q131),ISBLANK(R131))," ", IF(OR(P131<5,AND(P131=" ",Q131<>" ",R131<>" ")),"<5 yrs", IF(AND(P131>=5,P131<=14),"5 - 14 yrs", IF(AND(P131>=15,P131<=18),"15 - 18 yrs", IF(AND(P131>=19,P131<=49),"19 - 49 yrs","50 yrs +"))))) -> 19 - 49 yrs | T131: Female | U131: Pann Khwar | V131: U Toe Ni | W131: HT | X131: Hypertension | Y131: =INDEX(info!$Y$2:$Y$192,MATCH(phc_8[[#This Row],[Sub_Category]],info!$X$2:$X$192,0)) -> Chronic medical disease | Z131: {=INDEX(info!$AA$2:$AA$192,MATCH(PHC!$X131&PHC!$Y131,info!$X$2:$X$192&info!$Y$2:$Y$192,0))} -> Non-communicable disease | AA131: Amlo10, Ranitadine, Cetrizine, Metro | AB131: No | AC131: No | AD131: No | AE131: No | AK131: No | AM131: =IF(AF131="","","Q"&INT((MONTH(AF131)-1)/3)+1&YEAR(AF131)&#REF!&T131) | AN131: =IF(K131="","","Q"&INT((MONTH(K131)-1)/3)+1&YEAR(K131)&#REF!) -> #REF!
A132: 130 | B132: BHA | C132: Shining Star | D132: Mobile Clinic | E132: Mandalay | F132: Kyaukse | H132: Pann Khwar | I132: Village | K132: 46038 | L132: 50 | M132: =IF(phc_8[[#This Row],[Register No.]]="","",C132&"-"&D132&"-"&"BHA-PHC-"&phc_8[[#This Row],[Register No.]]) -> Shining Star-Mobile Clinic-BHA-PHC-50 | N132: New | O132: Ma Hla Myo Kywel | P132: 23 | S132: =IF(AND(ISBLANK(P132),ISBLANK(Q132),ISBLANK(R132))," ", IF(OR(P132<5,AND(P132=" ",Q132<>" ",R132<>" ")),"<5 yrs", IF(AND(P132>=5,P132<=14),"5 - 14 yrs", IF(AND(P132>=15,P132<=18),"15 - 18 yrs", IF(AND(P132>=19,P132<=49),"19 - 49 yrs","50 yrs +"))))) -> 19 - 49 yrs | T132: Female | U132: Pann Khwar | V132: U Than Win | W132: Polyuria | X132: UTI | Y132: =INDEX(info!$Y$2:$Y$192,MATCH(phc_8[[#This Row],[Sub_Category]],info!$X$2:$X$192,0)) -> Genito-urinary diseases | Z132: {=INDEX(info!$AA$2:$AA$192,MATCH(PHC!$X132&PHC!$Y132,info!$X$2:$X$192&info!$Y$2:$Y$192,0))} -> Communicable disease | AA132: Cifram, Genta ear drop, MV | AB132: No | AC132: No | AD132: No | AE132: No | AK132: No | AM132: =IF(AF132="","","Q"&INT((MONTH(AF132)-1)/3)+1&YEAR(AF132)&#REF!&T132) | AN132: =IF(K132="","","Q"&INT((MONTH(K132)-1)/3)+1&YEAR(K132)&#REF!) -> #REF!
A133: 131 | B133: BHA | C133: Shining Star | D133: Mobile Clinic | E133: Mandalay | F133: Kyaukse | H133: Pann Khwar | I133: Village | K133: 46038 | L133: 51 | M133: =IF(phc_8[[#This Row],[Register No.]]="","",C133&"-"&D133&"-"&"BHA-PHC-"&phc_8[[#This Row],[Register No.]]) -> Shining Star-Mobile Clinic-BHA-PHC-51 | N133: New | O133: Daw Than Myint | P133: 60 | S133: =IF(AND(ISBLANK(P133),ISBLANK(Q133),ISBLANK(R133))," ", IF(OR(P133<5,AND(P133=" ",Q133<>" ",R133<>" ")),"<5 yrs", IF(AND(P133>=5,P133<=14),"5 - 14 yrs", IF(AND(P133>=15,P133<=18),"15 - 18 yrs", IF(AND(P133>=19,P133<=49),"19 - 49 yrs","50 yrs +"))))) -> 50 yrs + | T133: Female | U133: Pann Khwar | V133: U Aung Thein | W133: Weakness | X133: Weakness | Y133: =INDEX(info!$Y$2:$Y$192,MATCH(phc_8[[#This Row],[Sub_Category]],info!$X$2:$X$192,0)) -> Other (non-communicable) | Z133: {=INDEX(info!$AA$2:$AA$192,MATCH(PHC!$X133&PHC!$Y133,info!$X$2:$X$192&info!$Y$2:$Y$192,0))} -> Other | AA133: IV B12, Betex, Ca+ | AB133: No | AC133: No | AD133: No | AE133: No | AK133: No | AM133: =IF(AF133="","","Q"&INT((MONTH(AF133)-1)/3)+1&YEAR(AF133)&#REF!&T133) | AN133: =IF(K133="","","Q"&INT((MONTH(K133)-1)/3)+1&YEAR(K133)&#REF!) -> #REF!
A134: 132 | B134: BHA | C134: Shining Star | D134: Mobile Clinic | E134: Mandalay | F134: Kyaukse | H134: Pann Khwar | I134: Village | K134: 46038 | L134: 52 | M134: =IF(phc_8[[#This Row],[Register No.]]="","",C134&"-"&D134&"-"&"BHA-PHC-"&phc_8[[#This Row],[Register No.]]) -> Shining Star-Mobile Clinic-BHA-PHC-52 | N134: New | O134: Daw Htay Kyi | P134: 68 | S134: =IF(AND(ISBLANK(P134),ISBLANK(Q134),ISBLANK(R134))," ", IF(OR(P134<5,AND(P134=" ",Q134<>" ",R134<>" ")),"<5 yrs", IF(AND(P134>=5,P134<=14),"5 - 14 yrs", IF(AND(P134>=15,P134<=18),"15 - 18 yrs", IF(AND(P134>=19,P134<=49),"19 - 49 yrs","50 yrs +"))))) -> 50 yrs + | T134: Female | U134: Pann Khwar | V134: U Maw | W134: Knee Jt Pain | X134: Injuries | Y134: =INDEX(info!$Y$2:$Y$192,MATCH(phc_8[[#This Row],[Sub_Category]],info!$X$2:$X$192,0)) -> Accident/minor sugical and injuries | Z134: {=INDEX(info!$AA$2:$AA$192,MATCH(PHC!$X134&PHC!$Y134,info!$X$2:$X$192&info!$Y$2:$Y$192,0))} -> Injury related | AA134: IV B12, Para, Ca+, Betex, Gabapentin | AB134: No | AC134: No | AD134: No | AE134: No | AK134: No | AM134: =IF(AF134="","","Q"&INT((MONTH(AF134)-1)/3)+1&YEAR(AF134)&#REF!&T134) | AN134: =IF(K134="","","Q"&INT((MONTH(K134)-1)/3)+1&YEAR(K134)&#REF!) -> #REF!
A135: 133 | B135: BHA | C135: Shining Star | D135: Mobile Clinic | E135: Mandalay | F135: Kyaukse | H135: Pann Khwar | I135: Village | K135: 46038 | L135: 53 | M135: =IF(phc_8[[#This Row],[Register No.]]="","",C135&"-"&D135&"-"&"BHA-PHC-"&phc_8[[#This Row],[Register No.]]) -> Shining Star-Mobile Clinic-BHA-PHC-53 | N135: New | O135: Daw Nyein | P135: 60 | S135: =IF(AND(ISBLANK(P135),ISBLANK(Q135),ISBLANK(R135))," ", IF(OR(P135<5,AND(P135=" ",Q135<>" ",R135<>" ")),"<5 yrs", IF(AND(P135>=5,P135<=14),"5 - 14 yrs", IF(AND(P135>=15,P135<=18),"15 - 18 yrs", IF(AND(P135>=19,P135<=49),"19 - 49 yrs","50 yrs +"))))) -> 50 yrs + | T135: Female | U135: Pann Khwar | V135: U Nyunt Sate | W135: Back Pain | X135: Muscle Pain | Y135: =INDEX(info!$Y$2:$Y$192,MATCH(phc_8[[#This Row],[Sub_Category]],info!$X$2:$X$192,0)) -> Other (non-communicable) | Z135: {=INDEX(info!$AA$2:$AA$192,MATCH(PHC!$X135&PHC!$Y135,info!$X$2:$X$192&info!$Y$2:$Y$192,0))} -> Other | AA135: Myomas, Betex | AB135: No | AC135: No | AD135: No | AE135: No | AK135: No | AM135: =IF(AF135="","","Q"&INT((MONTH(AF135)-1)/3)+1&YEAR(AF135)&#REF!&T135) | AN135: =IF(K135="","","Q"&INT((MONTH(K135)-1)/3)+1&YEAR(K135)&#REF!) -> #REF!
A136: 134 | B136: BHA | C136: Shining Star | D136: Mobile Clinic | E136: Mandalay | F136: Kyaukse | H136: Pann Khwar | I136: Village | K136: 46038 | L136: 54 | M136: =IF(phc_8[[#This Row],[Register No.]]="","",C136&"-"&D136&"-"&"BHA-PHC-"&phc_8[[#This Row],[Register No.]]) -> Shining Star-Mobile Clinic-BHA-PHC-54 | N136: New | O136: Daw Khin Nyein | P136: 75 | S136: =IF(AND(ISBLANK(P136),ISBLANK(Q136),ISBLANK(R136))," ", IF(OR(P136<5,AND(P136=" ",Q136<>" ",R136<>" ")),"<5 yrs", IF(AND(P136>=5,P136<=14),"5 - 14 yrs", IF(AND(P136>=15,P136<=18),"15 - 18 yrs", IF(AND(P136>=19,P136<=49),"19 - 49 yrs","50 yrs +"))))) -> 50 yrs + | T136: Female | U136: Pann Khwar | V136: U Chit Htun | W136: Abdominal Pain | X136: Gastritis | Y136: =INDEX(info!$Y$2:$Y$192,MATCH(phc_8[[#This Row],[Sub_Category]],info!$X$2:$X$192,0)) -> GI problem | Z136: {=INDEX(info!$AA$2:$AA$192,MATCH(PHC!$X136&PHC!$Y136,info!$X$2:$X$192&info!$Y$2:$Y$192,0))} -> Non-communicable disease | AA136: Pantocid, Siloxogene, Amlo10 | AB136: No | AC136: No | AD136: No | AE136: No | AK136: No | AM136: =IF(AF136="","","Q"&INT((MONTH(AF136)-1)/3)+1&YEAR(AF136)&#REF!&T136) | AN136: =IF(K136="","","Q"&INT((MONTH(K136)-1)/3)+1&YEAR(K136)&#REF!) -> #REF!
... A148: 146 | B148: BHA | C148: Shining Star | D148: Mobile Clinic | E148: Mandalay | F148: Kyaukse | H148: Pann Khwar | I148: Village | K148: 46038 | L148: 66 | M148: =IF(phc_8[[#This Row],[Register No.]]="","",C148&"-"&D148&"-"&"BHA-PHC-"&phc_8[[#This Row],[Register No.]]) -> Shining Star-Mobile Clinic-BHA-PHC-66 | N148: New | O148: Daw Than Nu | P148: 57 | S148: =IF(AND(ISBLANK(P148),ISBLANK(Q148),ISBLANK(R148))," ", IF(OR(P148<5,AND(P148=" ",Q148<>" ",R148<>" ")),"<5 yrs", IF(AND(P148>=5,P148<=14),"5 - 14 yrs", IF(AND(P148>=15,P148<=18),"15 - 18 yrs", IF(AND(P148>=19,P148<=49),"19 - 49 yrs","50 yrs +"))))) -> 50 yrs + | T148: Female | U148: Pann Khwar | V148: U Ant Mg | W148: DM | X148: DM | Y148: =INDEX(info!$Y$2:$Y$192,MATCH(phc_8[[#This Row],[Sub_Category]],info!$X$2:$X$192,0)) -> Chronic medical disease | Z148: {=INDEX(info!$AA$2:$AA$192,MATCH(PHC!$X148&PHC!$Y148,info!$X$2:$X$192&info!$Y$2:$Y$192,0))} -> Non-communicable disease | AA148: Losar25, Lasix,Am;o10, Ato10, Aldactone | AB148: No | AC148: No | AD148: No | AE148: No | AK148: No | AM148: =IF(AF148="","","Q"&INT((MONTH(AF148)-1)/3)+1&YEAR(AF148)&#REF!&T148) | AN148: =IF(K148="","","Q"&INT((MONTH(K148)-1)/3)+1&YEAR(K148)&#REF!) -> #REF!
A149: 147 | B149: BHA | C149: Shining Star | D149: Mobile Clinic | E149: Mandalay | F149: Kyaukse | H149: Pann Khwar | I149: Village | K149: 46038 | L149: 67 | M149: =IF(phc_8[[#This Row],[Register No.]]="","",C149&"-"&D149&"-"&"BHA-PHC-"&phc_8[[#This Row],[Register No.]]) -> Shining Star-Mobile Clinic-BHA-PHC-67 | N149: New | O149: Daw Htay Tint | P149: 37 | S149: =IF(AND(ISBLANK(P149),ISBLANK(Q149),ISBLANK(R149))," ", IF(OR(P149<5,AND(P149=" ",Q149<>" ",R149<>" ")),"<5 yrs", IF(AND(P149>=5,P149<=14),"5 - 14 yrs", IF(AND(P149>=15,P149<=18),"15 - 18 yrs", IF(AND(P149>=19,P149<=49),"19 - 49 yrs","50 yrs +"))))) -> 19 - 49 yrs | T149: Female | U149: Pann Khwar | V149: U Win Myint | W149: LT Sciatica | Y149: =INDEX(info!$Y$2:$Y$192,MATCH(phc_8[[#This Row],[Sub_Category]],info!$X$2:$X$192,0)) -> #N/A | Z149: {=INDEX(info!$AA$2:$AA$192,MATCH(PHC!$X149&PHC!$Y149,info!$X$2:$X$192&info!$Y$2:$Y$192,0))} -> #N/A | AA149: Ibu, Betex, Amlo5 | AB149: No | AC149: No | AD149: No | AE149: No | AK149: No | AM149: =IF(AF149="","","Q"&INT((MONTH(AF149)-1)/3)+1&YEAR(AF149)&#REF!&T149) | AN149: =IF(K149="","","Q"&INT((MONTH(K149)-1)/3)+1&YEAR(K149)&#REF!) -> #REF!
A150: 148 | B150: BHA | C150: Shining Star | D150: Mobile Clinic | E150: Mandalay | F150: Kyaukse | H150: Pann Khwar | I150: Village | K150: 46038 | L150: 68 | M150: =IF(phc_8[[#This Row],[Register No.]]="","",C150&"-"&D150&"-"&"BHA-PHC-"&phc_8[[#This Row],[Register No.]]) -> Shining Star-Mobile Clinic-BHA-PHC-68 | N150: New | O150: Daw Khin Than Win | P150: 56 | S150: =IF(AND(ISBLANK(P150),ISBLANK(Q150),ISBLANK(R150))," ", IF(OR(P150<5,AND(P150=" ",Q150<>" ",R150<>" ")),"<5 yrs", IF(AND(P150>=5,P150<=14),"5 - 14 yrs", IF(AND(P150>=15,P150<=18),"15 - 18 yrs", IF(AND(P150>=19,P150<=49),"19 - 49 yrs","50 yrs +"))))) -> 50 yrs + | T150: Female | U150: Pann Khwar | V150: U Nyo Lay | W150: DM | X150: DM | Y150: =INDEX(info!$Y$2:$Y$192,MATCH(phc_8[[#This Row],[Sub_Category]],info!$X$2:$X$192,0)) -> Chronic medical disease | Z150: {=INDEX(info!$AA$2:$AA$192,MATCH(PHC!$X150&PHC!$Y150,info!$X$2:$X$192&info!$Y$2:$Y$192,0))} -> Non-communicable disease | AA150: Amlo10, Metformin, Gliclacide, Ato10 | AB150: No | AC150: No | AD150: No | AE150: No | AK150: No | AM150: =IF(AF150="","","Q"&INT((MONTH(AF150)-1)/3)+1&YEAR(AF150)&#REF!&T150) | AN150: =IF(K150="","","Q"&INT((MONTH(K150)-1)/3)+1&YEAR(K150)&#REF!) -> #REF!
A151: 149 | B151: BHA | C151: Shining Star | D151: Mobile Clinic | E151: Mandalay | F151: Kyaukse | H151: Pann Khwar | I151: Village | K151: 46038 | L151: 69 | M151: =IF(phc_8[[#This Row],[Register No.]]="","",C151&"-"&D151&"-"&"BHA-PHC-"&phc_8[[#This Row],[Register No.]]) -> Shining Star-Mobile Clinic-BHA-PHC-69 | N151: New | O151: Daw Han Aye | P151: 83 | S151: =IF(AND(ISBLANK(P151),ISBLANK(Q151),ISBLANK(R151))," ", IF(OR(P151<5,AND(P151=" ",Q151<>" ",R151<>" ")),"<5 yrs", IF(AND(P151>=5,P151<=14),"5 - 14 yrs", IF(AND(P151>=15,P151<=18),"15 - 18 yrs", IF(AND(P151>=19,P151<=49),"19 - 49 yrs","50 yrs +"))))) -> 50 yrs + | T151: Female | U151: Pann Khwar | V151: U Htun Hla | W151: Weakness | X151: Weakness | Y151: =INDEX(info!$Y$2:$Y$192,MATCH(phc_8[[#This Row],[Sub_Category]],info!$X$2:$X$192,0)) -> Other (non-communicable) | Z151: {=INDEX(info!$AA$2:$AA$192,MATCH(PHC!$X151&PHC!$Y151,info!$X$2:$X$192&info!$Y$2:$Y$192,0))} -> Other | AA151: IV25%+B12+VitC, Zinc, VitC,Para, MV, Amlo5 | AB151: No | AC151: No | AD151: No | AE151: No | AK151: No | AM151: =IF(AF151="","","Q"&INT((MONTH(AF151)-1)/3)+1&YEAR(AF151)&#REF!&T151) | AN151: =IF(K151="","","Q"&INT((MONTH(K151)-1)/3)+1&YEAR(K151)&#REF!) -> #REF!
A152: 150 | B152: BHA | C152: Shining Star | D152: Mobile Clinic | E152: Mandalay | F152: Kyaukse | H152: Pann Khwar | I152: Village | K152: 46038 | L152: 70 | M152: =IF(phc_8[[#This Row],[Register No.]]="","",C152&"-"&D152&"-"&"BHA-PHC-"&phc_8[[#This Row],[Register No.]]) -> Shining Star-Mobile Clinic-BHA-PHC-70 | N152: New | O152: U Chit Myaing | P152: 70 | S152: =IF(AND(ISBLANK(P152),ISBLANK(Q152),ISBLANK(R152))," ", IF(OR(P152<5,AND(P152=" ",Q152<>" ",R152<>" ")),"<5 yrs", IF(AND(P152>=5,P152<=14),"5 - 14 yrs", IF(AND(P152>=15,P152<=18),"15 - 18 yrs", IF(AND(P152>=19,P152<=49),"19 - 49 yrs","50 yrs +"))))) -> 50 yrs + | T152: Male | U152: Pann Khwar | V152: U Htway | W152: LT Thight Pain | X152: Muscle Pain | Y152: =INDEX(info!$Y$2:$Y$192,MATCH(phc_8[[#This Row],[Sub_Category]],info!$X$2:$X$192,0)) -> Other (non-communicable) | Z152: {=INDEX(info!$AA$2:$AA$192,MATCH(PHC!$X152&PHC!$Y152,info!$X$2:$X$192&info!$Y$2:$Y$192,0))} -> Other | AA152: Ibu, Omex, Amlo10 | AB152: No | AC152: No | AD152: No | AE152: No | AK152: No | AM152: =IF(AF152="","","Q"&INT((MONTH(AF152)-1)/3)+1&YEAR(AF152)&#REF!&T152) | AN152: =IF(K152="","","Q"&INT((MONTH(K152)-1)/3)+1&YEAR(K152)&#REF!) -> #REF!
A153: 151 | B153: BHA | C153: Shining Star | D153: Mobile Clinic | E153: Mandalay | F153: Kyaukse | H153: Pann Khwar | I153: Village | K153: 46038 | L153: 71 | M153: =IF(phc_8[[#This Row],[Register No.]]="","",C153&"-"&D153&"-"&"BHA-PHC-"&phc_8[[#This Row],[Register No.]]) -> Shining Star-Mobile Clinic-BHA-PHC-71 | N153: New | O153: Daw Khin Toe | P153: 60 | S153: =IF(AND(ISBLANK(P153),ISBLANK(Q153),ISBLANK(R153))," ", IF(OR(P153<5,AND(P153=" ",Q153<>" ",R153<>" ")),"<5 yrs", IF(AND(P153>=5,P153<=14),"5 - 14 yrs", IF(AND(P153>=15,P153<=18),"15 - 18 yrs", IF(AND(P153>=19,P153<=49),"19 - 49 yrs","50 yrs +"))))) -> 50 yrs + | T153: Female | U153: Pann Khwar | V153: U Khin Mg | W153: HT | X153: Hypertension | Y153: =INDEX(info!$Y$2:$Y$192,MATCH(phc_8[[#This Row],[Sub_Category]],info!$X$2:$X$192,0)) -> Chronic medical disease | Z153: {=INDEX(info!$AA$2:$AA$192,MATCH(PHC!$X153&PHC!$Y153,info!$X$2:$X$192&info!$Y$2:$Y$192,0))} -> Non-communicable disease | AA153: Losar25, Betex, Aceclo, Omex | AB153: No | AC153: No | AD153: No | AE153: No | AK153: No | AM153: =IF(AF153="","","Q"&INT((MONTH(AF153)-1)/3)+1&YEAR(AF153)&#REF!&T153) | AN153: =IF(K153="","","Q"&INT((MONTH(K153)-1)/3)+1&YEAR(K153)&#REF!) -> #REF!
A154: 152 | B154: BHA | C154: Shining Star | D154: Mobile Clinic | E154: Mandalay | F154: Kyaukse | H154: Pann Khwar | I154: Village | K154: 46038 | L154: 72 | M154: =IF(phc_8[[#This Row],[Register No.]]="","",C154&"-"&D154&"-"&"BHA-PHC-"&phc_8[[#This Row],[Register No.]]) -> Shining Star-Mobile Clinic-BHA-PHC-72 | N154: New | O154: Daw Kyu Tin | P154: 42 | S154: =IF(AND(ISBLANK(P154),ISBLANK(Q154),ISBLANK(R154))," ", IF(OR(P154<5,AND(P154=" ",Q154<>" ",R154<>" ")),"<5 yrs", IF(AND(P154>=5,P154<=14),"5 - 14 yrs", IF(AND(P154>=15,P154<=18),"15 - 18 yrs", IF(AND(P154>=19,P154<=49),"19 - 49 yrs","50 yrs +"))))) -> 19 - 49 yrs | T154: Female | U154: Pann Khwar | V154: U Thet Htun | W154: Cervical Spondylosis | Y154: =INDEX(info!$Y$2:$Y$192,MATCH(phc_8[[#This Row],[Sub_Category]],info!$X$2:$X$192,0)) -> #N/A | Z154: {=INDEX(info!$AA$2:$AA$192,MATCH(PHC!$X154&PHC!$Y154,info!$X$2:$X$192&info!$Y$2:$Y$192,0))} -> #N/A | AA154: Aceclo, Omex, Pregabalin, Neurovit | AB154: No | AC154: No | AD154: No | AE154: No | AK154: No | AM154: =IF(AF154="","","Q"&INT((MONTH(AF154)-1)/3)+1&YEAR(AF154)&#REF!&T154) | AN154: =IF(K154="","","Q"&INT((MONTH(K154)-1)/3)+1&YEAR(K154)&#REF!) -> #REF!
A155: 153 | B155: BHA | C155: Shining Star | D155: Mobile Clinic | E155: Mandalay | F155: Kyaukse | H155: Pann Khwar | I155: Village | K155: 46038 | L155: 73 | M155: =IF(phc_8[[#This Row],[Register No.]]="","",C155&"-"&D155&"-"&"BHA-PHC-"&phc_8[[#This Row],[Register No.]]) -> Shining Star-Mobile Clinic-BHA-PHC-73 | N155: New | O155: Daw Hmway | P155: 67 | S155: =IF(AND(ISBLANK(P155),ISBLANK(Q155),ISBLANK(R155))," ", IF(OR(P155<5,AND(P155=" ",Q155<>" ",R155<>" ")),"<5 yrs", IF(AND(P155>=5,P155<=14),"5 - 14 yrs", IF(AND(P155>=15,P155<=18),"15 - 18 yrs", IF(AND(P155>=19,P155<=49),"19 - 49 yrs","50 yrs +"))))) -> 50 yrs + | T155: Female | U155: Pann Khwar | V155: U Hla Baw | W155: Frozen Shoulder | X155: Injuries | Y155: =INDEX(info!$Y$2:$Y$192,MATCH(phc_8[[#This Row],[Sub_Category]],info!$X$2:$X$192,0)) -> Accident/minor sugical and injuries | Z155: {=INDEX(info!$AA$2:$AA$192,MATCH(PHC!$X155&PHC!$Y155,info!$X$2:$X$192&info!$Y$2:$Y$192,0))} -> Injury related | AA155: IV B12, Para, Ca+, Gabapentin, MV | AB155: No | AC155: No | AD155: No | AE155: No | AK155: No | AM155: =IF(AF155="","","Q"&INT((MONTH(AF155)-1)/3)+1&YEAR(AF155)&#REF!&T155) | AN155: =IF(K155="","","Q"&INT((MONTH(K155)-1)/3)+1&YEAR(K155)&#REF!) -> #REF!
A156: 154 | B156: BHA | C156: Shining Star | D156: Mobile Clinic | E156: Mandalay | F156: Kyaukse | H156: Pann Khwar | I156: Village | K156: 46038 | L156: 74 | M156: =IF(phc_8[[#This Row],[Register No.]]="","",C156&"-"&D156&"-"&"BHA-PHC-"&phc_8[[#This Row],[Register No.]]) -> Shining Star-Mobile Clinic-BHA-PHC-74 | N156: New | O156: Daw Lone | P156: 54 | S156: =IF(AND(ISBLANK(P156),ISBLANK(Q156),ISBLANK(R156))," ", IF(OR(P156<5,AND(P156=" ",Q156<>" ",R156<>" ")),"<5 yrs", IF(AND(P156>=5,P156<=14),"5 - 14 yrs", IF(AND(P156>=15,P156<=18),"15 - 18 yrs", IF(AND(P156>=19,P156<=49),"19 - 49 yrs","50 yrs +"))))) -> 50 yrs + | T156: Female | U156: Pann Khwar | V156: U Htun Hlaing | W156: HT/DM | X156: DM | Y156: =INDEX(info!$Y$2:$Y$192,MATCH(phc_8[[#This Row],[Sub_Category]],info!$X$2:$X$192,0)) -> Chronic medical disease | Z156: {=INDEX(info!$AA$2:$AA$192,MATCH(PHC!$X156&PHC!$Y156,info!$X$2:$X$192&info!$Y$2:$Y$192,0))} -> Non-communicable disease | AA156: Enam5, Para, Amlo10, Ato20, Aspilet, Metformin, Gliclacide | AB156: No | AC156: No | AD156: No | AE156: No | AK156: No | AM156: =IF(AF156="","","Q"&INT((MONTH(AF156)-1)/3)+1&YEAR(AF156)&#REF!&T156) | AN156: =IF(K156="","","Q"&INT((MONTH(K156)-1)/3)+1&YEAR(K156)&#REF!) -> #REF!
...

Sheet MCH
A1: MCH Database | AH1: Note: Please fill the result If only RI done | AK1: ANC1 | AP1: ANC2 | AU1: ANC3 | AZ1: ANC4 | BG1: Kits distribution | BK1: Delivery Information | BV1: PNC1 | BW1: PNC2
A2: Sr.No | B2: Fund | C2: Implementing Organization Name | D2: Health Post/Clinic | E2: State | F2: Township | G2: Village Tract | H2: Village/Ward/Camp | I2: Alternative Village/ Camp Name | J2: Type of Place | K2: Helper | L2: Pcode | M2: Date of Registration [mm/dd/yy] | N2: Month | O2: Quarter | P2: Year | Q2: Reg.No | R2: Reg.Code | S2: Name | T2: Age | U2: Age_Category | V2: Age_cat | W2: Ethnicity | X2: Disable | Y2: Husband's name | Z2: Address (if not the same with Moblile Clinic location) | AA2: LMP | AB2: EDD | AC2: LB info | AD2: High Risk Pregnancy | AE2: Gravida/Parity | AF2: TT1 | AG2: TT2 | AH2: Syphilis Testing | AI2: HIV Testing | AJ2: Hep-B Testing | AK2: ANC1.1 [mm/dd/yy] | AL2: ANC1.2 | AM2: ANC1.3 | AN2: ANC1.4 | AO2: ANC1.5 | AP2: ANC2.1 | AQ2: ANC2.2 | AR2: ANC2.3 | AS2: ANC2.4 | AT2: ANC2.5 | AU2: ANC3.1 | AV2: ANC3.2 | AW2: ANC3.3 | AX2: ANC3.4 | AY2: ANC3.5 | AZ2: ANC4.1 | BA2: ANC4.2 | BB2: ANC4.3 | BC2: ANC4.4 | BD2: ANC4.5 | BE2: Total ANC | BF2: Quality AN-Care(As per indicator definition, at least AN care 2 time based on total trimester) | BG2: NBK | BH2: Happy Baby Kit | BI2: Diginity Kit | BJ2: CDK | BK2: Date of Delivery | BL2: Time | BM2: wt. of baby | BN2: Sex of baby | BO2: Delivered by | BP2: Name of Delivered Person | BQ2: Type of Delivered Person | BR2: SBA | BS2: Type of delivery | BT2: Place of delivery | BU2: Delivery outcome | BV2: PNC1 | BW2: PNC2.1 | BX2: PNC2.2 | BY2: PN2.3 | BZ2: PN2.4 | CA2: PN2.5 | CB2: Total_PNC | CC2: Follow Up Date | CD2: Referral or Not | CE2: Referral Date | CF2: Referral ID card number (000/MCH/YYYY) | CG2: Cause of referral | CH2: Teleconsultation | CI2: Remarks | CJ2: 1 | CK2: 2 | CL2: 3 | CM2: 4 | CN2: 5 | CO2: 6 | CP2: 7 | CQ2: 8 | CR2: 9 | CS2: 10 | CT2: 11 | CU2: 12 | CV2: 13 | CW2: 14 | CX2: 15 | CY2: 16 | CZ2: 17 | DA2: 18 | DB2: 19 | DC2: 20 | DD2: p1 | DE2: p2 | DF2: p3 | DG2: p4 | DH2: p5 | DI2: p6 | DJ2: Deli | DK2: LB | DL2: Deli Kit | DM2: Indi_help | DN2: Indi4times | DO2: lb_help | DP2: A1 | DQ2: A2 | DR2: A3 | DS2: A4 | DT2: A5 | DU2: A6 | DV2: A7 | DW2: A8 | DX2: A9 | DY2: A10 | DZ2: A11 | EA2: A12 | EB2: A13 | EC2: A14 | ED2: A15 | EE2: A16 | EF2: A17 | EG2: A18 | EH2: A19 | EI2: A20 | EJ2: AA1 | EK2: AA2 | EL2: AA3 | EM2: AA4 | EN2: AA5 | EO2: AA6 | EP2: AA7 | EQ2: AA8 | ER2: AA9 | ES2: AA10 | ET2: AA11 | EU2: AA12 | EV2: AA13 | EW2: AA14 | EX2: AA15 | EY2: AA16 | EZ2: AA17 | FA2: AA18 | FB2: AA19 | FC2: AA20 | FD2: AAA1 | FE2: AAA2 | FF2: AAA3 | FG2: AAA4 | FH2: AAA5 | FI2: AAA6 | FJ2: AAA7 | FK2: AAA8 | FL2: AAA9 | FM2: AAA10 | FN2: AAA11 | FO2: AAA12 | FP2: AAA13 | FQ2: AAA14 | FR2: AAA15 | FS2: AAA16 | FT2: AAA17 | FU2: AAA18 | FV2: AAA19 | FW2: AAA20
A3: 1 | B3: BHA | C3: Shining Star | E3: Mandalay | F3: Kyaukse | G3: Myittoo | H3: Village | L3: =IFERROR(VLOOKUP([10]!family_planning[[#This Row],[Helper]],[10]datavalidation!E:G,3,FALSE),"") | N3: =IF(mshn_database[[#This Row],[Date of Registration '[mm/dd/yy']]]="","",TEXT(mshn_database[[#This Row],[Date of Registration '[mm/dd/yy']]],"mmmm")) | O3: =IF(mshn_database[[#This Row],[Date of Registration '[mm/dd/yy']]]="","","Q"&INT((MONTH(mshn_database[[#This Row],[Date of Registration '[mm/dd/yy']]])-1)/3)+1) | P3: =IF(mshn_database[[#This Row],[Date of Registration '[mm/dd/yy']]]="","",TEXT(mshn_database[[#This Row],[Date of Registration '[mm/dd/yy']]],"yyyy")) | Q3: 1 | R3: =IF(Q3="","",C3&"-"&D3&"-"&"BHA-MCH-"&Q3) -> Shining Star--BHA-MCH-1 | S3: Ma Shwe Zin | T3: 26 | U3: =IF(ISBLANK(T3),"", IF(T3<5,"<5 yrs", IF(AND(T3>=5,T3<=14),"5 - 14 yrs", IF(AND(T3>=15,T3<=18),"15 - 18 yrs", IF(AND(T3>=19,T3<=49),"19 - 49 yrs", IF(T3>=50,"50 yrs +","")))))) -> 19 - 49 yrs | V3: =IF(mshn_database[[#This Row],[Age_Category]]="","",VLOOKUP(mshn_database[[#This Row],[Age_Category]],[10]info!$H$2:$I$6,2,FALSE)) -> #N/A | W3: Burma | X3: No | AC3: =IF(AB3="","",IF(AND(TODAY()>=AB3,BU3=""),"Need LB info","No need info yet/LB info aldy included")) | AF3: Yes | AG3: Yes | BE3: =COUNT(AK3:BD3) -> 0 | BF3: =IF((OR(AND(COUNT(AK3:AO3)>=1,COUNT(AP3:AT3)>=1),AND(COUNT(AK3:AO3)>=1,COUNT(AU3:AY3)>=1),AND(COUNT(AK3:AO3)>=1,COUNT(AZ3:BD3)>=1),AND(COUNT(AP3:AT3)>=1,COUNT(AU3:AY3)>=1),AND(COUNT(AP3:AT3)>=1,COUNT(AZ3:BD3)>=1),AND(COUNT(AU3:AY3)>=1,COUNT(AZ3:BD3)>=1))), "Yes", "No") -> No | BZ3: 46037 | CB3: =IF(AND(BV3="",BW3="",BX3="",BY3="",BZ3="",CA3=""),"",COUNT(BV3:CA3)) -> 1 | CD3: No | CJ3: =IF(AK3="","","Q"&INT((MONTH(AK3)-1)/3)+1&YEAR(AK3)&$V3) | CK3: =IF(AL3="","","Q"&INT((MONTH(AL3)-1)/3)+1&YEAR(AL3)&$V3) | CL3: =IF(AM3="","","Q"&INT((MONTH(AM3)-1)/3)+1&YEAR(AM3)&$V3) | CM3: =IF(AN3="","","Q"&INT((MONTH(AN3)-1)/3)+1&YEAR(AN3)&$V3) | CN3: =IF(AO3="","","Q"&INT((MONTH(AO3)-1)/3)+1&YEAR(AO3)&$V3) | CO3: =IF(AP3="","","Q"&INT((MONTH(AP3)-1)/3)+1&YEAR(AP3)&$V3) | CP3: =IF(AQ3="","","Q"&INT((MONTH(AQ3)-1)/3)+1&YEAR(AQ3)&$V3) | CQ3: =IF(AR3="","","Q"&INT((MONTH(AR3)-1)/3)+1&YEAR(AR3)&$V3) | ... DC3: =IF(BD3="","","Q"&INT((MONTH(BD3)-1)/3)+1&YEAR(BD3)&$V3) | DD3: =IF(BV3="","","Q"&INT((MONTH(BV3)-1)/3)+1&YEAR(BV3)&$V3) | DE3: =IF(BW3="","","Q"&INT((MONTH(BW3)-1)/3)+1&YEAR(BW3)&$V3) | DF3: =IF(BX3="","","Q"&INT((MONTH(BX3)-1)/3)+1&YEAR(BX3)&$V3) | DG3: =IF(BY3="","","Q"&INT((MONTH(BY3)-1)/3)+1&YEAR(BY3)&$V3) | DH3: =IF(BZ3="","","Q"&INT((MONTH(BZ3)-1)/3)+1&YEAR(BZ3)&$V3) -> #N/A | DI3: =IF(CA3="","","Q"&INT((MONTH(CA3)-1)/3)+1&YEAR(CA3)&$V3) | DJ3: =IF(BR3="","",IF(BR3="Yes","Q"&INT((MONTH(BK3)-1)/3)+1&YEAR(BK3)&$V3,"na")) | DK3: =IF(BU3="","",IF(BU3="Alive","Q"&INT((MONTH(BK3)-1)/3)+1&YEAR(BK3)&$V3,"na")) | DL3: =IF(BJ3="","","Q"&INT((MONTH(BJ3)-1)/3)+1&YEAR(BJ3)&$V3) | DM3: =IF(M3="","",TEXT(M3,"mmmm")&YEAR(M3)) | DN3: =IF(BE3>=4,N3&P3,"") | DO3: =IF(BK3="","",TEXT(BK3,"mmmm")&YEAR(BK3)) | DP3: =IF(AK3="","",1) | DQ3: =IF(AL3="","",1) | DR3: =IF(AM3="","",1) | DS3: =IF(AN3="","",1) | DT3: =IF(AO3="","",1) | DU3: =IF(AP3="","",1) | DV3: =IF(AQ3="","",1) | DW3: =IF(AR3="","",1) | ... EI3: =IF(BD3="","",1) | EJ3: =SUM($DP$3:DP3) -> 0 | EK3: =SUM($DP$3:DQ3) -> 0 | EL3: =SUM($DP$3:DR3) -> 0 | EM3: =SUM($DP$3:DS3) -> 0 | EN3: =SUM($DP$3:DT3) -> 0 | EO3: =SUM($DP$3:DU3) -> 0 | EP3: =SUM($DP$3:DV3) -> 0 | EQ3: =SUM($DP$3:DW3) -> 0 | ... FC3: =SUM($DP$3:EI3) -> 0 | FG3: IF(AND(AD3=3,AE3=4,
A4: 2 | B4: BHA | C4: Shining Star | E4: Mandalay | F4: Kyaukse | G4: Myittoo | H4: Village | L4: =IFERROR(VLOOKUP([10]!family_planning[[#This Row],[Helper]],[10]datavalidation!E:G,3,FALSE),"") | N4: =IF(mshn_database[[#This Row],[Date of Registration '[mm/dd/yy']]]="","",TEXT(mshn_database[[#This Row],[Date of Registration '[mm/dd/yy']]],"mmmm")) | O4: =IF(mshn_database[[#This Row],[Date of Registration '[mm/dd/yy']]]="","","Q"&INT((MONTH(mshn_database[[#This Row],[Date of Registration '[mm/dd/yy']]])-1)/3)+1) | P4: =IF(mshn_database[[#This Row],[Date of Registration '[mm/dd/yy']]]="","",TEXT(mshn_database[[#This Row],[Date of Registration '[mm/dd/yy']]],"yyyy")) | Q4: 2 | R4: =IF(Q4="","",C4&"-"&D4&"-"&"BHA-MCH-"&Q4) -> Shining Star--BHA-MCH-2 | S4: Ma Khaing Zin Win | T4: 27 | U4: =IF(ISBLANK(T4),"", IF(T4<5,"<5 yrs", IF(AND(T4>=5,T4<=14),"5 - 14 yrs", IF(AND(T4>=15,T4<=18),"15 - 18 yrs", IF(AND(T4>=19,T4<=49),"19 - 49 yrs", IF(T4>=50,"50 yrs +","")))))) -> 19 - 49 yrs | V4: =IF(mshn_database[[#This Row],[Age_Category]]="","",VLOOKUP(mshn_database[[#This Row],[Age_Category]],[10]info!$H$2:$I$6,2,FALSE)) -> #N/A | W4: Burma | X4: No | AC4: =IF(AB4="","",IF(AND(TODAY()>=AB4,BU4=""),"Need LB info","No need info yet/LB info aldy included")) | AF4: Yes | AG4: Yes | BE4: =COUNT(AK4:BD4) -> 0 | BF4: =IF((OR(AND(COUNT(AK4:AO4)>=1,COUNT(AP4:AT4)>=1),AND(COUNT(AK4:AO4)>=1,COUNT(AU4:AY4)>=1),AND(COUNT(AK4:AO4)>=1,COUNT(AZ4:BD4)>=1),AND(COUNT(AP4:AT4)>=1,COUNT(AU4:AY4)>=1),AND(COUNT(AP4:AT4)>=1,COUNT(AZ4:BD4)>=1),AND(COUNT(AU4:AY4)>=1,COUNT(AZ4:BD4)>=1))), "Yes", "No") -> No | BZ4: 46037 | CB4: =IF(AND(BV4="",BW4="",BX4="",BY4="",BZ4="",CA4=""),"",COUNT(BV4:CA4)) -> 1 | CD4: No | CJ4: =IF(AK4="","","Q"&INT((MONTH(AK4)-1)/3)+1&YEAR(AK4)&$V4) | CK4: =IF(AL4="","","Q"&INT((MONTH(AL4)-1)/3)+1&YEAR(AL4)&$V4) | CL4: =IF(AM4="","","Q"&INT((MONTH(AM4)-1)/3)+1&YEAR(AM4)&$V4) | CM4: =IF(AN4="","","Q"&INT((MONTH(AN4)-1)/3)+1&YEAR(AN4)&$V4) | CN4: =IF(AO4="","","Q"&INT((MONTH(AO4)-1)/3)+1&YEAR(AO4)&$V4) | CO4: =IF(AP4="","","Q"&INT((MONTH(AP4)-1)/3)+1&YEAR(AP4)&$V4) | CP4: =IF(AQ4="","","Q"&INT((MONTH(AQ4)-1)/3)+1&YEAR(AQ4)&$V4) | CQ4: =IF(AR4="","","Q"&INT((MONTH(AR4)-1)/3)+1&YEAR(AR4)&$V4) | ... DC4: =IF(BD4="","","Q"&INT((MONTH(BD4)-1)/3)+1&YEAR(BD4)&$V4) | DD4: =IF(BV4="","","Q"&INT((MONTH(BV4)-1)/3)+1&YEAR(BV4)&$V4) | DE4: =IF(BW4="","","Q"&INT((MONTH(BW4)-1)/3)+1&YEAR(BW4)&$V4) | DF4: =IF(BX4="","","Q"&INT((MONTH(BX4)-1)/3)+1&YEAR(BX4)&$V4) | DG4: =IF(BY4="","","Q"&INT((MONTH(BY4)-1)/3)+1&YEAR(BY4)&$V4) | DH4: =IF(BZ4="","","Q"&INT((MONTH(BZ4)-1)/3)+1&YEAR(BZ4)&$V4) -> #N/A | DI4: =IF(CA4="","","Q"&INT((MONTH(CA4)-1)/3)+1&YEAR(CA4)&$V4) | DJ4: =IF(BR4="","",IF(BR4="Yes","Q"&INT((MONTH(BK4)-1)/3)+1&YEAR(BK4)&$V4,"na")) | DK4: =IF(BU4="","",IF(BU4="Alive","Q"&INT((MONTH(BK4)-1)/3)+1&YEAR(BK4)&$V4,"na")) | DL4: =IF(BJ4="","","Q"&INT((MONTH(BJ4)-1)/3)+1&YEAR(BJ4)&$V4) | DM4: =IF(M4="","",TEXT(M4,"mmmm")&YEAR(M4)) | DN4: =IF(BE4>=4,N4&P4,"") | DO4: =IF(BK4="","",TEXT(BK4,"mmmm")&YEAR(BK4)) | DP4: =IF(AK4="","",1) | EJ4: =SUM($DP$3:DP27) -> 0 | EK4: =SUM($DP$3:DQ27) -> 0 | EL4: =SUM($DP$3:DR27) -> 0 | EM4: =SUM($DP$3:DS27) -> 0 | EN4: =SUM($DP$3:DT27) -> 0 | EO4: =SUM($DP$3:DU27) -> 0 | EP4: =SUM($DP$3:DV27) -> 0 | EQ4: =SUM($DP$3:DW27) -> 0 | ... FC4: =SUM($DP$3:EI27) -> 0
A5: 3 | B5: BHA | C5: Shining Star | E5: Mandalay | F5: Kyaukse | G5: Pann Khwar | H5: Village | L5: =IFERROR(VLOOKUP([10]!family_planning[[#This Row],[Helper]],[10]datavalidation!E:G,3,FALSE),"") | N5: =IF(mshn_database[[#This Row],[Date of Registration '[mm/dd/yy']]]="","",TEXT(mshn_database[[#This Row],[Date of Registration '[mm/dd/yy']]],"mmmm")) | O5: =IF(mshn_database[[#This Row],[Date of Registration '[mm/dd/yy']]]="","","Q"&INT((MONTH(mshn_database[[#This Row],[Date of Registration '[mm/dd/yy']]])-1)/3)+1) | P5: =IF(mshn_database[[#This Row],[Date of Registration '[mm/dd/yy']]]="","",TEXT(mshn_database[[#This Row],[Date of Registration '[mm/dd/yy']]],"yyyy")) | Q5: 3 | R5: =IF(Q5="","",C5&"-"&D5&"-"&"BHA-MCH-"&Q5) -> Shining Star--BHA-MCH-3 | S5: Ma Khin Pyone Kyi | T5: 36 | U5: =IF(ISBLANK(T5),"", IF(T5<5,"<5 yrs", IF(AND(T5>=5,T5<=14),"5 - 14 yrs", IF(AND(T5>=15,T5<=18),"15 - 18 yrs", IF(AND(T5>=19,T5<=49),"19 - 49 yrs", IF(T5>=50,"50 yrs +","")))))) -> 19 - 49 yrs | V5: =IF(mshn_database[[#This Row],[Age_Category]]="","",VLOOKUP(mshn_database[[#This Row],[Age_Category]],[10]info!$H$2:$I$6,2,FALSE)) -> #N/A | W5: Burma | X5: No | AC5: =IF(AB5="","",IF(AND(TODAY()>=AB5,BU5=""),"Need LB info","No need info yet/LB info aldy included")) | AF5: Yes | AG5: Yes | BE5: =COUNT(AK5:BD5) -> 0 | BF5: =IF((OR(AND(COUNT(AK5:AO5)>=1,COUNT(AP5:AT5)>=1),AND(COUNT(AK5:AO5)>=1,COUNT(AU5:AY5)>=1),AND(COUNT(AK5:AO5)>=1,COUNT(AZ5:BD5)>=1),AND(COUNT(AP5:AT5)>=1,COUNT(AU5:AY5)>=1),AND(COUNT(AP5:AT5)>=1,COUNT(AZ5:BD5)>=1),AND(COUNT(AU5:AY5)>=1,COUNT(AZ5:BD5)>=1))), "Yes", "No") -> No | CA5: 46038 | CB5: =IF(AND(BV5="",BW5="",BX5="",BY5="",BZ5="",CA5=""),"",COUNT(BV5:CA5)) -> 1 | CD5: No | CJ5: =IF(AK5="","","Q"&INT((MONTH(AK5)-1)/3)+1&YEAR(AK5)&$V5) | CK5: =IF(AL5="","","Q"&INT((MONTH(AL5)-1)/3)+1&YEAR(AL5)&$V5) | CL5: =IF(AM5="","","Q"&INT((MONTH(AM5)-1)/3)+1&YEAR(AM5)&$V5) | CM5: =IF(AN5="","","Q"&INT((MONTH(AN5)-1)/3)+1&YEAR(AN5)&$V5) | CN5: =IF(AO5="","","Q"&INT((MONTH(AO5)-1)/3)+1&YEAR(AO5)&$V5) | CO5: =IF(AP5="","","Q"&INT((MONTH(AP5)-1)/3)+1&YEAR(AP5)&$V5) | CP5: =IF(AQ5="","","Q"&INT((MONTH(AQ5)-1)/3)+1&YEAR(AQ5)&$V5) | CQ5: =IF(AR5="","","Q"&INT((MONTH(AR5)-1)/3)+1&YEAR(AR5)&$V5) | ... DC5: =IF(BD5="","","Q"&INT((MONTH(BD5)-1)/3)+1&YEAR(BD5)&$V5) | DD5: =IF(BV5="","","Q"&INT((MONTH(BV5)-1)/3)+1&YEAR(BV5)&$V5) | DE5: =IF(BW5="","","Q"&INT((MONTH(BW5)-1)/3)+1&YEAR(BW5)&$V5) | DF5: =IF(BX5="","","Q"&INT((MONTH(BX5)-1)/3)+1&YEAR(BX5)&$V5) | DG5: =IF(BY5="","","Q"&INT((MONTH(BY5)-1)/3)+1&YEAR(BY5)&$V5) | DH5: =IF(BZ5="","","Q"&INT((MONTH(BZ5)-1)/3)+1&YEAR(BZ5)&$V5) | DI5: =IF(CA5="","","Q"&INT((MONTH(CA5)-1)/3)+1&YEAR(CA5)&$V5) -> #N/A | DJ5: =IF(BR5="","",IF(BR5="Yes","Q"&INT((MONTH(BK5)-1)/3)+1&YEAR(BK5)&$V5,"na")) | DK5: =IF(BU5="","",IF(BU5="Alive","Q"&INT((MONTH(BK5)-1)/3)+1&YEAR(BK5)&$V5,"na")) | DL5: =IF(BJ5="","","Q"&INT((MONTH(BJ5)-1)/3)+1&YEAR(BJ5)&$V5) | DM5: =IF(M5="","",TEXT(M5,"mmmm")&YEAR(M5)) | DN5: =IF(BE5>=4,N5&P5,"") | DO5: =IF(BK5="","",TEXT(BK5,"mmmm")&YEAR(BK5)) | DP5: =IF(AK5="","",1) | EJ5: =SUM($DP$3:DP27) -> 0 | EK5: =SUM($DP$3:DQ27) -> 0 | EL5: =SUM($DP$3:DR27) -> 0 | EM5: =SUM($DP$3:DS27) -> 0 | EN5: =SUM($DP$3:DT27) -> 0 | EO5: =SUM($DP$3:DU27) -> 0 | EP5: =SUM($DP$3:DV27) -> 0 | EQ5: =SUM($DP$3:DW27) -> 0 | ... FC5: =SUM($DP$3:EI27) -> 0
Q6: 4 | S6: Ma Khin Zaw Lwin | T6: 28 | U6: =IF(ISBLANK(T6),"", IF(T6<5,"<5 yrs", IF(AND(T6>=5,T6<=14),"5 - 14 yrs", IF(AND(T6>=15,T6<=18),"15 - 18 yrs", IF(AND(T6>=19,T6<=49),"19 - 49 yrs", IF(T6>=50,"50 yrs +","")))))) -> 19 - 49 yrs | W6: Burma | X6: No
B7: BHA | L7: =IFERROR(VLOOKUP([10]!family_planning[[#This Row],[Helper]],[10]datavalidation!E:G,3,FALSE),"") | N7: =IF(mshn_database[[#This Row],[Date of Registration '[mm/dd/yy']]]="","",TEXT(mshn_database[[#This Row],[Date of Registration '[mm/dd/yy']]],"mmmm")) | O7: =IF(mshn_database[[#This Row],[Date of Registration '[mm/dd/yy']]]="","","Q"&INT((MONTH(mshn_database[[#This Row],[Date of Registration '[mm/dd/yy']]])-1)/3)+1) | P7: =IF(mshn_database[[#This Row],[Date of Registration '[mm/dd/yy']]]="","",TEXT(mshn_database[[#This Row],[Date of Registration '[mm/dd/yy']]],"yyyy")) | R7: =IF(Q7="","",C7&"-"&D7&"-"&"BHA-MCH-"&Q7) | U7: =IF(ISBLANK(T7),"", IF(T7<5,"<5 yrs", IF(AND(T7>=5,T7<=14),"5 - 14 yrs", IF(AND(T7>=15,T7<=18),"15 - 18 yrs", IF(AND(T7>=19,T7<=49),"19 - 49 yrs", IF(T7>=50,"50 yrs +","")))))) | V7: =IF(mshn_database[[#This Row],[Age_Category]]="","",VLOOKUP(mshn_database[[#This Row],[Age_Category]],[10]info!$H$2:$I$6,2,FALSE)) | AC7: =IF(AB7="","",IF(AND(TODAY()>=AB7,BU7=""),"Need LB info","No need info yet/LB info aldy included")) | BE7: =COUNT(AK7:BD7) -> 0 | BF7: =IF((OR(AND(COUNT(AK7:AO7)>=1,COUNT(AP7:AT7)>=1),AND(COUNT(AK7:AO7)>=1,COUNT(AU7:AY7)>=1),AND(COUNT(AK7:AO7)>=1,COUNT(AZ7:BD7)>=1),AND(COUNT(AP7:AT7)>=1,COUNT(AU7:AY7)>=1),AND(COUNT(AP7:AT7)>=1,COUNT(AZ7:BD7)>=1),AND(COUNT(AU7:AY7)>=1,COUNT(AZ7:BD7)>=1))), "Yes", "No") -> No | CB7: =IF(AND(BV7="",BW7="",BX7="",BY7="",BZ7="",CA7=""),"",COUNT(BV7:CA7)) | CD7: No | CJ7: =IF(AK7="","","Q"&INT((MONTH(AK7)-1)/3)+1&YEAR(AK7)&$V7) | CK7: =IF(AL7="","","Q"&INT((MONTH(AL7)-1)/3)+1&YEAR(AL7)&$V7) | CL7: =IF(AM7="","","Q"&INT((MONTH(AM7)-1)/3)+1&YEAR(AM7)&$V7) | CM7: =IF(AN7="","","Q"&INT((MONTH(AN7)-1)/3)+1&YEAR(AN7)&$V7) | CN7: =IF(AO7="","","Q"&INT((MONTH(AO7)-1)/3)+1&YEAR(AO7)&$V7) | CO7: =IF(AP7="","","Q"&INT((MONTH(AP7)-1)/3)+1&YEAR(AP7)&$V7) | CP7: =IF(AQ7="","","Q"&INT((MONTH(AQ7)-1)/3)+1&YEAR(AQ7)&$V7) | CQ7: =IF(AR7="","","Q"&INT((MONTH(AR7)-1)/3)+1&YEAR(AR7)&$V7) | ... DC7: =IF(BD7="","","Q"&INT((MONTH(BD7)-1)/3)+1&YEAR(BD7)&$V7) | DD7: =IF(BV7="","","Q"&INT((MONTH(BV7)-1)/3)+1&YEAR(BV7)&$V7) | DE7: =IF(BW7="","","Q"&INT((MONTH(BW7)-1)/3)+1&YEAR(BW7)&$V7) | DF7: =IF(BX7="","","Q"&INT((MONTH(BX7)-1)/3)+1&YEAR(BX7)&$V7) | DG7: =IF(BY7="","","Q"&INT((MONTH(BY7)-1)/3)+1&YEAR(BY7)&$V7) | DH7: =IF(BZ7="","","Q"&INT((MONTH(BZ7)-1)/3)+1&YEAR(BZ7)&$V7) | DI7: =IF(CA7="","","Q"&INT((MONTH(CA7)-1)/3)+1&YEAR(CA7)&$V7) | DJ7: =IF(BR7="","",IF(BR7="Yes","Q"&INT((MONTH(BK7)-1)/3)+1&YEAR(BK7)&$V7,"na")) | DK7: =IF(BU7="","",IF(BU7="Alive","Q"&INT((MONTH(BK7)-1)/3)+1&YEAR(BK7)&$V7,"na")) | DL7: =IF(BJ7="","","Q"&INT((MONTH(BJ7)-1)/3)+1&YEAR(BJ7)&$V7) | DM7: =IF(M7="","",TEXT(M7,"mmmm")&YEAR(M7)) | DN7: =IF(BE7>=4,N7&P7,"") | DO7: =IF(BK7="","",TEXT(BK7,"mmmm")&YEAR(BK7)) | DP7: =IF(AK7="","",1) | EJ7: =SUM($DP$3:DP27) -> 0 | EK7: =SUM($DP$3:DQ27) -> 0 | EL7: =SUM($DP$3:DR27) -> 0 | EM7: =SUM($DP$3:DS27) -> 0 | EN7: =SUM($DP$3:DT27) -> 0 | EO7: =SUM($DP$3:DU27) -> 0 | EP7: =SUM($DP$3:DV27) -> 0 | EQ7: =SUM($DP$3:DW27) -> 0 | ... FC7: =SUM($DP$3:EI27) -> 0
B8: BHA | L8: =IFERROR(VLOOKUP([10]!family_planning[[#This Row],[Helper]],[10]datavalidation!E:G,3,FALSE),"") | N8: =IF(mshn_database[[#This Row],[Date of Registration '[mm/dd/yy']]]="","",TEXT(mshn_database[[#This Row],[Date of Registration '[mm/dd/yy']]],"mmmm")) | O8: =IF(mshn_database[[#This Row],[Date of Registration '[mm/dd/yy']]]="","","Q"&INT((MONTH(mshn_database[[#This Row],[Date of Registration '[mm/dd/yy']]])-1)/3)+1) | P8: =IF(mshn_database[[#This Row],[Date of Registration '[mm/dd/yy']]]="","",TEXT(mshn_database[[#This Row],[Date of Registration '[mm/dd/yy']]],"yyyy")) | R8: =IF(Q8="","",C8&"-"&D8&"-"&"BHA-MCH-"&Q8) | U8: =IF(ISBLANK(T8),"", IF(T8<5,"<5 yrs", IF(AND(T8>=5,T8<=14),"5 - 14 yrs", IF(AND(T8>=15,T8<=18),"15 - 18 yrs", IF(AND(T8>=19,T8<=49),"19 - 49 yrs", IF(T8>=50,"50 yrs +","")))))) | V8: =IF(mshn_database[[#This Row],[Age_Category]]="","",VLOOKUP(mshn_database[[#This Row],[Age_Category]],[10]info!$H$2:$I$6,2,FALSE)) | AC8: =IF(AB8="","",IF(AND(TODAY()>=AB8,BU8=""),"Need LB info","No need info yet/LB info aldy included")) | BE8: =COUNT(AK8:BD8) -> 0 | BF8: =IF((OR(AND(COUNT(AK8:AO8)>=1,COUNT(AP8:AT8)>=1),AND(COUNT(AK8:AO8)>=1,COUNT(AU8:AY8)>=1),AND(COUNT(AK8:AO8)>=1,COUNT(AZ8:BD8)>=1),AND(COUNT(AP8:AT8)>=1,COUNT(AU8:AY8)>=1),AND(COUNT(AP8:AT8)>=1,COUNT(AZ8:BD8)>=1),AND(COUNT(AU8:AY8)>=1,COUNT(AZ8:BD8)>=1))), "Yes", "No") -> No | CB8: =IF(AND(BV8="",BW8="",BX8="",BY8="",BZ8="",CA8=""),"",COUNT(BV8:CA8)) | CJ8: =IF(AK8="","","Q"&INT((MONTH(AK8)-1)/3)+1&YEAR(AK8)&$V8) | CK8: =IF(AL8="","","Q"&INT((MONTH(AL8)-1)/3)+1&YEAR(AL8)&$V8) | CL8: =IF(AM8="","","Q"&INT((MONTH(AM8)-1)/3)+1&YEAR(AM8)&$V8) | CM8: =IF(AN8="","","Q"&INT((MONTH(AN8)-1)/3)+1&YEAR(AN8)&$V8) | CN8: =IF(AO8="","","Q"&INT((MONTH(AO8)-1)/3)+1&YEAR(AO8)&$V8) | CO8: =IF(AP8="","","Q"&INT((MONTH(AP8)-1)/3)+1&YEAR(AP8)&$V8) | CP8: =IF(AQ8="","","Q"&INT((MONTH(AQ8)-1)/3)+1&YEAR(AQ8)&$V8) | CQ8: =IF(AR8="","","Q"&INT((MONTH(AR8)-1)/3)+1&YEAR(AR8)&$V8) | ... DC8: =IF(BD8="","","Q"&INT((MONTH(BD8)-1)/3)+1&YEAR(BD8)&$V8) | DD8: =IF(BV8="","","Q"&INT((MONTH(BV8)-1)/3)+1&YEAR(BV8)&$V8) | DE8: =IF(BW8="","","Q"&INT((MONTH(BW8)-1)/3)+1&YEAR(BW8)&$V8) | DF8: =IF(BX8="","","Q"&INT((MONTH(BX8)-1)/3)+1&YEAR(BX8)&$V8) | DG8: =IF(BY8="","","Q"&INT((MONTH(BY8)-1)/3)+1&YEAR(BY8)&$V8) | DH8: =IF(BZ8="","","Q"&INT((MONTH(BZ8)-1)/3)+1&YEAR(BZ8)&$V8) | DI8: =IF(CA8="","","Q"&INT((MONTH(CA8)-1)/3)+1&YEAR(CA8)&$V8) | DJ8: =IF(BR8="","",IF(BR8="Yes","Q"&INT((MONTH(BK8)-1)/3)+1&YEAR(BK8)&$V8,"na")) | DK8: =IF(BU8="","",IF(BU8="Alive","Q"&INT((MONTH(BK8)-1)/3)+1&YEAR(BK8)&$V8,"na")) | DL8: =IF(BJ8="","","Q"&INT((MONTH(BJ8)-1)/3)+1&YEAR(BJ8)&$V8) | DM8: =IF(M8="","",TEXT(M8,"mmmm")&YEAR(M8)) | DN8: =IF(BE8>=4,N8&P8,"") | DO8: =IF(BK8="","",TEXT(BK8,"mmmm")&YEAR(BK8)) | DP8: =IF(AK8="","",1) | EJ8: =SUM($DP$3:DP8) -> 0 | EK8: =SUM($DP$3:DQ8) -> 0 | EL8: =SUM($DP$3:DR8) -> 0 | EM8: =SUM($DP$3:DS8) -> 0 | EN8: =SUM($DP$3:DT8) -> 0 | EO8: =SUM($DP$3:DU8) -> 0 | EP8: =SUM($DP$3:DV8) -> 0 | EQ8: =SUM($DP$3:DW8) -> 0 | ... FC8: =SUM($DP$3:EI8) -> 0
B9: BHA | L9: =IFERROR(VLOOKUP([10]!family_planning[[#This Row],[Helper]],[10]datavalidation!E:G,3,FALSE),"") | N9: =IF(mshn_database[[#This Row],[Date of Registration '[mm/dd/yy']]]="","",TEXT(mshn_database[[#This Row],[Date of Registration '[mm/dd/yy']]],"mmmm")) | O9: =IF(mshn_database[[#This Row],[Date of Registration '[mm/dd/yy']]]="","","Q"&INT((MONTH(mshn_database[[#This Row],[Date of Registration '[mm/dd/yy']]])-1)/3)+1) | P9: =IF(mshn_database[[#This Row],[Date of Registration '[mm/dd/yy']]]="","",TEXT(mshn_database[[#This Row],[Date of Registration '[mm/dd/yy']]],"yyyy")) | R9: =IF(Q9="","",C9&"-"&D9&"-"&"BHA-MCH-"&Q9) | U9: =IF(ISBLANK(T9),"", IF(T9<5,"<5 yrs", IF(AND(T9>=5,T9<=14),"5 - 14 yrs", IF(AND(T9>=15,T9<=18),"15 - 18 yrs", IF(AND(T9>=19,T9<=49),"19 - 49 yrs", IF(T9>=50,"50 yrs +","")))))) | V9: =IF(mshn_database[[#This Row],[Age_Category]]="","",VLOOKUP(mshn_database[[#This Row],[Age_Category]],[10]info!$H$2:$I$6,2,FALSE)) | AC9: =IF(AB9="","",IF(AND(TODAY()>=AB9,BU9=""),"Need LB info","No need info yet/LB info aldy included")) | BE9: =COUNT(AK9:BD9) -> 0 | BF9: =IF((OR(AND(COUNT(AK9:AO9)>=1,COUNT(AP9:AT9)>=1),AND(COUNT(AK9:AO9)>=1,COUNT(AU9:AY9)>=1),AND(COUNT(AK9:AO9)>=1,COUNT(AZ9:BD9)>=1),AND(COUNT(AP9:AT9)>=1,COUNT(AU9:AY9)>=1),AND(COUNT(AP9:AT9)>=1,COUNT(AZ9:BD9)>=1),AND(COUNT(AU9:AY9)>=1,COUNT(AZ9:BD9)>=1))), "Yes", "No") -> No | CB9: =IF(AND(BV9="",BW9="",BX9="",BY9="",BZ9="",CA9=""),"",COUNT(BV9:CA9)) | CJ9: =IF(AK9="","","Q"&INT((MONTH(AK9)-1)/3)+1&YEAR(AK9)&$V9) | CK9: =IF(AL9="","","Q"&INT((MONTH(AL9)-1)/3)+1&YEAR(AL9)&$V9) | CL9: =IF(AM9="","","Q"&INT((MONTH(AM9)-1)/3)+1&YEAR(AM9)&$V9) | CM9: =IF(AN9="","","Q"&INT((MONTH(AN9)-1)/3)+1&YEAR(AN9)&$V9) | CN9: =IF(AO9="","","Q"&INT((MONTH(AO9)-1)/3)+1&YEAR(AO9)&$V9) | CO9: =IF(AP9="","","Q"&INT((MONTH(AP9)-1)/3)+1&YEAR(AP9)&$V9) | CP9: =IF(AQ9="","","Q"&INT((MONTH(AQ9)-1)/3)+1&YEAR(AQ9)&$V9) | CQ9: =IF(AR9="","","Q"&INT((MONTH(AR9)-1)/3)+1&YEAR(AR9)&$V9) | ... DC9: =IF(BD9="","","Q"&INT((MONTH(BD9)-1)/3)+1&YEAR(BD9)&$V9) | DD9: =IF(BV9="","","Q"&INT((MONTH(BV9)-1)/3)+1&YEAR(BV9)&$V9) | DE9: =IF(BW9="","","Q"&INT((MONTH(BW9)-1)/3)+1&YEAR(BW9)&$V9) | DF9: =IF(BX9="","","Q"&INT((MONTH(BX9)-1)/3)+1&YEAR(BX9)&$V9) | DG9: =IF(BY9="","","Q"&INT((MONTH(BY9)-1)/3)+1&YEAR(BY9)&$V9) | DH9: =IF(BZ9="","","Q"&INT((MONTH(BZ9)-1)/3)+1&YEAR(BZ9)&$V9) | DI9: =IF(CA9="","","Q"&INT((MONTH(CA9)-1)/3)+1&YEAR(CA9)&$V9) | DJ9: =IF(BR9="","",IF(BR9="Yes","Q"&INT((MONTH(BK9)-1)/3)+1&YEAR(BK9)&$V9,"na")) | DK9: =IF(BU9="","",IF(BU9="Alive","Q"&INT((MONTH(BK9)-1)/3)+1&YEAR(BK9)&$V9,"na")) | DL9: =IF(BJ9="","","Q"&INT((MONTH(BJ9)-1)/3)+1&YEAR(BJ9)&$V9) | DM9: =IF(M9="","",TEXT(M9,"mmmm")&YEAR(M9)) | DN9: =IF(BE9>=4,N9&P9,"") | DO9: =IF(BK9="","",TEXT(BK9,"mmmm")&YEAR(BK9)) | DP9: =IF(AK9="","",1) | EJ9: =SUM($DP$3:DP9) -> 0 | EK9: =SUM($DP$3:DQ9) -> 0 | EL9: =SUM($DP$3:DR9) -> 0 | EM9: =SUM($DP$3:DS9) -> 0 | EN9: =SUM($DP$3:DT9) -> 0 | EO9: =SUM($DP$3:DU9) -> 0 | EP9: =SUM($DP$3:DV9) -> 0 | EQ9: =SUM($DP$3:DW9) -> 0 | ... FC9: =SUM($DP$3:EI9) -> 0
B10: BHA | L10: =IFERROR(VLOOKUP([10]!family_planning[[#This Row],[Helper]],[10]datavalidation!E:G,3,FALSE),"") | N10: =IF(mshn_database[[#This Row],[Date of Registration '[mm/dd/yy']]]="","",TEXT(mshn_database[[#This Row],[Date of Registration '[mm/dd/yy']]],"mmmm")) | O10: =IF(mshn_database[[#This Row],[Date of Registration '[mm/dd/yy']]]="","","Q"&INT((MONTH(mshn_database[[#This Row],[Date of Registration '[mm/dd/yy']]])-1)/3)+1) | P10: =IF(mshn_database[[#This Row],[Date of Registration '[mm/dd/yy']]]="","",TEXT(mshn_database[[#This Row],[Date of Registration '[mm/dd/yy']]],"yyyy")) | R10: =IF(Q10="","",C10&"-"&D10&"-"&"BHA-MCH-"&Q10) | U10: =IF(ISBLANK(T10),"", IF(T10<5,"<5 yrs", IF(AND(T10>=5,T10<=14),"5 - 14 yrs", IF(AND(T10>=15,T10<=18),"15 - 18 yrs", IF(AND(T10>=19,T10<=49),"19 - 49 yrs", IF(T10>=50,"50 yrs +","")))))) | V10: =IF(mshn_database[[#This Row],[Age_Category]]="","",VLOOKUP(mshn_database[[#This Row],[Age_Category]],[10]info!$H$2:$I$6,2,FALSE)) | AC10: =IF(AB10="","",IF(AND(TODAY()>=AB10,BU10=""),"Need LB info","No need info yet/LB info aldy included")) | BE10: =COUNT(AK10:BD10) -> 0 | BF10: =IF((OR(AND(COUNT(AK10:AO10)>=1,COUNT(AP10:AT10)>=1),AND(COUNT(AK10:AO10)>=1,COUNT(AU10:AY10)>=1),AND(COUNT(AK10:AO10)>=1,COUNT(AZ10:BD10)>=1),AND(COUNT(AP10:AT10)>=1,COUNT(AU10:AY10)>=1),AND(COUNT(AP10:AT10)>=1,COUNT(AZ10:BD10)>=1),AND(COUNT(AU10:AY10)>=1,COUNT(AZ10:BD10)>=1))), "Yes", "No") -> No | CB10: =IF(AND(BV10="",BW10="",BX10="",BY10="",BZ10="",CA10=""),"",COUNT(BV10:CA10)) | CJ10: =IF(AK10="","","Q"&INT((MONTH(AK10)-1)/3)+1&YEAR(AK10)&$V10) | CK10: =IF(AL10="","","Q"&INT((MONTH(AL10)-1)/3)+1&YEAR(AL10)&$V10) | CL10: =IF(AM10="","","Q"&INT((MONTH(AM10)-1)/3)+1&YEAR(AM10)&$V10) | CM10: =IF(AN10="","","Q"&INT((MONTH(AN10)-1)/3)+1&YEAR(AN10)&$V10) | CN10: =IF(AO10="","","Q"&INT((MONTH(AO10)-1)/3)+1&YEAR(AO10)&$V10) | CO10: =IF(AP10="","","Q"&INT((MONTH(AP10)-1)/3)+1&YEAR(AP10)&$V10) | CP10: =IF(AQ10="","","Q"&INT((MONTH(AQ10)-1)/3)+1&YEAR(AQ10)&$V10) | CQ10: =IF(AR10="","","Q"&INT((MONTH(AR10)-1)/3)+1&YEAR(AR10)&$V10) | ... DC10: =IF(BD10="","","Q"&INT((MONTH(BD10)-1)/3)+1&YEAR(BD10)&$V10) | DD10: =IF(BV10="","","Q"&INT((MONTH(BV10)-1)/3)+1&YEAR(BV10)&$V10) | DE10: =IF(BW10="","","Q"&INT((MONTH(BW10)-1)/3)+1&YEAR(BW10)&$V10) | DF10: =IF(BX10="","","Q"&INT((MONTH(BX10)-1)/3)+1&YEAR(BX10)&$V10) | DG10: =IF(BY10="","","Q"&INT((MONTH(BY10)-1)/3)+1&YEAR(BY10)&$V10) | DH10: =IF(BZ10="","","Q"&INT((MONTH(BZ10)-1)/3)+1&YEAR(BZ10)&$V10) | DI10: =IF(CA10="","","Q"&INT((MONTH(CA10)-1)/3)+1&YEAR(CA10)&$V10) | DJ10: =IF(BR10="","",IF(BR10="Yes","Q"&INT((MONTH(BK10)-1)/3)+1&YEAR(BK10)&$V10,"na")) | DK10: =IF(BU10="","",IF(BU10="Alive","Q"&INT((MONTH(BK10)-1)/3)+1&YEAR(BK10)&$V10,"na")) | DL10: =IF(BJ10="","","Q"&INT((MONTH(BJ10)-1)/3)+1&YEAR(BJ10)&$V10) | DM10: =IF(M10="","",TEXT(M10,"mmmm")&YEAR(M10)) | DN10: =IF(BE10>=4,N10&P10,"") | DO10: =IF(BK10="","",TEXT(BK10,"mmmm")&YEAR(BK10)) | DP10: =IF(AK10="","",1) | EJ10: =SUM($DP$3:DP10) -> 0 | EK10: =SUM($DP$3:DQ10) -> 0 | EL10: =SUM($DP$3:DR10) -> 0 | EM10: =SUM($DP$3:DS10) -> 0 | EN10: =SUM($DP$3:DT10) -> 0 | EO10: =SUM($DP$3:DU10) -> 0 | EP10: =SUM($DP$3:DV10) -> 0 | EQ10: =SUM($DP$3:DW10) -> 0 | ... FC10: =SUM($DP$3:EI10) -> 0
B11: BHA | L11: =IFERROR(VLOOKUP([10]!family_planning[[#This Row],[Helper]],[10]datavalidation!E:G,3,FALSE),"") | N11: =IF(mshn_database[[#This Row],[Date of Registration '[mm/dd/yy']]]="","",TEXT(mshn_database[[#This Row],[Date of Registration '[mm/dd/yy']]],"mmmm")) | O11: =IF(mshn_database[[#This Row],[Date of Registration '[mm/dd/yy']]]="","","Q"&INT((MONTH(mshn_database[[#This Row],[Date of Registration '[mm/dd/yy']]])-1)/3)+1) | P11: =IF(mshn_database[[#This Row],[Date of Registration '[mm/dd/yy']]]="","",TEXT(mshn_database[[#This Row],[Date of Registration '[mm/dd/yy']]],"yyyy")) | R11: =IF(Q11="","",C11&"-"&D11&"-"&"BHA-MCH-"&Q11) | U11: =IF(ISBLANK(T11),"", IF(T11<5,"<5 yrs", IF(AND(T11>=5,T11<=14),"5 - 14 yrs", IF(AND(T11>=15,T11<=18),"15 - 18 yrs", IF(AND(T11>=19,T11<=49),"19 - 49 yrs", IF(T11>=50,"50 yrs +","")))))) | V11: =IF(mshn_database[[#This Row],[Age_Category]]="","",VLOOKUP(mshn_database[[#This Row],[Age_Category]],[10]info!$H$2:$I$6,2,FALSE)) | AC11: =IF(AB11="","",IF(AND(TODAY()>=AB11,BU11=""),"Need LB info","No need info yet/LB info aldy included")) | BE11: =COUNT(AK11:BD11) -> 0 | BF11: =IF((OR(AND(COUNT(AK11:AO11)>=1,COUNT(AP11:AT11)>=1),AND(COUNT(AK11:AO11)>=1,COUNT(AU11:AY11)>=1),AND(COUNT(AK11:AO11)>=1,COUNT(AZ11:BD11)>=1),AND(COUNT(AP11:AT11)>=1,COUNT(AU11:AY11)>=1),AND(COUNT(AP11:AT11)>=1,COUNT(AZ11:BD11)>=1),AND(COUNT(AU11:AY11)>=1,COUNT(AZ11:BD11)>=1))), "Yes", "No") -> No | CB11: =IF(AND(BV11="",BW11="",BX11="",BY11="",BZ11="",CA11=""),"",COUNT(BV11:CA11)) | CJ11: =IF(AK11="","","Q"&INT((MONTH(AK11)-1)/3)+1&YEAR(AK11)&$V11) | CK11: =IF(AL11="","","Q"&INT((MONTH(AL11)-1)/3)+1&YEAR(AL11)&$V11) | CL11: =IF(AM11="","","Q"&INT((MONTH(AM11)-1)/3)+1&YEAR(AM11)&$V11) | CM11: =IF(AN11="","","Q"&INT((MONTH(AN11)-1)/3)+1&YEAR(AN11)&$V11) | CN11: =IF(AO11="","","Q"&INT((MONTH(AO11)-1)/3)+1&YEAR(AO11)&$V11) | CO11: =IF(AP11="","","Q"&INT((MONTH(AP11)-1)/3)+1&YEAR(AP11)&$V11) | CP11: =IF(AQ11="","","Q"&INT((MONTH(AQ11)-1)/3)+1&YEAR(AQ11)&$V11) | CQ11: =IF(AR11="","","Q"&INT((MONTH(AR11)-1)/3)+1&YEAR(AR11)&$V11) | ... DC11: =IF(BD11="","","Q"&INT((MONTH(BD11)-1)/3)+1&YEAR(BD11)&$V11) | DD11: =IF(BV11="","","Q"&INT((MONTH(BV11)-1)/3)+1&YEAR(BV11)&$V11) | DE11: =IF(BW11="","","Q"&INT((MONTH(BW11)-1)/3)+1&YEAR(BW11)&$V11) | DF11: =IF(BX11="","","Q"&INT((MONTH(BX11)-1)/3)+1&YEAR(BX11)&$V11) | DG11: =IF(BY11="","","Q"&INT((MONTH(BY11)-1)/3)+1&YEAR(BY11)&$V11) | DH11: =IF(BZ11="","","Q"&INT((MONTH(BZ11)-1)/3)+1&YEAR(BZ11)&$V11) | DI11: =IF(CA11="","","Q"&INT((MONTH(CA11)-1)/3)+1&YEAR(CA11)&$V11) | DJ11: =IF(BR11="","",IF(BR11="Yes","Q"&INT((MONTH(BK11)-1)/3)+1&YEAR(BK11)&$V11,"na")) | DK11: =IF(BU11="","",IF(BU11="Alive","Q"&INT((MONTH(BK11)-1)/3)+1&YEAR(BK11)&$V11,"na")) | DL11: =IF(BJ11="","","Q"&INT((MONTH(BJ11)-1)/3)+1&YEAR(BJ11)&$V11) | DM11: =IF(M11="","",TEXT(M11,"mmmm")&YEAR(M11)) | DN11: =IF(BE11>=4,N11&P11,"") | DO11: =IF(BK11="","",TEXT(BK11,"mmmm")&YEAR(BK11)) | DP11: =IF(AK11="","",1) | EJ11: =SUM($DP$3:DP11) -> 0 | EK11: =SUM($DP$3:DQ11) -> 0 | EL11: =SUM($DP$3:DR11) -> 0 | EM11: =SUM($DP$3:DS11) -> 0 | EN11: =SUM($DP$3:DT11) -> 0 | EO11: =SUM($DP$3:DU11) -> 0 | EP11: =SUM($DP$3:DV11) -> 0 | EQ11: =SUM($DP$3:DW11) -> 0 | ... FC11: =SUM($DP$3:EI11) -> 0
B12: BHA | L12: =IFERROR(VLOOKUP([10]!family_planning[[#This Row],[Helper]],[10]datavalidation!E:G,3,FALSE),"") | N12: =IF(mshn_database[[#This Row],[Date of Registration '[mm/dd/yy']]]="","",TEXT(mshn_database[[#This Row],[Date of Registration '[mm/dd/yy']]],"mmmm")) | O12: =IF(mshn_database[[#This Row],[Date of Registration '[mm/dd/yy']]]="","","Q"&INT((MONTH(mshn_database[[#This Row],[Date of Registration '[mm/dd/yy']]])-1)/3)+1) | P12: =IF(mshn_database[[#This Row],[Date of Registration '[mm/dd/yy']]]="","",TEXT(mshn_database[[#This Row],[Date of Registration '[mm/dd/yy']]],"yyyy")) | R12: =IF(Q12="","",C12&"-"&D12&"-"&"BHA-MCH-"&Q12) | U12: =IF(ISBLANK(T12),"", IF(T12<5,"<5 yrs", IF(AND(T12>=5,T12<=14),"5 - 14 yrs", IF(AND(T12>=15,T12<=18),"15 - 18 yrs", IF(AND(T12>=19,T12<=49),"19 - 49 yrs", IF(T12>=50,"50 yrs +","")))))) | V12: =IF(mshn_database[[#This Row],[Age_Category]]="","",VLOOKUP(mshn_database[[#This Row],[Age_Category]],[10]info!$H$2:$I$6,2,FALSE)) | AC12: =IF(AB12="","",IF(AND(TODAY()>=AB12,BU12=""),"Need LB info","No need info yet/LB info aldy included")) | BE12: =COUNT(AK12:BD12) -> 0 | BF12: =IF((OR(AND(COUNT(AK12:AO12)>=1,COUNT(AP12:AT12)>=1),AND(COUNT(AK12:AO12)>=1,COUNT(AU12:AY12)>=1),AND(COUNT(AK12:AO12)>=1,COUNT(AZ12:BD12)>=1),AND(COUNT(AP12:AT12)>=1,COUNT(AU12:AY12)>=1),AND(COUNT(AP12:AT12)>=1,COUNT(AZ12:BD12)>=1),AND(COUNT(AU12:AY12)>=1,COUNT(AZ12:BD12)>=1))), "Yes", "No") -> No | CB12: =IF(AND(BV12="",BW12="",BX12="",BY12="",BZ12="",CA12=""),"",COUNT(BV12:CA12)) | CJ12: =IF(AK12="","","Q"&INT((MONTH(AK12)-1)/3)+1&YEAR(AK12)&$V12) | CK12: =IF(AL12="","","Q"&INT((MONTH(AL12)-1)/3)+1&YEAR(AL12)&$V12) | CL12: =IF(AM12="","","Q"&INT((MONTH(AM12)-1)/3)+1&YEAR(AM12)&$V12) | CM12: =IF(AN12="","","Q"&INT((MONTH(AN12)-1)/3)+1&YEAR(AN12)&$V12) | CN12: =IF(AO12="","","Q"&INT((MONTH(AO12)-1)/3)+1&YEAR(AO12)&$V12) | CO12: =IF(AP12="","","Q"&INT((MONTH(AP12)-1)/3)+1&YEAR(AP12)&$V12) | CP12: =IF(AQ12="","","Q"&INT((MONTH(AQ12)-1)/3)+1&YEAR(AQ12)&$V12) | CQ12: =IF(AR12="","","Q"&INT((MONTH(AR12)-1)/3)+1&YEAR(AR12)&$V12) | ... DC12: =IF(BD12="","","Q"&INT((MONTH(BD12)-1)/3)+1&YEAR(BD12)&$V12) | DD12: =IF(BV12="","","Q"&INT((MONTH(BV12)-1)/3)+1&YEAR(BV12)&$V12) | DE12: =IF(BW12="","","Q"&INT((MONTH(BW12)-1)/3)+1&YEAR(BW12)&$V12) | DF12: =IF(BX12="","","Q"&INT((MONTH(BX12)-1)/3)+1&YEAR(BX12)&$V12) | DG12: =IF(BY12="","","Q"&INT((MONTH(BY12)-1)/3)+1&YEAR(BY12)&$V12) | DH12: =IF(BZ12="","","Q"&INT((MONTH(BZ12)-1)/3)+1&YEAR(BZ12)&$V12) | DI12: =IF(CA12="","","Q"&INT((MONTH(CA12)-1)/3)+1&YEAR(CA12)&$V12) | DJ12: =IF(BR12="","",IF(BR12="Yes","Q"&INT((MONTH(BK12)-1)/3)+1&YEAR(BK12)&$V12,"na")) | DK12: =IF(BU12="","",IF(BU12="Alive","Q"&INT((MONTH(BK12)-1)/3)+1&YEAR(BK12)&$V12,"na")) | DL12: =IF(BJ12="","","Q"&INT((MONTH(BJ12)-1)/3)+1&YEAR(BJ12)&$V12) | DM12: =IF(M12="","",TEXT(M12,"mmmm")&YEAR(M12)) | DN12: =IF(BE12>=4,N12&P12,"") | DO12: =IF(BK12="","",TEXT(BK12,"mmmm")&YEAR(BK12)) | DP12: =IF(AK12="","",1) | EJ12: =SUM($DP$3:DP12) -> 0 | EK12: =SUM($DP$3:DQ12) -> 0 | EL12: =SUM($DP$3:DR12) -> 0 | EM12: =SUM($DP$3:DS12) -> 0 | EN12: =SUM($DP$3:DT12) -> 0 | EO12: =SUM($DP$3:DU12) -> 0 | EP12: =SUM($DP$3:DV12) -> 0 | EQ12: =SUM($DP$3:DW12) -> 0 | ... FC12: =SUM($DP$3:EI12) -> 0
B13: BHA | L13: =IFERROR(VLOOKUP([10]!family_planning[[#This Row],[Helper]],[10]datavalidation!E:G,3,FALSE),"") | N13: =IF(mshn_database[[#This Row],[Date of Registration '[mm/dd/yy']]]="","",TEXT(mshn_database[[#This Row],[Date of Registration '[mm/dd/yy']]],"mmmm")) | O13: =IF(mshn_database[[#This Row],[Date of Registration '[mm/dd/yy']]]="","","Q"&INT((MONTH(mshn_database[[#This Row],[Date of Registration '[mm/dd/yy']]])-1)/3)+1) | P13: =IF(mshn_database[[#This Row],[Date of Registration '[mm/dd/yy']]]="","",TEXT(mshn_database[[#This Row],[Date of Registration '[mm/dd/yy']]],"yyyy")) | R13: =IF(Q13="","",C13&"-"&D13&"-"&"BHA-MCH-"&Q13) | U13: =IF(ISBLANK(T13),"", IF(T13<5,"<5 yrs", IF(AND(T13>=5,T13<=14),"5 - 14 yrs", IF(AND(T13>=15,T13<=18),"15 - 18 yrs", IF(AND(T13>=19,T13<=49),"19 - 49 yrs", IF(T13>=50,"50 yrs +","")))))) | V13: =IF(mshn_database[[#This Row],[Age_Category]]="","",VLOOKUP(mshn_database[[#This Row],[Age_Category]],[10]info!$H$2:$I$6,2,FALSE)) | AC13: =IF(AB13="","",IF(AND(TODAY()>=AB13,BU13=""),"Need LB info","No need info yet/LB info aldy included")) | BE13: =COUNT(AK13:BD13) -> 0 | BF13: =IF((OR(AND(COUNT(AK13:AO13)>=1,COUNT(AP13:AT13)>=1),AND(COUNT(AK13:AO13)>=1,COUNT(AU13:AY13)>=1),AND(COUNT(AK13:AO13)>=1,COUNT(AZ13:BD13)>=1),AND(COUNT(AP13:AT13)>=1,COUNT(AU13:AY13)>=1),AND(COUNT(AP13:AT13)>=1,COUNT(AZ13:BD13)>=1),AND(COUNT(AU13:AY13)>=1,COUNT(AZ13:BD13)>=1))), "Yes", "No") -> No | CB13: =IF(AND(BV13="",BW13="",BX13="",BY13="",BZ13="",CA13=""),"",COUNT(BV13:CA13)) | CJ13: =IF(AK13="","","Q"&INT((MONTH(AK13)-1)/3)+1&YEAR(AK13)&$V13) | CK13: =IF(AL13="","","Q"&INT((MONTH(AL13)-1)/3)+1&YEAR(AL13)&$V13) | CL13: =IF(AM13="","","Q"&INT((MONTH(AM13)-1)/3)+1&YEAR(AM13)&$V13) | CM13: =IF(AN13="","","Q"&INT((MONTH(AN13)-1)/3)+1&YEAR(AN13)&$V13) | CN13: =IF(AO13="","","Q"&INT((MONTH(AO13)-1)/3)+1&YEAR(AO13)&$V13) | CO13: =IF(AP13="","","Q"&INT((MONTH(AP13)-1)/3)+1&YEAR(AP13)&$V13) | CP13: =IF(AQ13="","","Q"&INT((MONTH(AQ13)-1)/3)+1&YEAR(AQ13)&$V13) | CQ13: =IF(AR13="","","Q"&INT((MONTH(AR13)-1)/3)+1&YEAR(AR13)&$V13) | ... DC13: =IF(BD13="","","Q"&INT((MONTH(BD13)-1)/3)+1&YEAR(BD13)&$V13) | DD13: =IF(BV13="","","Q"&INT((MONTH(BV13)-1)/3)+1&YEAR(BV13)&$V13) | DE13: =IF(BW13="","","Q"&INT((MONTH(BW13)-1)/3)+1&YEAR(BW13)&$V13) | DF13: =IF(BX13="","","Q"&INT((MONTH(BX13)-1)/3)+1&YEAR(BX13)&$V13) | DG13: =IF(BY13="","","Q"&INT((MONTH(BY13)-1)/3)+1&YEAR(BY13)&$V13) | DH13: =IF(BZ13="","","Q"&INT((MONTH(BZ13)-1)/3)+1&YEAR(BZ13)&$V13) | DI13: =IF(CA13="","","Q"&INT((MONTH(CA13)-1)/3)+1&YEAR(CA13)&$V13) | DJ13: =IF(BR13="","",IF(BR13="Yes","Q"&INT((MONTH(BK13)-1)/3)+1&YEAR(BK13)&$V13,"na")) | DK13: =IF(BU13="","",IF(BU13="Alive","Q"&INT((MONTH(BK13)-1)/3)+1&YEAR(BK13)&$V13,"na")) | DL13: =IF(BJ13="","","Q"&INT((MONTH(BJ13)-1)/3)+1&YEAR(BJ13)&$V13) | DM13: =IF(M13="","",TEXT(M13,"mmmm")&YEAR(M13)) | DN13: =IF(BE13>=4,N13&P13,"") | DO13: =IF(BK13="","",TEXT(BK13,"mmmm")&YEAR(BK13)) | DP13: =IF(AK13="","",1) | EJ13: =SUM($DP$3:DP13) -> 0 | EK13: =SUM($DP$3:DQ13) -> 0 | EL13: =SUM($DP$3:DR13) -> 0 | EM13: =SUM($DP$3:DS13) -> 0 | EN13: =SUM($DP$3:DT13) -> 0 | EO13: =SUM($DP$3:DU13) -> 0 | EP13: =SUM($DP$3:DV13) -> 0 | EQ13: =SUM($DP$3:DW13) -> 0 | ... FC13: =SUM($DP$3:EI13) -> 0
B14: BHA | L14: =IFERROR(VLOOKUP([10]!family_planning[[#This Row],[Helper]],[10]datavalidation!E:G,3,FALSE),"") | N14: =IF(mshn_database[[#This Row],[Date of Registration '[mm/dd/yy']]]="","",TEXT(mshn_database[[#This Row],[Date of Registration '[mm/dd/yy']]],"mmmm")) | O14: =IF(mshn_database[[#This Row],[Date of Registration '[mm/dd/yy']]]="","","Q"&INT((MONTH(mshn_database[[#This Row],[Date of Registration '[mm/dd/yy']]])-1)/3)+1) | P14: =IF(mshn_database[[#This Row],[Date of Registration '[mm/dd/yy']]]="","",TEXT(mshn_database[[#This Row],[Date of Registration '[mm/dd/yy']]],"yyyy")) | R14: =IF(Q14="","",C14&"-"&D14&"-"&"BHA-MCH-"&Q14) | U14: =IF(ISBLANK(T14),"", IF(T14<5,"<5 yrs", IF(AND(T14>=5,T14<=14),"5 - 14 yrs", IF(AND(T14>=15,T14<=18),"15 - 18 yrs", IF(AND(T14>=19,T14<=49),"19 - 49 yrs", IF(T14>=50,"50 yrs +","")))))) | V14: =IF(mshn_database[[#This Row],[Age_Category]]="","",VLOOKUP(mshn_database[[#This Row],[Age_Category]],[10]info!$H$2:$I$6,2,FALSE)) | AC14: =IF(AB14="","",IF(AND(TODAY()>=AB14,BU14=""),"Need LB info","No need info yet/LB info aldy included")) | BE14: =COUNT(AK14:BD14) -> 0 | BF14: =IF((OR(AND(COUNT(AK14:AO14)>=1,COUNT(AP14:AT14)>=1),AND(COUNT(AK14:AO14)>=1,COUNT(AU14:AY14)>=1),AND(COUNT(AK14:AO14)>=1,COUNT(AZ14:BD14)>=1),AND(COUNT(AP14:AT14)>=1,COUNT(AU14:AY14)>=1),AND(COUNT(AP14:AT14)>=1,COUNT(AZ14:BD14)>=1),AND(COUNT(AU14:AY14)>=1,COUNT(AZ14:BD14)>=1))), "Yes", "No") -> No | CB14: =IF(AND(BV14="",BW14="",BX14="",BY14="",BZ14="",CA14=""),"",COUNT(BV14:CA14)) | CJ14: =IF(AK14="","","Q"&INT((MONTH(AK14)-1)/3)+1&YEAR(AK14)&$V14) | CK14: =IF(AL14="","","Q"&INT((MONTH(AL14)-1)/3)+1&YEAR(AL14)&$V14) | CL14: =IF(AM14="","","Q"&INT((MONTH(AM14)-1)/3)+1&YEAR(AM14)&$V14) | CM14: =IF(AN14="","","Q"&INT((MONTH(AN14)-1)/3)+1&YEAR(AN14)&$V14) | CN14: =IF(AO14="","","Q"&INT((MONTH(AO14)-1)/3)+1&YEAR(AO14)&$V14) | CO14: =IF(AP14="","","Q"&INT((MONTH(AP14)-1)/3)+1&YEAR(AP14)&$V14) | CP14: =IF(AQ14="","","Q"&INT((MONTH(AQ14)-1)/3)+1&YEAR(AQ14)&$V14) | CQ14: =IF(AR14="","","Q"&INT((MONTH(AR14)-1)/3)+1&YEAR(AR14)&$V14) | ... DC14: =IF(BD14="","","Q"&INT((MONTH(BD14)-1)/3)+1&YEAR(BD14)&$V14) | DD14: =IF(BV14="","","Q"&INT((MONTH(BV14)-1)/3)+1&YEAR(BV14)&$V14) | DE14: =IF(BW14="","","Q"&INT((MONTH(BW14)-1)/3)+1&YEAR(BW14)&$V14) | DF14: =IF(BX14="","","Q"&INT((MONTH(BX14)-1)/3)+1&YEAR(BX14)&$V14) | DG14: =IF(BY14="","","Q"&INT((MONTH(BY14)-1)/3)+1&YEAR(BY14)&$V14) | DH14: =IF(BZ14="","","Q"&INT((MONTH(BZ14)-1)/3)+1&YEAR(BZ14)&$V14) | DI14: =IF(CA14="","","Q"&INT((MONTH(CA14)-1)/3)+1&YEAR(CA14)&$V14) | DJ14: =IF(BR14="","",IF(BR14="Yes","Q"&INT((MONTH(BK14)-1)/3)+1&YEAR(BK14)&$V14,"na")) | DK14: =IF(BU14="","",IF(BU14="Alive","Q"&INT((MONTH(BK14)-1)/3)+1&YEAR(BK14)&$V14,"na")) | DL14: =IF(BJ14="","","Q"&INT((MONTH(BJ14)-1)/3)+1&YEAR(BJ14)&$V14) | DM14: =IF(M14="","",TEXT(M14,"mmmm")&YEAR(M14)) | DN14: =IF(BE14>=4,N14&P14,"") | DO14: =IF(BK14="","",TEXT(BK14,"mmmm")&YEAR(BK14)) | DP14: =IF(AK14="","",1) | EJ14: =SUM($DP$3:DP14) -> 0 | EK14: =SUM($DP$3:DQ14) -> 0 | EL14: =SUM($DP$3:DR14) -> 0 | EM14: =SUM($DP$3:DS14) -> 0 | EN14: =SUM($DP$3:DT14) -> 0 | EO14: =SUM($DP$3:DU14) -> 0 | EP14: =SUM($DP$3:DV14) -> 0 | EQ14: =SUM($DP$3:DW14) -> 0 | ... FC14: =SUM($DP$3:EI14) -> 0
B15: BHA | L15: =IFERROR(VLOOKUP([10]!family_planning[[#This Row],[Helper]],[10]datavalidation!E:G,3,FALSE),"") | N15: =IF(mshn_database[[#This Row],[Date of Registration '[mm/dd/yy']]]="","",TEXT(mshn_database[[#This Row],[Date of Registration '[mm/dd/yy']]],"mmmm")) | O15: =IF(mshn_database[[#This Row],[Date of Registration '[mm/dd/yy']]]="","","Q"&INT((MONTH(mshn_database[[#This Row],[Date of Registration '[mm/dd/yy']]])-1)/3)+1) | P15: =IF(mshn_database[[#This Row],[Date of Registration '[mm/dd/yy']]]="","",TEXT(mshn_database[[#This Row],[Date of Registration '[mm/dd/yy']]],"yyyy")) | R15: =IF(Q15="","",C15&"-"&D15&"-"&"BHA-MCH-"&Q15) | U15: =IF(ISBLANK(T15),"", IF(T15<5,"<5 yrs", IF(AND(T15>=5,T15<=14),"5 - 14 yrs", IF(AND(T15>=15,T15<=18),"15 - 18 yrs", IF(AND(T15>=19,T15<=49),"19 - 49 yrs", IF(T15>=50,"50 yrs +","")))))) | V15: =IF(mshn_database[[#This Row],[Age_Category]]="","",VLOOKUP(mshn_database[[#This Row],[Age_Category]],[10]info!$H$2:$I$6,2,FALSE)) | AC15: =IF(AB15="","",IF(AND(TODAY()>=AB15,BU15=""),"Need LB info","No need info yet/LB info aldy included")) | BE15: =COUNT(AK15:BD15) -> 0 | BF15: =IF((OR(AND(COUNT(AK15:AO15)>=1,COUNT(AP15:AT15)>=1),AND(COUNT(AK15:AO15)>=1,COUNT(AU15:AY15)>=1),AND(COUNT(AK15:AO15)>=1,COUNT(AZ15:BD15)>=1),AND(COUNT(AP15:AT15)>=1,COUNT(AU15:AY15)>=1),AND(COUNT(AP15:AT15)>=1,COUNT(AZ15:BD15)>=1),AND(COUNT(AU15:AY15)>=1,COUNT(AZ15:BD15)>=1))), "Yes", "No") -> No | CB15: =IF(AND(BV15="",BW15="",BX15="",BY15="",BZ15="",CA15=""),"",COUNT(BV15:CA15)) | CJ15: =IF(AK15="","","Q"&INT((MONTH(AK15)-1)/3)+1&YEAR(AK15)&$V15) | CK15: =IF(AL15="","","Q"&INT((MONTH(AL15)-1)/3)+1&YEAR(AL15)&$V15) | CL15: =IF(AM15="","","Q"&INT((MONTH(AM15)-1)/3)+1&YEAR(AM15)&$V15) | CM15: =IF(AN15="","","Q"&INT((MONTH(AN15)-1)/3)+1&YEAR(AN15)&$V15) | CN15: =IF(AO15="","","Q"&INT((MONTH(AO15)-1)/3)+1&YEAR(AO15)&$V15) | CO15: =IF(AP15="","","Q"&INT((MONTH(AP15)-1)/3)+1&YEAR(AP15)&$V15) | CP15: =IF(AQ15="","","Q"&INT((MONTH(AQ15)-1)/3)+1&YEAR(AQ15)&$V15) | CQ15: =IF(AR15="","","Q"&INT((MONTH(AR15)-1)/3)+1&YEAR(AR15)&$V15) | ... DC15: =IF(BD15="","","Q"&INT((MONTH(BD15)-1)/3)+1&YEAR(BD15)&$V15) | DD15: =IF(BV15="","","Q"&INT((MONTH(BV15)-1)/3)+1&YEAR(BV15)&$V15) | DE15: =IF(BW15="","","Q"&INT((MONTH(BW15)-1)/3)+1&YEAR(BW15)&$V15) | DF15: =IF(BX15="","","Q"&INT((MONTH(BX15)-1)/3)+1&YEAR(BX15)&$V15) | DG15: =IF(BY15="","","Q"&INT((MONTH(BY15)-1)/3)+1&YEAR(BY15)&$V15) | DH15: =IF(BZ15="","","Q"&INT((MONTH(BZ15)-1)/3)+1&YEAR(BZ15)&$V15) | DI15: =IF(CA15="","","Q"&INT((MONTH(CA15)-1)/3)+1&YEAR(CA15)&$V15) | DJ15: =IF(BR15="","",IF(BR15="Yes","Q"&INT((MONTH(BK15)-1)/3)+1&YEAR(BK15)&$V15,"na")) | DK15: =IF(BU15="","",IF(BU15="Alive","Q"&INT((MONTH(BK15)-1)/3)+1&YEAR(BK15)&$V15,"na")) | DL15: =IF(BJ15="","","Q"&INT((MONTH(BJ15)-1)/3)+1&YEAR(BJ15)&$V15) | DM15: =IF(M15="","",TEXT(M15,"mmmm")&YEAR(M15)) | DN15: =IF(BE15>=4,N15&P15,"") | DO15: =IF(BK15="","",TEXT(BK15,"mmmm")&YEAR(BK15)) | DP15: =IF(AK15="","",1) | EJ15: =SUM($DP$3:DP15) -> 0 | EK15: =SUM($DP$3:DQ15) -> 0 | EL15: =SUM($DP$3:DR15) -> 0 | EM15: =SUM($DP$3:DS15) -> 0 | EN15: =SUM($DP$3:DT15) -> 0 | EO15: =SUM($DP$3:DU15) -> 0 | EP15: =SUM($DP$3:DV15) -> 0 | EQ15: =SUM($DP$3:DW15) -> 0 | ... FC15: =SUM($DP$3:EI15) -> 0
B16: BHA | L16: =IFERROR(VLOOKUP([10]!family_planning[[#This Row],[Helper]],[10]datavalidation!E:G,3,FALSE),"") | N16: =IF(mshn_database[[#This Row],[Date of Registration '[mm/dd/yy']]]="","",TEXT(mshn_database[[#This Row],[Date of Registration '[mm/dd/yy']]],"mmmm")) | O16: =IF(mshn_database[[#This Row],[Date of Registration '[mm/dd/yy']]]="","","Q"&INT((MONTH(mshn_database[[#This Row],[Date of Registration '[mm/dd/yy']]])-1)/3)+1) | P16: =IF(mshn_database[[#This Row],[Date of Registration '[mm/dd/yy']]]="","",TEXT(mshn_database[[#This Row],[Date of Registration '[mm/dd/yy']]],"yyyy")) | R16: =IF(Q16="","",C16&"-"&D16&"-"&"BHA-MCH-"&Q16) | U16: =IF(ISBLANK(T16),"", IF(T16<5,"<5 yrs", IF(AND(T16>=5,T16<=14),"5 - 14 yrs", IF(AND(T16>=15,T16<=18),"15 - 18 yrs", IF(AND(T16>=19,T16<=49),"19 - 49 yrs", IF(T16>=50,"50 yrs +","")))))) | V16: =IF(mshn_database[[#This Row],[Age_Category]]="","",VLOOKUP(mshn_database[[#This Row],[Age_Category]],[10]info!$H$2:$I$6,2,FALSE)) | AC16: =IF(AB16="","",IF(AND(TODAY()>=AB16,BU16=""),"Need LB info","No need info yet/LB info aldy included")) | BE16: =COUNT(AK16:BD16) -> 0 | BF16: =IF((OR(AND(COUNT(AK16:AO16)>=1,COUNT(AP16:AT16)>=1),AND(COUNT(AK16:AO16)>=1,COUNT(AU16:AY16)>=1),AND(COUNT(AK16:AO16)>=1,COUNT(AZ16:BD16)>=1),AND(COUNT(AP16:AT16)>=1,COUNT(AU16:AY16)>=1),AND(COUNT(AP16:AT16)>=1,COUNT(AZ16:BD16)>=1),AND(COUNT(AU16:AY16)>=1,COUNT(AZ16:BD16)>=1))), "Yes", "No") -> No | CB16: =IF(AND(BV16="",BW16="",BX16="",BY16="",BZ16="",CA16=""),"",COUNT(BV16:CA16)) | CJ16: =IF(AK16="","","Q"&INT((MONTH(AK16)-1)/3)+1&YEAR(AK16)&$V16) | CK16: =IF(AL16="","","Q"&INT((MONTH(AL16)-1)/3)+1&YEAR(AL16)&$V16) | CL16: =IF(AM16="","","Q"&INT((MONTH(AM16)-1)/3)+1&YEAR(AM16)&$V16) | CM16: =IF(AN16="","","Q"&INT((MONTH(AN16)-1)/3)+1&YEAR(AN16)&$V16) | CN16: =IF(AO16="","","Q"&INT((MONTH(AO16)-1)/3)+1&YEAR(AO16)&$V16) | CO16: =IF(AP16="","","Q"&INT((MONTH(AP16)-1)/3)+1&YEAR(AP16)&$V16) | CP16: =IF(AQ16="","","Q"&INT((MONTH(AQ16)-1)/3)+1&YEAR(AQ16)&$V16) | CQ16: =IF(AR16="","","Q"&INT((MONTH(AR16)-1)/3)+1&YEAR(AR16)&$V16) | ... DC16: =IF(BD16="","","Q"&INT((MONTH(BD16)-1)/3)+1&YEAR(BD16)&$V16) | DD16: =IF(BV16="","","Q"&INT((MONTH(BV16)-1)/3)+1&YEAR(BV16)&$V16) | DE16: =IF(BW16="","","Q"&INT((MONTH(BW16)-1)/3)+1&YEAR(BW16)&$V16) | DF16: =IF(BX16="","","Q"&INT((MONTH(BX16)-1)/3)+1&YEAR(BX16)&$V16) | DG16: =IF(BY16="","","Q"&INT((MONTH(BY16)-1)/3)+1&YEAR(BY16)&$V16) | DH16: =IF(BZ16="","","Q"&INT((MONTH(BZ16)-1)/3)+1&YEAR(BZ16)&$V16) | DI16: =IF(CA16="","","Q"&INT((MONTH(CA16)-1)/3)+1&YEAR(CA16)&$V16) | DJ16: =IF(BR16="","",IF(BR16="Yes","Q"&INT((MONTH(BK16)-1)/3)+1&YEAR(BK16)&$V16,"na")) | DK16: =IF(BU16="","",IF(BU16="Alive","Q"&INT((MONTH(BK16)-1)/3)+1&YEAR(BK16)&$V16,"na")) | DL16: =IF(BJ16="","","Q"&INT((MONTH(BJ16)-1)/3)+1&YEAR(BJ16)&$V16) | DM16: =IF(M16="","",TEXT(M16,"mmmm")&YEAR(M16)) | DN16: =IF(BE16>=4,N16&P16,"") | DO16: =IF(BK16="","",TEXT(BK16,"mmmm")&YEAR(BK16)) | DP16: =IF(AK16="","",1) | EJ16: =SUM($DP$3:DP16) -> 0 | EK16: =SUM($DP$3:DQ16) -> 0 | EL16: =SUM($DP$3:DR16) -> 0 | EM16: =SUM($DP$3:DS16) -> 0 | EN16: =SUM($DP$3:DT16) -> 0 | EO16: =SUM($DP$3:DU16) -> 0 | EP16: =SUM($DP$3:DV16) -> 0 | EQ16: =SUM($DP$3:DW16) -> 0 | ... FC16: =SUM($DP$3:EI16) -> 0
B17: BHA | L17: =IFERROR(VLOOKUP([10]!family_planning[[#This Row],[Helper]],[10]datavalidation!E:G,3,FALSE),"") | N17: =IF(mshn_database[[#This Row],[Date of Registration '[mm/dd/yy']]]="","",TEXT(mshn_database[[#This Row],[Date of Registration '[mm/dd/yy']]],"mmmm")) | O17: =IF(mshn_database[[#This Row],[Date of Registration '[mm/dd/yy']]]="","","Q"&INT((MONTH(mshn_database[[#This Row],[Date of Registration '[mm/dd/yy']]])-1)/3)+1) | P17: =IF(mshn_database[[#This Row],[Date of Registration '[mm/dd/yy']]]="","",TEXT(mshn_database[[#This Row],[Date of Registration '[mm/dd/yy']]],"yyyy")) | R17: =IF(Q17="","",C17&"-"&D17&"-"&"BHA-MCH-"&Q17) | U17: =IF(ISBLANK(T17),"", IF(T17<5,"<5 yrs", IF(AND(T17>=5,T17<=14),"5 - 14 yrs", IF(AND(T17>=15,T17<=18),"15 - 18 yrs", IF(AND(T17>=19,T17<=49),"19 - 49 yrs", IF(T17>=50,"50 yrs +","")))))) | V17: =IF(mshn_database[[#This Row],[Age_Category]]="","",VLOOKUP(mshn_database[[#This Row],[Age_Category]],[10]info!$H$2:$I$6,2,FALSE)) | AC17: =IF(AB17="","",IF(AND(TODAY()>=AB17,BU17=""),"Need LB info","No need info yet/LB info aldy included")) | BE17: =COUNT(AK17:BD17) -> 0 | BF17: =IF((OR(AND(COUNT(AK17:AO17)>=1,COUNT(AP17:AT17)>=1),AND(COUNT(AK17:AO17)>=1,COUNT(AU17:AY17)>=1),AND(COUNT(AK17:AO17)>=1,COUNT(AZ17:BD17)>=1),AND(COUNT(AP17:AT17)>=1,COUNT(AU17:AY17)>=1),AND(COUNT(AP17:AT17)>=1,COUNT(AZ17:BD17)>=1),AND(COUNT(AU17:AY17)>=1,COUNT(AZ17:BD17)>=1))), "Yes", "No") -> No | CB17: =IF(AND(BV17="",BW17="",BX17="",BY17="",BZ17="",CA17=""),"",COUNT(BV17:CA17)) | CJ17: =IF(AK17="","","Q"&INT((MONTH(AK17)-1)/3)+1&YEAR(AK17)&$V17) | CK17: =IF(AL17="","","Q"&INT((MONTH(AL17)-1)/3)+1&YEAR(AL17)&$V17) | CL17: =IF(AM17="","","Q"&INT((MONTH(AM17)-1)/3)+1&YEAR(AM17)&$V17) | CM17: =IF(AN17="","","Q"&INT((MONTH(AN17)-1)/3)+1&YEAR(AN17)&$V17) | CN17: =IF(AO17="","","Q"&INT((MONTH(AO17)-1)/3)+1&YEAR(AO17)&$V17) | CO17: =IF(AP17="","","Q"&INT((MONTH(AP17)-1)/3)+1&YEAR(AP17)&$V17) | CP17: =IF(AQ17="","","Q"&INT((MONTH(AQ17)-1)/3)+1&YEAR(AQ17)&$V17) | CQ17: =IF(AR17="","","Q"&INT((MONTH(AR17)-1)/3)+1&YEAR(AR17)&$V17) | ... DC17: =IF(BD17="","","Q"&INT((MONTH(BD17)-1)/3)+1&YEAR(BD17)&$V17) | DD17: =IF(BV17="","","Q"&INT((MONTH(BV17)-1)/3)+1&YEAR(BV17)&$V17) | DE17: =IF(BW17="","","Q"&INT((MONTH(BW17)-1)/3)+1&YEAR(BW17)&$V17) | DF17: =IF(BX17="","","Q"&INT((MONTH(BX17)-1)/3)+1&YEAR(BX17)&$V17) | DG17: =IF(BY17="","","Q"&INT((MONTH(BY17)-1)/3)+1&YEAR(BY17)&$V17) | DH17: =IF(BZ17="","","Q"&INT((MONTH(BZ17)-1)/3)+1&YEAR(BZ17)&$V17) | DI17: =IF(CA17="","","Q"&INT((MONTH(CA17)-1)/3)+1&YEAR(CA17)&$V17) | DJ17: =IF(BR17="","",IF(BR17="Yes","Q"&INT((MONTH(BK17)-1)/3)+1&YEAR(BK17)&$V17,"na")) | DK17: =IF(BU17="","",IF(BU17="Alive","Q"&INT((MONTH(BK17)-1)/3)+1&YEAR(BK17)&$V17,"na")) | DL17: =IF(BJ17="","","Q"&INT((MONTH(BJ17)-1)/3)+1&YEAR(BJ17)&$V17) | DM17: =IF(M17="","",TEXT(M17,"mmmm")&YEAR(M17)) | DN17: =IF(BE17>=4,N17&P17,"") | DO17: =IF(BK17="","",TEXT(BK17,"mmmm")&YEAR(BK17)) | DP17: =IF(AK17="","",1) | EJ17: =SUM($DP$3:DP17) -> 0 | EK17: =SUM($DP$3:DQ17) -> 0 | EL17: =SUM($DP$3:DR17) -> 0 | EM17: =SUM($DP$3:DS17) -> 0 | EN17: =SUM($DP$3:DT17) -> 0 | EO17: =SUM($DP$3:DU17) -> 0 | EP17: =SUM($DP$3:DV17) -> 0 | EQ17: =SUM($DP$3:DW17) -> 0 | ... FC17: =SUM($DP$3:EI17) -> 0
B18: BHA | L18: =IFERROR(VLOOKUP([10]!family_planning[[#This Row],[Helper]],[10]datavalidation!E:G,3,FALSE),"") | N18: =IF(mshn_database[[#This Row],[Date of Registration '[mm/dd/yy']]]="","",TEXT(mshn_database[[#This Row],[Date of Registration '[mm/dd/yy']]],"mmmm")) | O18: =IF(mshn_database[[#This Row],[Date of Registration '[mm/dd/yy']]]="","","Q"&INT((MONTH(mshn_database[[#This Row],[Date of Registration '[mm/dd/yy']]])-1)/3)+1) | P18: =IF(mshn_database[[#This Row],[Date of Registration '[mm/dd/yy']]]="","",TEXT(mshn_database[[#This Row],[Date of Registration '[mm/dd/yy']]],"yyyy")) | R18: =IF(Q18="","",C18&"-"&D18&"-"&"BHA-MCH-"&Q18) | U18: =IF(ISBLANK(T18),"", IF(T18<5,"<5 yrs", IF(AND(T18>=5,T18<=14),"5 - 14 yrs", IF(AND(T18>=15,T18<=18),"15 - 18 yrs", IF(AND(T18>=19,T18<=49),"19 - 49 yrs", IF(T18>=50,"50 yrs +","")))))) | V18: =IF(mshn_database[[#This Row],[Age_Category]]="","",VLOOKUP(mshn_database[[#This Row],[Age_Category]],[10]info!$H$2:$I$6,2,FALSE)) | AC18: =IF(AB18="","",IF(AND(TODAY()>=AB18,BU18=""),"Need LB info","No need info yet/LB info aldy included")) | BE18: =COUNT(AK18:BD18) -> 0 | BF18: =IF((OR(AND(COUNT(AK18:AO18)>=1,COUNT(AP18:AT18)>=1),AND(COUNT(AK18:AO18)>=1,COUNT(AU18:AY18)>=1),AND(COUNT(AK18:AO18)>=1,COUNT(AZ18:BD18)>=1),AND(COUNT(AP18:AT18)>=1,COUNT(AU18:AY18)>=1),AND(COUNT(AP18:AT18)>=1,COUNT(AZ18:BD18)>=1),AND(COUNT(AU18:AY18)>=1,COUNT(AZ18:BD18)>=1))), "Yes", "No") -> No | CB18: =IF(AND(BV18="",BW18="",BX18="",BY18="",BZ18="",CA18=""),"",COUNT(BV18:CA18)) | CJ18: =IF(AK18="","","Q"&INT((MONTH(AK18)-1)/3)+1&YEAR(AK18)&$V18) | CK18: =IF(AL18="","","Q"&INT((MONTH(AL18)-1)/3)+1&YEAR(AL18)&$V18) | CL18: =IF(AM18="","","Q"&INT((MONTH(AM18)-1)/3)+1&YEAR(AM18)&$V18) | CM18: =IF(AN18="","","Q"&INT((MONTH(AN18)-1)/3)+1&YEAR(AN18)&$V18) | CN18: =IF(AO18="","","Q"&INT((MONTH(AO18)-1)/3)+1&YEAR(AO18)&$V18) | CO18: =IF(AP18="","","Q"&INT((MONTH(AP18)-1)/3)+1&YEAR(AP18)&$V18) | CP18: =IF(AQ18="","","Q"&INT((MONTH(AQ18)-1)/3)+1&YEAR(AQ18)&$V18) | CQ18: =IF(AR18="","","Q"&INT((MONTH(AR18)-1)/3)+1&YEAR(AR18)&$V18) | ... DC18: =IF(BD18="","","Q"&INT((MONTH(BD18)-1)/3)+1&YEAR(BD18)&$V18) | DD18: =IF(BV18="","","Q"&INT((MONTH(BV18)-1)/3)+1&YEAR(BV18)&$V18) | DE18: =IF(BW18="","","Q"&INT((MONTH(BW18)-1)/3)+1&YEAR(BW18)&$V18) | DF18: =IF(BX18="","","Q"&INT((MONTH(BX18)-1)/3)+1&YEAR(BX18)&$V18) | DG18: =IF(BY18="","","Q"&INT((MONTH(BY18)-1)/3)+1&YEAR(BY18)&$V18) | DH18: =IF(BZ18="","","Q"&INT((MONTH(BZ18)-1)/3)+1&YEAR(BZ18)&$V18) | DI18: =IF(CA18="","","Q"&INT((MONTH(CA18)-1)/3)+1&YEAR(CA18)&$V18) | DJ18: =IF(BR18="","",IF(BR18="Yes","Q"&INT((MONTH(BK18)-1)/3)+1&YEAR(BK18)&$V18,"na")) | DK18: =IF(BU18="","",IF(BU18="Alive","Q"&INT((MONTH(BK18)-1)/3)+1&YEAR(BK18)&$V18,"na")) | DL18: =IF(BJ18="","","Q"&INT((MONTH(BJ18)-1)/3)+1&YEAR(BJ18)&$V18) | DM18: =IF(M18="","",TEXT(M18,"mmmm")&YEAR(M18)) | DN18: =IF(BE18>=4,N18&P18,"") | DO18: =IF(BK18="","",TEXT(BK18,"mmmm")&YEAR(BK18)) | DP18: =IF(AK18="","",1) | EJ18: =SUM($DP$3:DP18) -> 0 | EK18: =SUM($DP$3:DQ18) -> 0 | EL18: =SUM($DP$3:DR18) -> 0 | EM18: =SUM($DP$3:DS18) -> 0 | EN18: =SUM($DP$3:DT18) -> 0 | EO18: =SUM($DP$3:DU18) -> 0 | EP18: =SUM($DP$3:DV18) -> 0 | EQ18: =SUM($DP$3:DW18) -> 0 | ... FC18: =SUM($DP$3:EI18) -> 0
B19: BHA | L19: =IFERROR(VLOOKUP([10]!family_planning[[#This Row],[Helper]],[10]datavalidation!E:G,3,FALSE),"") | N19: =IF(mshn_database[[#This Row],[Date of Registration '[mm/dd/yy']]]="","",TEXT(mshn_database[[#This Row],[Date of Registration '[mm/dd/yy']]],"mmmm")) | O19: =IF(mshn_database[[#This Row],[Date of Registration '[mm/dd/yy']]]="","","Q"&INT((MONTH(mshn_database[[#This Row],[Date of Registration '[mm/dd/yy']]])-1)/3)+1) | P19: =IF(mshn_database[[#This Row],[Date of Registration '[mm/dd/yy']]]="","",TEXT(mshn_database[[#This Row],[Date of Registration '[mm/dd/yy']]],"yyyy")) | R19: =IF(Q19="","",C19&"-"&D19&"-"&"BHA-MCH-"&Q19) | U19: =IF(ISBLANK(T19),"", IF(T19<5,"<5 yrs", IF(AND(T19>=5,T19<=14),"5 - 14 yrs", IF(AND(T19>=15,T19<=18),"15 - 18 yrs", IF(AND(T19>=19,T19<=49),"19 - 49 yrs", IF(T19>=50,"50 yrs +","")))))) | V19: =IF(mshn_database[[#This Row],[Age_Category]]="","",VLOOKUP(mshn_database[[#This Row],[Age_Category]],[10]info!$H$2:$I$6,2,FALSE)) | AC19: =IF(AB19="","",IF(AND(TODAY()>=AB19,BU19=""),"Need LB info","No need info yet/LB info aldy included")) | BE19: =COUNT(AK19:BD19) -> 0 | BF19: =IF((OR(AND(COUNT(AK19:AO19)>=1,COUNT(AP19:AT19)>=1),AND(COUNT(AK19:AO19)>=1,COUNT(AU19:AY19)>=1),AND(COUNT(AK19:AO19)>=1,COUNT(AZ19:BD19)>=1),AND(COUNT(AP19:AT19)>=1,COUNT(AU19:AY19)>=1),AND(COUNT(AP19:AT19)>=1,COUNT(AZ19:BD19)>=1),AND(COUNT(AU19:AY19)>=1,COUNT(AZ19:BD19)>=1))), "Yes", "No") -> No | CB19: =IF(AND(BV19="",BW19="",BX19="",BY19="",BZ19="",CA19=""),"",COUNT(BV19:CA19)) | CJ19: =IF(AK19="","","Q"&INT((MONTH(AK19)-1)/3)+1&YEAR(AK19)&$V19) | CK19: =IF(AL19="","","Q"&INT((MONTH(AL19)-1)/3)+1&YEAR(AL19)&$V19) | CL19: =IF(AM19="","","Q"&INT((MONTH(AM19)-1)/3)+1&YEAR(AM19)&$V19) | CM19: =IF(AN19="","","Q"&INT((MONTH(AN19)-1)/3)+1&YEAR(AN19)&$V19) | CN19: =IF(AO19="","","Q"&INT((MONTH(AO19)-1)/3)+1&YEAR(AO19)&$V19) | CO19: =IF(AP19="","","Q"&INT((MONTH(AP19)-1)/3)+1&YEAR(AP19)&$V19) | CP19: =IF(AQ19="","","Q"&INT((MONTH(AQ19)-1)/3)+1&YEAR(AQ19)&$V19) | CQ19: =IF(AR19="","","Q"&INT((MONTH(AR19)-1)/3)+1&YEAR(AR19)&$V19) | ... DC19: =IF(BD19="","","Q"&INT((MONTH(BD19)-1)/3)+1&YEAR(BD19)&$V19) | DD19: =IF(BV19="","","Q"&INT((MONTH(BV19)-1)/3)+1&YEAR(BV19)&$V19) | DE19: =IF(BW19="","","Q"&INT((MONTH(BW19)-1)/3)+1&YEAR(BW19)&$V19) | DF19: =IF(BX19="","","Q"&INT((MONTH(BX19)-1)/3)+1&YEAR(BX19)&$V19) | DG19: =IF(BY19="","","Q"&INT((MONTH(BY19)-1)/3)+1&YEAR(BY19)&$V19) | DH19: =IF(BZ19="","","Q"&INT((MONTH(BZ19)-1)/3)+1&YEAR(BZ19)&$V19) | DI19: =IF(CA19="","","Q"&INT((MONTH(CA19)-1)/3)+1&YEAR(CA19)&$V19) | DJ19: =IF(BR19="","",IF(BR19="Yes","Q"&INT((MONTH(BK19)-1)/3)+1&YEAR(BK19)&$V19,"na")) | DK19: =IF(BU19="","",IF(BU19="Alive","Q"&INT((MONTH(BK19)-1)/3)+1&YEAR(BK19)&$V19,"na")) | DL19: =IF(BJ19="","","Q"&INT((MONTH(BJ19)-1)/3)+1&YEAR(BJ19)&$V19) | DM19: =IF(M19="","",TEXT(M19,"mmmm")&YEAR(M19)) | DN19: =IF(BE19>=4,N19&P19,"") | DO19: =IF(BK19="","",TEXT(BK19,"mmmm")&YEAR(BK19)) | DP19: =IF(AK19="","",1) | EJ19: =SUM($DP$3:DP19) -> 0 | EK19: =SUM($DP$3:DQ19) -> 0 | EL19: =SUM($DP$3:DR19) -> 0 | EM19: =SUM($DP$3:DS19) -> 0 | EN19: =SUM($DP$3:DT19) -> 0 | EO19: =SUM($DP$3:DU19) -> 0 | EP19: =SUM($DP$3:DV19) -> 0 | EQ19: =SUM($DP$3:DW19) -> 0 | ... FC19: =SUM($DP$3:EI19) -> 0
B20: BHA | L20: =IFERROR(VLOOKUP([10]!family_planning[[#This Row],[Helper]],[10]datavalidation!E:G,3,FALSE),"") | N20: =IF(mshn_database[[#This Row],[Date of Registration '[mm/dd/yy']]]="","",TEXT(mshn_database[[#This Row],[Date of Registration '[mm/dd/yy']]],"mmmm")) | O20: =IF(mshn_database[[#This Row],[Date of Registration '[mm/dd/yy']]]="","","Q"&INT((MONTH(mshn_database[[#This Row],[Date of Registration '[mm/dd/yy']]])-1)/3)+1) | P20: =IF(mshn_database[[#This Row],[Date of Registration '[mm/dd/yy']]]="","",TEXT(mshn_database[[#This Row],[Date of Registration '[mm/dd/yy']]],"yyyy")) | R20: =IF(Q20="","",C20&"-"&D20&"-"&"BHA-MCH-"&Q20) | U20: =IF(ISBLANK(T20),"", IF(T20<5,"<5 yrs", IF(AND(T20>=5,T20<=14),"5 - 14 yrs", IF(AND(T20>=15,T20<=18),"15 - 18 yrs", IF(AND(T20>=19,T20<=49),"19 - 49 yrs", IF(T20>=50,"50 yrs +","")))))) | V20: =IF(mshn_database[[#This Row],[Age_Category]]="","",VLOOKUP(mshn_database[[#This Row],[Age_Category]],[10]info!$H$2:$I$6,2,FALSE)) | AC20: =IF(AB20="","",IF(AND(TODAY()>=AB20,BU20=""),"Need LB info","No need info yet/LB info aldy included")) | BE20: =COUNT(AK20:BD20) -> 0 | BF20: =IF((OR(AND(COUNT(AK20:AO20)>=1,COUNT(AP20:AT20)>=1),AND(COUNT(AK20:AO20)>=1,COUNT(AU20:AY20)>=1),AND(COUNT(AK20:AO20)>=1,COUNT(AZ20:BD20)>=1),AND(COUNT(AP20:AT20)>=1,COUNT(AU20:AY20)>=1),AND(COUNT(AP20:AT20)>=1,COUNT(AZ20:BD20)>=1),AND(COUNT(AU20:AY20)>=1,COUNT(AZ20:BD20)>=1))), "Yes", "No") -> No | CB20: =IF(AND(BV20="",BW20="",BX20="",BY20="",BZ20="",CA20=""),"",COUNT(BV20:CA20)) | CJ20: =IF(AK20="","","Q"&INT((MONTH(AK20)-1)/3)+1&YEAR(AK20)&$V20) | CK20: =IF(AL20="","","Q"&INT((MONTH(AL20)-1)/3)+1&YEAR(AL20)&$V20) | CL20: =IF(AM20="","","Q"&INT((MONTH(AM20)-1)/3)+1&YEAR(AM20)&$V20) | CM20: =IF(AN20="","","Q"&INT((MONTH(AN20)-1)/3)+1&YEAR(AN20)&$V20) | CN20: =IF(AO20="","","Q"&INT((MONTH(AO20)-1)/3)+1&YEAR(AO20)&$V20) | CO20: =IF(AP20="","","Q"&INT((MONTH(AP20)-1)/3)+1&YEAR(AP20)&$V20) | CP20: =IF(AQ20="","","Q"&INT((MONTH(AQ20)-1)/3)+1&YEAR(AQ20)&$V20) | CQ20: =IF(AR20="","","Q"&INT((MONTH(AR20)-1)/3)+1&YEAR(AR20)&$V20) | ... DC20: =IF(BD20="","","Q"&INT((MONTH(BD20)-1)/3)+1&YEAR(BD20)&$V20) | DD20: =IF(BV20="","","Q"&INT((MONTH(BV20)-1)/3)+1&YEAR(BV20)&$V20) | DE20: =IF(BW20="","","Q"&INT((MONTH(BW20)-1)/3)+1&YEAR(BW20)&$V20) | DF20: =IF(BX20="","","Q"&INT((MONTH(BX20)-1)/3)+1&YEAR(BX20)&$V20) | DG20: =IF(BY20="","","Q"&INT((MONTH(BY20)-1)/3)+1&YEAR(BY20)&$V20) | DH20: =IF(BZ20="","","Q"&INT((MONTH(BZ20)-1)/3)+1&YEAR(BZ20)&$V20) | DI20: =IF(CA20="","","Q"&INT((MONTH(CA20)-1)/3)+1&YEAR(CA20)&$V20) | DJ20: =IF(BR20="","",IF(BR20="Yes","Q"&INT((MONTH(BK20)-1)/3)+1&YEAR(BK20)&$V20,"na")) | DK20: =IF(BU20="","",IF(BU20="Alive","Q"&INT((MONTH(BK20)-1)/3)+1&YEAR(BK20)&$V20,"na")) | DL20: =IF(BJ20="","","Q"&INT((MONTH(BJ20)-1)/3)+1&YEAR(BJ20)&$V20) | DM20: =IF(M20="","",TEXT(M20,"mmmm")&YEAR(M20)) | DN20: =IF(BE20>=4,N20&P20,"") | DO20: =IF(BK20="","",TEXT(BK20,"mmmm")&YEAR(BK20)) | DP20: =IF(AK20="","",1) | EJ20: =SUM($DP$3:DP20) -> 0 | EK20: =SUM($DP$3:DQ20) -> 0 | EL20: =SUM($DP$3:DR20) -> 0 | EM20: =SUM($DP$3:DS20) -> 0 | EN20: =SUM($DP$3:DT20) -> 0 | EO20: =SUM($DP$3:DU20) -> 0 | EP20: =SUM($DP$3:DV20) -> 0 | EQ20: =SUM($DP$3:DW20) -> 0 | ... FC20: =SUM($DP$3:EI20) -> 0
L21: =IFERROR(VLOOKUP([10]!family_planning[[#This Row],[Helper]],[10]datavalidation!E:G,3,FALSE),"") | N21: =IF(mshn_database[[#This Row],[Date of Registration '[mm/dd/yy']]]="","",TEXT(mshn_database[[#This Row],[Date of Registration '[mm/dd/yy']]],"mmmm")) | O21: =IF(mshn_database[[#This Row],[Date of Registration '[mm/dd/yy']]]="","","Q"&INT((MONTH(mshn_database[[#This Row],[Date of Registration '[mm/dd/yy']]])-1)/3)+1) | P21: =IF(mshn_database[[#This Row],[Date of Registration '[mm/dd/yy']]]="","",TEXT(mshn_database[[#This Row],[Date of Registration '[mm/dd/yy']]],"yyyy")) | R21: =IF(Q21="","",C21&"-"&D21&"-"&"BHA-MCH-"&Q21) | U21: =IF(ISBLANK(T21),"", IF(T21<5,"<5 yrs", IF(AND(T21>=5,T21<=14),"5 - 14 yrs", IF(AND(T21>=15,T21<=18),"15 - 18 yrs", IF(AND(T21>=19,T21<=49),"19 - 49 yrs", IF(T21>=50,"50 yrs +","")))))) | V21: =IF(mshn_database[[#This Row],[Age_Category]]="","",VLOOKUP(mshn_database[[#This Row],[Age_Category]],[10]info!$H$2:$I$6,2,FALSE)) | AC21: =IF(AB21="","",IF(AND(TODAY()>=AB21,BU21=""),"Need LB info","No need info yet/LB info aldy included")) | BE21: =COUNT(AK21:BD21) -> 0 | BF21: =IF((OR(AND(COUNT(AK21:AO21)>=1,COUNT(AP21:AT21)>=1),AND(COUNT(AK21:AO21)>=1,COUNT(AU21:AY21)>=1),AND(COUNT(AK21:AO21)>=1,COUNT(AZ21:BD21)>=1),AND(COUNT(AP21:AT21)>=1,COUNT(AU21:AY21)>=1),AND(COUNT(AP21:AT21)>=1,COUNT(AZ21:BD21)>=1),AND(COUNT(AU21:AY21)>=1,COUNT(AZ21:BD21)>=1))), "Yes", "No") -> No | CB21: =IF(AND(BV21="",BW21="",BX21="",BY21="",BZ21="",CA21=""),"",COUNT(BV21:CA21)) | CJ21: =IF(AK21="","","Q"&INT((MONTH(AK21)-1)/3)+1&YEAR(AK21)&$V21) | CK21: =IF(AL21="","","Q"&INT((MONTH(AL21)-1)/3)+1&YEAR(AL21)&$V21) | CL21: =IF(AM21="","","Q"&INT((MONTH(AM21)-1)/3)+1&YEAR(AM21)&$V21) | CM21: =IF(AN21="","","Q"&INT((MONTH(AN21)-1)/3)+1&YEAR(AN21)&$V21) | CN21: =IF(AO21="","","Q"&INT((MONTH(AO21)-1)/3)+1&YEAR(AO21)&$V21) | CO21: =IF(AP21="","","Q"&INT((MONTH(AP21)-1)/3)+1&YEAR(AP21)&$V21) | CP21: =IF(AQ21="","","Q"&INT((MONTH(AQ21)-1)/3)+1&YEAR(AQ21)&$V21) | CQ21: =IF(AR21="","","Q"&INT((MONTH(AR21)-1)/3)+1&YEAR(AR21)&$V21) | ... DC21: =IF(BD21="","","Q"&INT((MONTH(BD21)-1)/3)+1&YEAR(BD21)&$V21) | DD21: =IF(BV21="","","Q"&INT((MONTH(BV21)-1)/3)+1&YEAR(BV21)&$V21) | DE21: =IF(BW21="","","Q"&INT((MONTH(BW21)-1)/3)+1&YEAR(BW21)&$V21) | DF21: =IF(BX21="","","Q"&INT((MONTH(BX21)-1)/3)+1&YEAR(BX21)&$V21) | DG21: =IF(BY21="","","Q"&INT((MONTH(BY21)-1)/3)+1&YEAR(BY21)&$V21) | DH21: =IF(BZ21="","","Q"&INT((MONTH(BZ21)-1)/3)+1&YEAR(BZ21)&$V21) | DI21: =IF(CA21="","","Q"&INT((MONTH(CA21)-1)/3)+1&YEAR(CA21)&$V21) | DJ21: =IF(BR21="","",IF(BR21="Yes","Q"&INT((MONTH(BK21)-1)/3)+1&YEAR(BK21)&$V21,"na")) | DK21: =IF(BU21="","",IF(BU21="Alive","Q"&INT((MONTH(BK21)-1)/3)+1&YEAR(BK21)&$V21,"na")) | DL21: =IF(BJ21="","","Q"&INT((MONTH(BJ21)-1)/3)+1&YEAR(BJ21)&$V21) | DM21: =IF(M21="","",TEXT(M21,"mmmm")&YEAR(M21)) | DN21: =IF(BE21>=4,N21&P21,"") | DO21: =IF(BK21="","",TEXT(BK21,"mmmm")&YEAR(BK21)) | DP21: =IF(AK21="","",1) | EJ21: =SUM($DP$3:DP21) -> 0 | EK21: =SUM($DP$3:DQ21) -> 0 | EL21: =SUM($DP$3:DR21) -> 0 | EM21: =SUM($DP$3:DS21) -> 0 | EN21: =SUM($DP$3:DT21) -> 0 | EO21: =SUM($DP$3:DU21) -> 0 | EP21: =SUM($DP$3:DV21) -> 0 | EQ21: =SUM($DP$3:DW21) -> 0 | ... FC21: =SUM($DP$3:EI21) -> 0
